Workbook

Sheet ReadMe
B3: International Monetary Fund
B4: Monetary and Capital Markets Department
B10: Sovereign Debt Investor Base for Advanced Economies
B11: Regularly updated at end-April and end-October
B12: (This Version: Nov 1, 2024)
B13: Note: Data for 2023 are preliminary and subject to change. In 2019, the dataset was extended to all advanced economies with annual data going back to 1989, where feasible (see "ExtendedDataset" worksheet). The methodology follows Arslanalp and Tsuda (2014) with additional source data. For any questions, please contact Serkan Arslanalp (sarslanalp@imf.org) and Takahiro Tsuda (takahiro.tsuda@mof.go.jp).
B17: Database weblink: | C17: https://www.imf.org/~/media/Websites/IMF/imported-datasets/external/pubs/ft/wp/2012/Data/_wp12284.ashx
B19: Data Sources: | C19: Primary data sources include: Bank for International Settlements International Banking Statistics; ECB; Eurostat; IMF International Financial Statistics (IFS); IMF Coordinated Portfolio Investment Survey (CPIS); IMF Currency Composition of Official Foreign Exchange Reserves (COFER); IMF-World Bank Quarterly External Debt Statistics. Where applicable, national data sources are used.
B21: Data description | C21: The dataset provides estimates of investor holdings of general government debt of 24 advanced economies. The investor base is grouped under six classes: domestic central bank, domestic banks, domestic nonbanks, foreign official sector, foreign banks, and foreign nonbanks. All data are either in face value or adjusted for valuation changes, where appropriate, to remove price revaluations. All intra-governmental holdings are netted out. All figures are in billions of national currency. ECB data are used for the calculation of domestic central bank and domestic bank holdings of sovereign debt for eurozone countries.
B23: Sample period | C23: 1989:Q4 - 2024:Q2
B26: Authors | C26: The database was assembled by Serkan Arslanalp and Takahiro Tsuda, previously affiliated with the Monetary and Capital Markets Department of the International Monetary Fund.
B29: Published paper/reference: | C29: http://www.palgrave-journals.com/imfer/journal/v62/n3/pdf/imfer201420a.pdf
C31: Arslanalp S. and T. Tsuda, 2014, "Tracking Global Demand for Advanced Economy Sovereign Debt" IMF Economic Review, Volume 62, Number 3, Washington DC.
B32: Working paper/reference: | C32: http://www.imf.org/external/pubs/ft/wp/2012/wp12284.pdf
C33: The dataset can be quoted as "Sovereign investor base estimates by Arslanalp and Tsuda (2014)". The full reference is: Arslanalp S. and T. Tsuda, 2014, "Tracking Global Demand for Advanced Economy Sovereign Debt" IMF Economic Review, Volume 62, Number 3, Washington DC. An earlier version was published as: Serkan Arslanalp and Takahiro Tsuda (2012) "Tracking Global Demand for Advanced Economy Sovereign Debt", IMF Working Paper WP/12/284, Washington, DC.
B37: Date of last update: | C37: Nov 1, 2024.
B39: Note: | C39: Subject to changes due to data revisions.
B41: Contact information | C41: Please send your comments and queries to Serkan Arslanalp (sarslanalp@imf.org) and Takahiro Tsuda (takahiro.tsuda@mof.go.jp).
B46: Contents (all figures are presented in billions of national currency):
B47: Total General Government Gross Debt, on a consolidated basis 1/…………………………………….……………………….. | J47: Table 1
B49: General Government Gross Debt held by Foreign Investors 1/…………………………………………………………………………… | J49: Table 2
B51: General Government Gross Debt held by Foreign Official Sector 1/…………………………………………………………. | J51: Table 2.1
B52: General Government Gross Debt held by Foreign Banks…………………………………………………………………. | J52: Table 2.2
B53: General Government Gross Debt held by Foreign Nonbanks…………………………………………………………….. | J53: Table 2.3
B55: General Government Gross Debt held by Domestic Investors 1/………………………………………………………………………… | J55: Table 3
B57: General Government Gross Debt held by Domestic Central Bank……………………………………………………….. | J57: Table 3.1
B58: General Government Gross Debt held by Domestic Banks………………………………………………………………. | J58: Table 3.2
B59: General Government Gross Debt held by Domestic Nonbanks………………………………………………………….. | J59: Table 3.3
B61: 1/ For these series, estimates are also provided for general government debt securities.

Sheet ExtendedDataset
A1: Total (Billion LC) | B1: 1989 | C1: =B1+1 -> 1990 | D1: =C1+1 -> 1991 | E1: =D1+1 -> 1992 | F1: =E1+1 -> 1993 | G1: =F1+1 -> 1994 | H1: =G1+1 -> 1995 | I1: =H1+1 -> 1996 | J1: =I1+1 -> 1997 | ... AJ1: =AI1+1 -> 2023
A2: Australia | B2: 82.168 | C2: 85.056 | D2: 100.853 | E2: 121.104 | F2: 146.331 | G2: 166.042 | H2: 173.557 | I2: 166.858 | J2: 154.004 | K2: 143.471 | L2: 132.632 | M2: 115.578 | N2: 111.529 | O2: 105.476 | P2: 101.269 | Q2: ='Table 1. Total'!E2 -> 98.371 | R2: ='Table 1. Total'!I2 -> 95.67 | S2: ='Table 1. Total'!M2 -> 94.371 | T2: ='Table 1. Total'!Q2 -> 101.98 | U2: ='Table 1. Total'!U2 -> 139.455 | V2: ='Table 1. Total'!Y2 -> 197.87 | W2: ='Table 1. Total'!AC2 -> 255.388 | X2: ='Table 1. Total'!AG2 -> 327.225 | Y2: ='Table 1. Total'!AK2 -> 381.15 | Z2: ='Table 1. Total'!AO2 -> 439.698 | AA2: ='Table 1. Total'!AS2 -> 503.236 | AB2: ='Table 1. Total'!AW2 -> 559.156 | AC2: ='Table 1. Total'!BA2 -> 621.359 | AD2: ='Table 1. Total'!BE2 -> 682.677 | AE2: ='Table 1. Total'!BI2 -> 711.617 | AF2: ='Table 1. Total'!BM2 -> 811.364 | AG2: ='Table 1. Total'!BQ2 -> 1039.316 | AH2: ='Table 1. Total'!BU2 -> 1185.387 | AI2: ='Table 1. Total'!BY2 -> 1268.571 | AJ2: ='Table 1. Total'!CC2 -> 1313.062
A3: Austria | B3: 70.1 | C3: 74.1 | D3: 80 | E3: 87.8 | F3: 99.3 | G3: 111.2 | H3: 125.3 | I3: 125.2 | J3: 118.6 | K3: 125.4 | L3: 135.9 | M3: 141.543 | N3: 147.503 | O3: 151.8 | P3: 153.107 | Q3: ='Table 1. Total'!E3 -> 158.546 | R3: ='Table 1. Total'!I3 -> 175.204 | S3: ='Table 1. Total'!M3 -> 181.304 | T3: ='Table 1. Total'!Q3 -> 185.73 | U3: ='Table 1. Total'!U3 -> 202.915 | V3: ='Table 1. Total'!Y3 -> 231.173 | W3: ='Table 1. Total'!AC3 -> 245.985 | X3: ='Table 1. Total'!AG3 -> 256.876 | Y3: ='Table 1. Total'!AK3 -> 262.565 | Z3: ='Table 1. Total'!AO3 -> 264.761 | AA3: ='Table 1. Total'!AS3 -> 281.289 | AB3: ='Table 1. Total'!AW3 -> 292.874 | AC3: ='Table 1. Total'!BA3 -> 296.693 | AD3: ='Table 1. Total'!BE3 -> 290.373 | AE3: ='Table 1. Total'!BI3 -> 285.84 | AF3: ='Table 1. Total'!BM3 -> 280.975 | AG3: ='Table 1. Total'!BQ3 -> 316.36 | AH3: ='Table 1. Total'!BU3 -> 334.713 | AI3: ='Table 1. Total'!BY3 -> 351.129 | AJ3: ='Table 1. Total'!CC3 -> 371.729
A4: Belgium | B4: 186.6 | C4: 206 | D4: 219.4 | E4: 243.5 | F4: 260.9 | G4: 278.7 | H4: 288.1 | I4: 278.1 | J4: 275.6 | K4: 277.3 | L4: 279.5 | M4: 280.96 | N4: 286.055 | O4: 288.111 | P4: 285.867 | Q4: ='Table 1. Total'!E4 -> 288.419 | R4: ='Table 1. Total'!I4 -> 294.975 | S4: ='Table 1. Total'!M4 -> 297.495 | T4: ='Table 1. Total'!Q4 -> 300.064 | U4: ='Table 1. Total'!U4 -> 327.683 | V4: ='Table 1. Total'!Y4 -> 347.224 | W4: ='Table 1. Total'!AC4 -> 364.132 | X4: ='Table 1. Total'!AG4 -> 389.107 | Y4: ='Table 1. Total'!AK4 -> 404.752 | Z4: ='Table 1. Total'!AO4 -> 414.476 | AA4: ='Table 1. Total'!AS4 -> 431.464 | AB4: ='Table 1. Total'!AW4 -> 438.657 | AC4: ='Table 1. Total'!BA4 -> 451.818 | AD4: ='Table 1. Total'!BE4 -> 454.282 | AE4: ='Table 1. Total'!BI4 -> 459.669 | AF4: ='Table 1. Total'!BM4 -> 467.534 | AG4: ='Table 1. Total'!BQ4 -> 515.53 | AH4: ='Table 1. Total'!BU4 -> 548.775 | AI4: ='Table 1. Total'!BY4 -> 578.336 | AJ4: ='Table 1. Total'!CC4 -> 614.991
A5: Canada | B5: 498.232 | C5: 540.566 | D5: 596.721 | E5: 651.177 | F5: 714.637 | G5: 769.362 | H5: 809.808 | I5: 830.255 | J5: 827.563 | K5: 832.022 | L5: 847.73 | M5: 839.749 | N5: 848.993 | O5: 871.956 | P5: 868.112 | Q5: ='Table 1. Total'!E5 -> 871.456 | R5: ='Table 1. Total'!I5 -> 879.686 | S5: ='Table 1. Total'!M5 -> 896.041 | T5: ='Table 1. Total'!Q5 -> 890.993 | U5: ='Table 1. Total'!U5 -> 1012.48 | V5: ='Table 1. Total'!Y5 -> 1154.954 | W5: ='Table 1. Total'!AC5 -> 1244.007 | X5: ='Table 1. Total'!AG5 -> 1336.885 | Y5: ='Table 1. Total'!AK5 -> 1427.99 | Z5: ='Table 1. Total'!AO5 -> 1508.667 | AA5: ='Table 1. Total'!AS5 -> 1531.127 | AB5: ='Table 1. Total'!AW5 -> 1635.591 | AC5: ='Table 1. Total'!BA5 -> 1674.636 | AD5: ='Table 1. Total'!BE5 -> 1743.514 | AE5: ='Table 1. Total'!BI5 -> 1813.879 | AF5: ='Table 1. Total'!BM5 -> 1882.054 | AG5: ='Table 1. Total'!BQ5 -> 2354.228 | AH5: ='Table 1. Total'!BU5 -> 2548.598 | AI5: ='Table 1. Total'!BY5 -> 2629.466 | AJ5: ='Table 1. Total'!CC5 -> 2753.325
A6: Czech Republic | B6: … | C6: … | D6: … | E6: … | F6: … | G6: … | H6: 216.6 | I6: 211.8 | J6: 240.3 | K6: 301 | L6: 342.1 | M6: 405.418 | N6: 585.615 | O6: 695.133 | P6: 795.04 | Q6: ='Table 1. Total'!E6 -> 873.493 | R6: ='Table 1. Total'!I6 -> 910.183 | S6: ='Table 1. Total'!M6 -> 973.107 | T6: ='Table 1. Total'!Q6 -> 1054.633 | U6: ='Table 1. Total'!U6 -> 1136.774 | V6: ='Table 1. Total'!Y6 -> 1319.002 | W6: ='Table 1. Total'!AC6 -> 1480.097 | X6: ='Table 1. Total'!AG6 -> 1613.65 | Y6: ='Table 1. Total'!AK6 -> 1805.307 | Z6: ='Table 1. Total'!AO6 -> 1840.247 | AA6: ='Table 1. Total'!AS6 -> 1818.888 | AB6: ='Table 1. Total'!AW6 -> 1836.047 | AC6: ='Table 1. Total'!BA6 -> 1754.737 | AD6: ='Table 1. Total'!BE6 -> 1749.677 | AE6: ='Table 1. Total'!BI6 -> 1734.602 | AF6: ='Table 1. Total'!BM6 -> 1740.263 | AG6: ='Table 1. Total'!BQ6 -> 2149.655 | AH6: ='Table 1. Total'!BU6 -> 2566.752 | AI6: ='Table 1. Total'!BY6 -> 2997.632 | AJ6: ='Table 1. Total'!CC6 -> 3234.002
A7: Denmark | B7: 511.4 | C7: 533.9 | D7: 562.7 | E7: 631.4 | F7: 747.9 | G7: 765.6 | H7: 758 | I7: 760.8 | J7: 754.7 | K7: 732.4 | L7: 722 | M7: 710.098 | N7: 687.462 | O7: 710.254 | P7: 693.004 | Q7: ='Table 1. Total'!E7 -> 697.698 | R7: ='Table 1. Total'!I7 -> 625.854 | S7: ='Table 1. Total'!M7 -> 559.349 | T7: ='Table 1. Total'!Q7 -> 513.925 | U7: ='Table 1. Total'!U7 -> 643.16 | V7: ='Table 1. Total'!Y7 -> 744.541 | W7: ='Table 1. Total'!AC7 -> 836.167 | X7: ='Table 1. Total'!AG7 -> 924.011 | Y7: ='Table 1. Total'!AK7 -> 922.073 | Z7: ='Table 1. Total'!AO7 -> 924.613 | AA7: ='Table 1. Total'!AS7 -> 964.634 | AB7: ='Table 1. Total'!AW7 -> 904.464 | AC7: ='Table 1. Total'!BA7 -> 876.165 | AD7: ='Table 1. Total'!BE7 -> 879.176 | AE7: ='Table 1. Total'!BI7 -> 864.633 | AF7: ='Table 1. Total'!BM7 -> 883.091 | AG7: ='Table 1. Total'!BQ7 -> 1076.709 | AH7: ='Table 1. Total'!BU7 -> 1039.517 | AI7: ='Table 1. Total'!BY7 -> 969.223 | AJ7: ='Table 1. Total'!CC7 -> 942.073
A8: Finland | B8: 15 | C8: 15.1 | D8: 20.4 | E8: 31.2 | F8: 42.7 | G8: 52 | H8: 56.5 | I8: 57.7 | J8: 57.5 | K8: 56.4 | L8: 55.9 | M8: 61.564 | N8: 62.825 | O8: 63.299 | P8: 68.508 | Q8: ='Table 1. Total'!E8 -> 71.335 | R8: ='Table 1. Total'!I8 -> 69.397 | S8: ='Table 1. Total'!M8 -> 69.532 | T8: ='Table 1. Total'!Q8 -> 67.34 | U8: ='Table 1. Total'!U8 -> 67.435 | V8: ='Table 1. Total'!Y8 -> 80.2 | W8: ='Table 1. Total'!AC8 -> 94.286 | X8: ='Table 1. Total'!AG8 -> 102.829 | Y8: ='Table 1. Total'!AK8 -> 115.931 | Z8: ='Table 1. Total'!AO8 -> 123.75 | AA8: ='Table 1. Total'!AS8 -> 133.42 | AB8: ='Table 1. Total'!AW8 -> 144.537 | AC8: ='Table 1. Total'!BA8 -> 148.088 | AD8: ='Table 1. Total'!BE8 -> 149.611 | AE8: ='Table 1. Total'!BI8 -> 151.569 | AF8: ='Table 1. Total'!BM8 -> 155.827 | AG8: ='Table 1. Total'!BQ8 -> 178.148 | AH8: ='Table 1. Total'!BU8 -> 182.213 | AI8: ='Table 1. Total'!BY8 -> 197.022 | AJ8: ='Table 1. Total'!CC8 -> 210.866
A9: France | B9: 334.1 | C9: 362.9 | D9: 384.2 | E9: 457.8 | F9: 543.5 | G9: 601.3 | H9: 714.7 | I9: 755.3 | J9: 793 | K9: 836.1 | L9: 856.9 | M9: 880.005 | N9: 907.673 | O9: 966.823 | P9: 1060.406 | Q9: ='Table 1. Total'!E9 -> 1134.347 | R9: ='Table 1. Total'!I9 -> 1201.471 | S9: ='Table 1. Total'!M9 -> 1207.313 | T9: ='Table 1. Total'!Q9 -> 1268.859 | U9: ='Table 1. Total'!U9 -> 1389.402 | V9: ='Table 1. Total'!Y9 -> 1627.182 | W9: ='Table 1. Total'!AC9 -> 1722.172 | X9: ='Table 1. Total'!AG9 -> 1830.136 | Y9: ='Table 1. Total'!AK9 -> 1915.835 | Z9: ='Table 1. Total'!AO9 -> 2004.704 | AA9: ='Table 1. Total'!AS9 -> 2070.579 | AB9: ='Table 1. Total'!AW9 -> 2134.071 | AC9: ='Table 1. Total'!BA9 -> 2190.007 | AD9: ='Table 1. Total'!BE9 -> 2262.443 | AE9: ='Table 1. Total'!BI9 -> 2319.775 | AF9: ='Table 1. Total'!BM9 -> 2386.133 | AG9: ='Table 1. Total'!BQ9 -> 2662.105 | AH9: ='Table 1. Total'!BU9 -> 2826.726 | AI9: ='Table 1. Total'!BY9 -> 2953.624 | AJ9: ='Table 1. Total'!CC9 -> 3101.376
A10: Germany | B10: 464.9 | C10: 527.5 | D10: 590.1 | E10: 701.1 | F10: 794.2 | G10: 888.2 | H10: 1079.9 | I10: 1115.7 | J10: 1142.5 | K10: 1199.3 | L10: 1243.7 | M10: 1261.585 | N10: 1274.759 | O10: 1330.083 | P10: 1419.426 | Q10: ='Table 1. Total'!E10 -> 1489.671 | R10: ='Table 1. Total'!I10 -> 1561.021 | S10: ='Table 1. Total'!M10 -> 1610.904 | T10: ='Table 1. Total'!Q10 -> 1619.065 | U10: ='Table 1. Total'!U10 -> 1687.442 | V10: ='Table 1. Total'!Y10 -> 1804.696 | W10: ='Table 1. Total'!AC10 -> 2119.242 | X10: ='Table 1. Total'!AG10 -> 2155.876 | Y10: ='Table 1. Total'!AK10 -> 2234.803 | Z10: ='Table 1. Total'!AO10 -> 2220.281 | AA10: ='Table 1. Total'!AS10 -> 2224.56 | AB10: ='Table 1. Total'!AW10 -> 2197.474 | AC10: ='Table 1. Total'!BA10 -> 2182.375 | AD10: ='Table 1. Total'!BE10 -> 2132.784 | AE10: ='Table 1. Total'!BI10 -> 2086.445 | AF10: ='Table 1. Total'!BM10 -> 2075.012 | AG10: ='Table 1. Total'!BQ10 -> 2346.955 | AH10: ='Table 1. Total'!BU10 -> 2502.817 | AI10: ='Table 1. Total'!BY10 -> 2569.897 | AJ10: ='Table 1. Total'!CC10 -> 2631.777
A11: Greece | B11: 44.8 | C11: 52.5 | D11: 61 | E11: 68.1 | F11: 90 | G11: 94.1 | H11: 100.8 | I11: 115 | J11: 124.6 | K11: 126.1 | L11: 136.5 | M11: 148.217 | N11: 162.971 | O11: 171.41 | P11: 181.51 | Q11: ='Table 1. Total'!E11 -> 199.282 | R11: ='Table 1. Total'!I11 -> 213.976 | S11: ='Table 1. Total'!M11 -> 225.73 | T11: ='Table 1. Total'!Q11 -> 239.915 | U11: ='Table 1. Total'!U11 -> 264.775 | V11: ='Table 1. Total'!Y11 -> 301.062 | W11: ='Table 1. Total'!AC11 -> 330.57 | X11: ='Table 1. Total'!AG11 -> 356.235 | Y11: ='Table 1. Total'!AK11 -> 305.085 | Z11: ='Table 1. Total'!AO11 -> 321.257 | AA11: ='Table 1. Total'!AS11 -> 321.631 | AB11: ='Table 1. Total'!AW11 -> 314.987 | AC11: ='Table 1. Total'!BA11 -> 319.425 | AD11: ='Table 1. Total'!BE11 -> 323.004 | AE11: ='Table 1. Total'!BI11 -> 341.416 | AF11: ='Table 1. Total'!BM11 -> 339.201 | AG11: ='Table 1. Total'!BQ11 -> 350.798 | AH11: ='Table 1. Total'!BU11 -> 364.141 | AI11: ='Table 1. Total'!BY11 -> 368.005 | AJ11: ='Table 1. Total'!CC11 -> 369.099
A12: Ireland | B12: 34.8 | C12: 35.1 | D12: 37 | E12: 39.3 | F12: 41 | G12: 41.3 | H12: 41.3 | I12: 44.4 | J12: 43.6 | K12: 41.4 | L12: 43.2 | M12: 39.506 | N12: 40.995 | O12: 42.009 | P12: 43.429 | Q12: ='Table 1. Total'!E12 -> 43.914 | R12: ='Table 1. Total'!I12 -> 44.381 | S12: ='Table 1. Total'!M12 -> 43.739 | T12: ='Table 1. Total'!Q12 -> 47.195 | U12: ='Table 1. Total'!U12 -> 79.621 | V12: ='Table 1. Total'!Y12 -> 104.703 | W12: ='Table 1. Total'!AC12 -> 144.23 | X12: ='Table 1. Total'!AG12 -> 189.727 | Y12: ='Table 1. Total'!AK12 -> 210.026 | Z12: ='Table 1. Total'!AO12 -> 215.242 | AA12: ='Table 1. Total'!AS12 -> 203.381 | AB12: ='Table 1. Total'!AW12 -> 201.578 | AC12: ='Table 1. Total'!BA12 -> 200.635 | AD12: ='Table 1. Total'!BE12 -> 201.262 | AE12: ='Table 1. Total'!BI12 -> 205.848 | AF12: ='Table 1. Total'!BM12 -> 203.383 | AG12: ='Table 1. Total'!BQ12 -> 217.885 | AH12: ='Table 1. Total'!BU12 -> 236.127 | AI12: ='Table 1. Total'!BY12 -> 224.78 | AJ12: ='Table 1. Total'!CC12 -> 220.724
A13: Italy | B13: 754.9 | C13: 839.6 | D13: 947.8 | E13: 920.7 | F13: 972.9 | G13: 1036.7 | H13: 1096.6 | I13: 1260.4 | J13: 1271.9 | K13: 1299.7 | L13: 1331.3 | M13: 1353.569 | N13: 1420.027 | O13: 1436.142 | P13: 1471.326 | Q13: ='Table 1. Total'!E13 -> 1526.461 | R13: ='Table 1. Total'!I13 -> 1591.65 | S13: ='Table 1. Total'!M13 -> 1657.403 | T13: ='Table 1. Total'!Q13 -> 1677.725 | U13: ='Table 1. Total'!U13 -> 1738.851 | V13: ='Table 1. Total'!Y13 -> 1839.486 | W13: ='Table 1. Total'!AC13 -> 1921.1 | X13: ='Table 1. Total'!AG13 -> 1974.013 | Y13: ='Table 1. Total'!AK13 -> 2055.338 | Z13: ='Table 1. Total'!AO13 -> 2137.088 | AA13: ='Table 1. Total'!AS13 -> 2204.424 | AB13: ='Table 1. Total'!AW13 -> 2241.195 | AC13: ='Table 1. Total'!BA13 -> 2287.84 | AD13: ='Table 1. Total'!BE13 -> 2332.197 | AE13: ='Table 1. Total'!BI13 -> 2384.631 | AF13: ='Table 1. Total'!BM13 -> 2414.252 | AG13: ='Table 1. Total'!BQ13 -> 2576.629 | AH13: ='Table 1. Total'!BU13 -> 2685.173 | AI13: ='Table 1. Total'!BY13 -> 2762.908 | AJ13: ='Table 1. Total'!CC13 -> 2868.411
A14: Japan | B14: 222324.72 | C14: 230176.01 | D14: 241918.18 | E14: 265620.8 | F14: 289970.72 | G14: 336374.8 | H14: 387861.96 | I14: 419213.54 | J14: 449640.98 | K14: 499769.22 | L14: 560978.82 | M14: 614161.3 | N14: 647986.66 | O14: 667570.32 | P14: 717925.66 | Q14: ='Table 1. Total'!E14 -> 761502.46 | R14: ='Table 1. Total'!I14 -> 776591.23 | S14: ='Table 1. Total'!M14 -> 770922.57 | T14: ='Table 1. Total'!Q14 -> 766182.23 | U14: ='Table 1. Total'!U14 -> 765795.46 | V14: ='Table 1. Total'!Y14 -> 813270.64 | W14: ='Table 1. Total'!AC14 -> 863420.39 | X14: ='Table 1. Total'!AG14 -> 910512.03 | Y14: ='Table 1. Total'!AK14 -> 950146.14 | Z14: ='Table 1. Total'!AO14 -> 988964.92 | AA14: ='Table 1. Total'!AS14 -> 1029614 | AB14: ='Table 1. Total'!AW14 -> 1052524.6 | AC14: ='Table 1. Total'!BA14 -> 1079840.1 | AD14: ='Table 1. Total'!BE14 -> 1101997.4 | AE14: ='Table 1. Total'!BI14 -> 1115855 | AF14: ='Table 1. Total'!BM14 -> 1134597.1 | AG14: ='Table 1. Total'!BQ14 -> 1220382.9 | AH14: ='Table 1. Total'!BU14 -> 1220737.8 | AI14: ='Table 1. Total'!BY14 -> 1271760.7 | AJ14: ='Table 1. Total'!CC14 -> 1297630.5
A15: Korea | B15: … | C15: … | D15: … | E15: … | F15: … | G15: 26705.25 | H15: 26913.496 | I15: 27569.593 | J15: 45715.571 | K15: 62287.498 | L15: 76887.736 | M15: 85414.821 | N15: 92944.294 | O15: 96002.275 | P15: 110663.67 | Q15: ='Table 1. Total'!E15 -> 144708.15 | R15: ='Table 1. Total'!I15 -> 180193.7 | S15: ='Table 1. Total'!M15 -> 219155.53 | T15: ='Table 1. Total'!Q15 -> 233924.3 | U15: ='Table 1. Total'!U15 -> 264086.6 | V15: ='Table 1. Total'!Y15 -> 305920.5 | W15: ='Table 1. Total'!AC15 -> 361300.3 | X15: ='Table 1. Total'!AG15 -> 408061.1 | Y15: ='Table 1. Total'!AK15 -> 459960.7 | Z15: ='Table 1. Total'!AO15 -> 503735 | AA15: ='Table 1. Total'!AS15 -> 567910.7 | AB15: ='Table 1. Total'!AW15 -> 629971.2 | AC15: ='Table 1. Total'!BA15 -> 656429.4 | AD15: ='Table 1. Total'!BE15 -> 659289.6 | AE15: ='Table 1. Total'!BI15 -> 696487.2 | AF15: ='Table 1. Total'!BM15 -> 756759.7 | AG15: ='Table 1. Total'!BQ15 -> 866222.8 | AH15: ='Table 1. Total'!BU15 -> 945734.6 | AI15: ='Table 1. Total'!BY15 -> 963399.8 | AJ15: ='Table 1. Total'!CC15 -> 1056770.1
A16: Netherlands | B16: 176.7 | C16: 185.9 | D16: 196.6 | E16: 216.1 | F16: 228.8 | G16: 235.5 | H16: 251.9 | I16: 248.2 | J16: 240.3 | K16: 247.5 | L16: 246.2 | M16: 236.233 | N16: 239.037 | O16: 245.253 | P16: 256.822 | Q16: ='Table 1. Total'!E16 -> 266.661 | R16: ='Table 1. Total'!I16 -> 274.598 | S16: ='Table 1. Total'!M16 -> 264.472 | T16: ='Table 1. Total'!Q16 -> 266.545 | U16: ='Table 1. Total'!U16 -> 353.866 | V16: ='Table 1. Total'!Y16 -> 355.057 | W16: ='Table 1. Total'!AC16 -> 379.043 | X16: ='Table 1. Total'!AG16 -> 401.579 | Y16: ='Table 1. Total'!AK16 -> 432.723 | Z16: ='Table 1. Total'!AO16 -> 447.221 | AA16: ='Table 1. Total'!AS16 -> 455.93 | AB16: ='Table 1. Total'!AW16 -> 446.049 | AC16: ='Table 1. Total'!BA16 -> 438.204 | AD16: ='Table 1. Total'!BE16 -> 420.09 | AE16: ='Table 1. Total'!BI16 -> 405.617 | AF16: ='Table 1. Total'!BM16 -> 394.948 | AG16: ='Table 1. Total'!BQ16 -> 435.565 | AH16: ='Table 1. Total'!BU16 -> 449.62 | AI16: ='Table 1. Total'!BY16 -> 480.465 | AJ16: ='Table 1. Total'!CC16 -> 481.468
A17: New Zealand | B17: 22.644 | C17: 22.481 | D17: 24.324 | E17: 26.28 | F17: 28.672 | G17: 30.355 | H17: 31.322 | I17: 32.067 | J17: 30.825 | K17: 32.279 | L17: 33.07 | M17: 33.437 | N17: 34.408 | O17: 35.961 | P17: 37.472 | Q17: ='Table 1. Total'!E17 -> 35.442 | R17: ='Table 1. Total'!I17 -> 35.192 | S17: ='Table 1. Total'!M17 -> 29.599 | T17: ='Table 1. Total'!Q17 -> 31.035 | U17: ='Table 1. Total'!U17 -> 32.004 | V17: ='Table 1. Total'!Y17 -> 43.218 | W17: ='Table 1. Total'!AC17 -> 52.327 | X17: ='Table 1. Total'!AG17 -> 70.758 | Y17: ='Table 1. Total'!AK17 -> 79.069 | Z17: ='Table 1. Total'!AO17 -> 78.522 | AA17: ='Table 1. Total'!AS17 -> 82.347 | AB17: ='Table 1. Total'!AW17 -> 82.041 | AC17: ='Table 1. Total'!BA17 -> 84.199 | AD17: ='Table 1. Total'!BE17 -> 81.886 | AE17: ='Table 1. Total'!BI17 -> 89.994 | AF17: ='Table 1. Total'!BM17 -> 88.575 | AG17: ='Table 1. Total'!BQ17 -> 145.195 | AH17: ='Table 1. Total'!BU17 -> 165.956 | AI17: ='Table 1. Total'!BY17 -> 179.674 | AJ17: ='Table 1. Total'!CC17 -> 192.36
A18: Norway | B18: 229.16 | C18: 217.042 | D18: 310.044 | E18: 365.853 | F18: 458.937 | G18: 454.394 | H18: 315.311 | I18: 300.011 | J18: 293.974 | K18: 274.325 | L18: 316.103 | M18: 430.505 | N18: 424.568 | O18: 527.258 | P18: 677.804 | Q18: ='Table 1. Total'!E18 -> 768.099 | R18: ='Table 1. Total'!I18 -> 830.362 | S18: ='Table 1. Total'!M18 -> 1161.579 | T18: ='Table 1. Total'!Q18 -> 1164.455 | U18: ='Table 1. Total'!U18 -> 1233.543 | V18: ='Table 1. Total'!Y18 -> 1027.885 | W18: ='Table 1. Total'!AC18 -> 1108.379 | X18: ='Table 1. Total'!AG18 -> 810.594 | Y18: ='Table 1. Total'!AK18 -> 892.884 | Z18: ='Table 1. Total'!AO18 -> 948.621 | AA18: ='Table 1. Total'!AS18 -> 899.989 | AB18: ='Table 1. Total'!AW18 -> 1038.987 | AC18: ='Table 1. Total'!BA18 -> 1152.857 | AD18: ='Table 1. Total'!BE18 -> 1246.467 | AE18: ='Table 1. Total'!BI18 -> 1389.998 | AF18: ='Table 1. Total'!BM18 -> 1434.891 | AG18: ='Table 1. Total'!BQ18 -> 1563.851 | AH18: ='Table 1. Total'!BU18 -> 1787.432 | AI18: ='Table 1. Total'!BY18 -> 2083.819 | AJ18: ='Table 1. Total'!CC18 -> 2271.031
A19: Portugal | B19: 29.1 | C19: 34.6 | D19: 42.1 | E19: 43.1 | F19: 44.4 | G19: 50.8 | H19: 56.5 | I19: 61.1 | J19: 59.6 | K19: 61.9 | L19: 66.3 | M19: 69.592 | N19: 77.908 | O19: 85.527 | P19: 93.321 | Q19: ='Table 1. Total'!E19 -> 102.155 | R19: ='Table 1. Total'!I19 -> 114.543 | S19: ='Table 1. Total'!M19 -> 122.467 | T19: ='Table 1. Total'!Q19 -> 127.571 | U19: ='Table 1. Total'!U19 -> 135.209 | V19: ='Table 1. Total'!Y19 -> 153.624 | W19: ='Table 1. Total'!AC19 -> 179.653 | X19: ='Table 1. Total'!AG19 -> 201.044 | Y19: ='Table 1. Total'!AK19 -> 216.747 | Z19: ='Table 1. Total'!AO19 -> 223.313 | AA19: ='Table 1. Total'!AS19 -> 229.391 | AB19: ='Table 1. Total'!AW19 -> 235.046 | AC19: ='Table 1. Total'!BA19 -> 244.495 | AD19: ='Table 1. Total'!BE19 -> 246.399 | AE19: ='Table 1. Total'!BI19 -> 248.277 | AF19: ='Table 1. Total'!BM19 -> 249.044 | AG19: ='Table 1. Total'!BQ19 -> 269.578 | AH19: ='Table 1. Total'!BU19 -> 268.189 | AI19: ='Table 1. Total'!BY19 -> 271.358 | AJ19: ='Table 1. Total'!CC19 -> 261.849
A20: Slovenia | B20: … | C20: … | D20: … | E20: … | F20: … | G20: … | H20: 2.788 | I20: 3.54 | J20: 3.915 | K20: 4.429 | L20: 4.921 | M20: 5.484 | N20: 6.036 | O20: 6.708 | P20: 6.944 | Q20: ='Table 1. Total'!E20 -> 7.428 | R20: ='Table 1. Total'!I20 -> 7.69 | S20: ='Table 1. Total'!M20 -> 8.202 | T20: ='Table 1. Total'!Q20 -> 8.016 | U20: ='Table 1. Total'!U20 -> 8.263 | V20: ='Table 1. Total'!Y20 -> 12.519 | W20: ='Table 1. Total'!AC20 -> 13.918 | X20: ='Table 1. Total'!AG20 -> 17.22 | Y20: ='Table 1. Total'!AK20 -> 19.431 | Z20: ='Table 1. Total'!AO20 -> 25.53 | AA20: ='Table 1. Total'!AS20 -> 30.239 | AB20: ='Table 1. Total'!AW20 -> 32.111 | AC20: ='Table 1. Total'!BA20 -> 31.783 | AD20: ='Table 1. Total'!BE20 -> 31.922 | AE20: ='Table 1. Total'!BI20 -> 32.281 | AF20: ='Table 1. Total'!BM20 -> 31.793 | AG20: ='Table 1. Total'!BQ20 -> 37.47 | AH20: ='Table 1. Total'!BU20 -> 38.93 | AI20: ='Table 1. Total'!BY20 -> 41.395 | AJ20: ='Table 1. Total'!CC20 -> 43.739
A21: Spain | B21: 148.8 | C21: 173.6 | D21: 195.2 | E21: 207.7 | F21: 233.7 | G21: 255.1 | H21: 295.6 | I21: 324.3 | J21: 331.6 | K21: 346.4 | L21: 362.2 | M21: 374.557 | N21: 378.883 | O21: 384.145 | P21: 382.775 | Q21: ='Table 1. Total'!E21 -> 389.888 | R21: ='Table 1. Total'!I21 -> 393.479 | S21: ='Table 1. Total'!M21 -> 392.132 | T21: ='Table 1. Total'!Q21 -> 384.662 | U21: ='Table 1. Total'!U21 -> 440.621 | V21: ='Table 1. Total'!Y21 -> 569.535 | W21: ='Table 1. Total'!AC21 -> 649.153 | X21: ='Table 1. Total'!AG21 -> 743.043 | Y21: ='Table 1. Total'!AK21 -> 927.813 | Z21: ='Table 1. Total'!AO21 -> 1025.805 | AA21: ='Table 1. Total'!AS21 -> 1085.165 | AB21: ='Table 1. Total'!AW21 -> 1114.129 | AC21: ='Table 1. Total'!BA21 -> 1145.655 | AD21: ='Table 1. Total'!BE21 -> 1184.148 | AE21: ='Table 1. Total'!BI21 -> 1209.742 | AF21: ='Table 1. Total'!BM21 -> 1224.364 | AG21: ='Table 1. Total'!BQ21 -> 1346.916 | AH21: ='Table 1. Total'!BU21 -> 1429.404 | AI21: ='Table 1. Total'!BY21 -> 1504.105 | AJ21: ='Table 1. Total'!CC21 -> 1575.374
A22: Sweden | B22: 561.3 | C22: 593.3 | D22: 763.4 | E22: 962.4 | F22: 1094.2 | G22: 1208.8 | H22: 1310 | I22: 1357.071 | J22: 1370.729 | K22: 1424.195 | L22: 1376.76 | M22: 1214.95 | N22: 1302.144 | O22: 1297.554 | P22: 1335.709 | Q22: ='Table 1. Total'!E22 -> 1375.293 | R22: ='Table 1. Total'!I22 -> 1431.293 | S22: ='Table 1. Total'!M22 -> 1366.719 | T22: ='Table 1. Total'!Q22 -> 1298.322 | U22: ='Table 1. Total'!U22 -> 1287.298 | V22: ='Table 1. Total'!Y22 -> 1369.295 | W22: ='Table 1. Total'!AC22 -> 1370.64 | X22: ='Table 1. Total'!AG22 -> 1395.605 | Y22: ='Table 1. Total'!AK22 -> 1415.032 | Z22: ='Table 1. Total'!AO22 -> 1551.553 | AA22: ='Table 1. Total'!AS22 -> 1810.859 | AB22: ='Table 1. Total'!AW22 -> 1881.274 | AC22: ='Table 1. Total'!BA22 -> 1883.772 | AD22: ='Table 1. Total'!BE22 -> 1904.584 | AE22: ='Table 1. Total'!BI22 -> 1907.798 | AF22: ='Table 1. Total'!BM22 -> 1796.655 | AG22: ='Table 1. Total'!BQ22 -> 2015.37 | AH22: ='Table 1. Total'!BU22 -> 2004.815 | AI22: ='Table 1. Total'!BY22 -> 1972.413 | AJ22: ='Table 1. Total'!CC22 -> 1954.397
A23: Switzerland | B23: 83.924 | C23: 95.947 | D23: 107.97 | E23: 127.546 | F23: 148.355 | G23: 161.016 | H23: 171.837 | I23: 180.653 | J23: 192.965 | K23: 207.645 | L23: 200.179 | M23: 205.838 | N23: 205.43 | O23: 221.778 | P23: 226.28 | Q23: ='Table 1. Total'!E23 -> 229.685 | R23: ='Table 1. Total'!I23 -> 226.061 | S23: ='Table 1. Total'!M23 -> 211.955 | T23: ='Table 1. Total'!Q23 -> 201.843 | U23: ='Table 1. Total'!U23 -> 197.241 | V23: ='Table 1. Total'!Y23 -> 184.879 | W23: ='Table 1. Total'!AC23 -> 182.414 | X23: ='Table 1. Total'!AG23 -> 181.288 | Y23: ='Table 1. Total'!AK23 -> 188.025 | Z23: ='Table 1. Total'!AO23 -> 190.767 | AA23: ='Table 1. Total'!AS23 -> 195.129 | AB23: ='Table 1. Total'!AW23 -> 192.448 | AC23: ='Table 1. Total'!BA23 -> 187.807 | AD23: ='Table 1. Total'!BE23 -> 192.077 | AE23: ='Table 1. Total'!BI23 -> 185.45 | AF23: ='Table 1. Total'!BM23 -> 186.712 | AG23: ='Table 1. Total'!BQ23 -> 197.457 | AH23: ='Table 1. Total'!BU23 -> 200.354 | AI23: ='Table 1. Total'!BY23 -> 193.208 | AJ23: ='Table 1. Total'!CC23 -> 200.103
A24: United Kingdom | B24: 193.217 | C24: 189.581 | D24: 202.744 | E24: 248.331 | F24: 324.232 | G24: 330.02 | H24: 383.823 | I24: 407.117 | J24: 420.757 | K24: 419.066 | L24: 421.574 | M24: 414.826 | N24: 400.663 | O24: 422.18 | P24: 462.61 | Q24: ='Table 1. Total'!E24 -> 526.43 | R24: ='Table 1. Total'!I24 -> 573.493 | S24: ='Table 1. Total'!M24 -> 619.114 | T24: ='Table 1. Total'!Q24 -> 666.88 | U24: ='Table 1. Total'!U24 -> 809.985 | V24: ='Table 1. Total'!Y24 -> 1005.405 | W24: ='Table 1. Total'!AC24 -> 1220.252 | X24: ='Table 1. Total'!AG24 -> 1353.765 | Y24: ='Table 1. Total'!AK24 -> 1447.791 | Z24: ='Table 1. Total'!AO24 -> 1519.787 | AA24: ='Table 1. Total'!AS24 -> 1622.144 | AB24: ='Table 1. Total'!AW24 -> 1683.922 | AC24: ='Table 1. Total'!BA24 -> 1749.166 | AD24: ='Table 1. Total'!BE24 -> 1805.987 | AE24: ='Table 1. Total'!BI24 -> 1858.41 | AF24: ='Table 1. Total'!BM24 -> 1913.514 | AG24: ='Table 1. Total'!BQ24 -> 2226.332 | AH24: ='Table 1. Total'!BU24 -> 2402.766 | AI24: ='Table 1. Total'!BY24 -> 2516.819 | AJ24: ='Table 1. Total'!CC24 -> 2720.877
A25: United States | B25: 3117.515 | C25: 3402.66 | D25: 3785.078 | E25: 4164.195 | F25: 4514.972 | G25: 4713.119 | H25: 4910.113 | I25: 5119.515 | J25: 5247.668 | K25: 5259.565 | L25: 5244.22 | M25: 4981.406 | N25: 5123.519 | O25: 5523.241 | P25: 6046.996 | Q25: ='Table 1. Total'!E25 -> 7341.928 | R25: ='Table 1. Total'!I25 -> 7709.545 | S25: ='Table 1. Total'!M25 -> 7981.395 | T25: ='Table 1. Total'!Q25 -> 8348.06 | U25: ='Table 1. Total'!U25 -> 9758.877 | V25: ='Table 1. Total'!Y25 -> 11397.29 | W25: ='Table 1. Total'!AC25 -> 13109.307 | X25: ='Table 1. Total'!AG25 -> 14243.031 | Y25: ='Table 1. Total'!AK25 -> 15409.728 | Z25: ='Table 1. Total'!AO25 -> 16205.501 | AA25: ='Table 1. Total'!AS25 -> 16902.619 | AB25: ='Table 1. Total'!AW25 -> 17634.537 | AC25: ='Table 1. Total'!BA25 -> 18445.034 | AD25: ='Table 1. Total'!BE25 -> 19024.482 | AE25: ='Table 1. Total'!BI25 -> 20264.329 | AF25: ='Table 1. Total'!BM25 -> 21357.612 | AG25: ='Table 1. Total'!BQ25 -> 25710.881 | AH25: ='Table 1. Total'!BU25 -> 27130.289 | AI25: ='Table 1. Total'!BY25 -> 28499.037 | AJ25: ='Table 1. Total'!CC25 -> 31022.747
A26: Cyprus | B26: … | C26: … | D26: … | E26: … | F26: … | G26: … | H26: 3.732 | I26: 4.045 | J26: 4.633 | K26: 5.141 | L26: 5.583 | M26: 6.103 | N26: 6.746 | O26: 7.431 | P26: 8.281 | Q26: 9.16 | R26: 9.698 | S26: 9.717 | T26: 9.593 | U26: 8.8 | V26: 10.616 | W26: 11.543 | X26: 13.728 | Y26: 16.3 | Z26: 19.394 | AA26: 19.706 | AB26: 20.025 | AC26: 20.33 | AD26: 19.597 | AE26: 21.965 | AF26: 21.598 | AG26: 25.417 | AH26: 24.776 | AI26: 23.813 | AJ26: 23.076
A27: Estonia | B27: … | C27: … | D27: … | E27: … | F27: … | G27: … | H27: 0.236 | I27: 0.277 | J27: 0.311 | K27: 0.302 | L27: 0.348 | M27: 0.316 | N27: 0.344 | O27: 0.443 | P27: 0.49 | Q27: 0.505 | R27: 0.537 | S27: 0.64 | T27: 0.641 | U27: 0.777 | V27: 1.127 | W27: 1.178 | X27: 1.272 | Y27: 2.016 | Z27: 2.191 | AA27: 2.355 | AB27: 2.267 | AC27: 2.272 | AD27: 2.294 | AE27: 2.249 | AF27: 2.576 | AG27: 5.32 | AH27: 5.794 | AI27: 6.965 | AJ27: 7.708
A28: Iceland | B28: 114.734 | C28: 134.542 | D28: 154.183 | E28: 185.639 | F28: 220.078 | G28: 245.071 | H28: 267.611 | I28: 274.447 | J28: 279.351 | K28: 265.216 | L28: 497.639 | M28: 537.821 | N28: 668.96 | O28: 701.761 | P28: 745.818 | Q28: 784.696 | R28: 731.653 | S28: 865.981 | T28: 948.735 | U28: 1754.257 | V28: 2094.358 | W28: 2238.058 | X28: 2438.817 | Y28: 2471.131 | Z28: 2402.796 | AA28: 2405.555 | AB28: 2248.986 | AC28: 2071.73 | AD28: 1895.401 | AE28: 1798.772 | AF28: 2013.2 | AG28: 2270.442 | AH28: 2451.637 | AI28: 2621.714 | AJ28: 2689.558
A29: Israel | B29: 138.963 | C29: 161.794 | D29: 185.568 | E29: 204.919 | F29: 237.246 | G29: 267.77 | H29: 296.736 | I29: 337.153 | J29: 372.243 | K29: 422.764 | L29: 435.781 | M29: 430.214 | N29: 460.884 | O29: 518.57 | P29: 537.446 | Q29: 553.962 | R29: 564.29 | S29: 549.757 | T29: 536.974 | U29: 557.486 | V29: 608.446 | W29: 618.53 | X29: 644.732 | Y29: 679.465 | Z29: 709.755 | AA29: 729.999 | AB29: 741.542 | AC29: 753.41 | AD29: 761.61 | AE29: 803.807 | AF29: 837.727 | AG29: 999.299 | AH29: 1059.78 | AI29: 1053.579 | AJ29: 1143.294
A30: Latvia | B30: … | C30: … | D30: … | E30: … | F30: … | G30: … | H30: 0.561 | I30: 0.626 | J30: 0.62 | K30: 0.575 | L30: 0.905 | M30: 1.011 | N30: 1.304 | O30: 1.252 | P30: 1.41 | Q30: 1.629 | R30: 1.639 | S30: 1.737 | T30: 1.935 | U30: 4.511 | V30: 6.957 | W30: 8.538 | X30: 8.949 | Y30: 9.364 | Z30: 9.172 | AA30: 9.818 | AB30: 9.089 | AC30: 10.224 | AD30: 10.493 | AE30: 10.784 | AF30: 11.209 | AG30: 12.87 | AH30: 14.81 | AI30: 16.039 | AJ30: 17.579
A31: Lithuania | B31: … | C31: … | D31: … | E31: … | F31: 0.507 | G31: 0.764 | H31: 0.895 | I31: 1.352 | J31: 1.802 | K31: 2.154 | L31: 2.886 | M31: 2.912 | N31: 3.185 | O31: 3.366 | P31: 3.395 | Q31: 3.405 | R31: 3.702 | S31: 4.152 | T31: 4.61 | U31: 4.762 | V31: 7.529 | W31: 10.154 | X31: 11.632 | Y31: 13.266 | Z31: 13.553 | AA31: 14.829 | AB31: 15.882 | AC31: 15.448 | AD31: 16.542 | AE31: 15.323 | AF31: 17.526 | AG31: 23.063 | AH31: 24.536 | AI31: 25.672 | AJ31: 27.558
A32: Luxembourg | B32: 0.72 | C32: 0.65 | D32: 0.63 | E32: 0.82 | F32: 1.12 | G32: 1.14 | H32: 1.61 | I32: 1.61 | J32: 1.63 | K32: 1.65 | L32: 1.66 | M32: 1.723 | N32: 1.82 | O32: 1.863 | P32: 1.95 | Q32: 2.207 | R32: 2.407 | S32: 2.804 | T32: 3.046 | U32: 5.852 | V32: 5.969 | W32: 8.095 | X32: 8.201 | Y32: 9.7 | Z32: 10.998 | AA32: 11.317 | AB32: 11.432 | AC32: 11.003 | AD32: 12.667 | AE32: 12.544 | AF32: 13.921 | AG32: 15.799 | AH32: 17.637 | AI32: 19.078 | AJ32: 20.262
A33: Malta | B33: … | C33: … | D33: … | E33: … | F33: … | G33: … | H33: 0.968 | I33: 1.177 | J33: 1.569 | K33: 1.79 | L33: 2.442 | M33: 2.654 | N33: 2.989 | O33: 2.927 | P33: 3.267 | Q33: 3.45 | R33: 3.606 | S33: 3.473 | T33: 3.585 | U33: 3.837 | V33: 4.153 | W33: 4.463 | X33: 4.848 | Y33: 4.907 | Z33: 5.28 | AA33: 5.436 | AB33: 5.627 | AC33: 5.774 | AD33: 5.711 | AE33: 5.669 | AF33: 5.728 | AG33: 6.983 | AH33: 8.273 | AI33: 9.011 | AJ33: 9.791
A34: San Marino | B34: … | C34: … | D34: … | E34: … | F34: … | G34: … | H34: … | I34: … | J34: … | K34: … | L34: … | M34: … | N34: … | O34: … | P34: … | Q34: 0.233 | R34: 0.208 | S34: 0.215 | T34: 0.202 | U34: 0.253 | V34: 0.297 | W34: 0.283 | X34: 0.217 | Y34: 0.215 | Z34: 0.293 | AA34: 0.265 | AB34: 0.247 | AC34: 0.285 | AD34: 0.768 | AE34: 0.802 | AF34: 0.829 | AG34: 0.969 | AH34: 1.276 | AI34: 1.299 | AJ34: 1.331
A35: Singapore | B35: 46.028 | C35: 51.426 | D35: 59.041 | E35: 67.253 | F35: 69.822 | G35: 75.344 | H35: 86.508 | I35: 94.831 | J35: 102.372 | K35: 115.183 | L35: 125.777 | M35: 134.37 | N35: 149 | O35: 156.751 | P35: 169.332 | Q35: 186.598 | R35: 200.006 | S35: 206.439 | T35: 234.093 | U35: 255.465 | V35: 291.502 | W35: 321.182 | X35: 354.023 | Y35: 384.998 | Z35: 390.407 | AA35: 387.251 | AB35: 421.302 | AC35: 463.166 | AD35: 502.022 | AE35: 546.7 | AF35: 641.094 | AG35: 704.721 | AH35: 777.958 | AI35: 1079.758 | AJ35: 1150.26
A36: Slovak Republic | B36: … | C36: … | D36: … | E36: … | F36: … | G36: … | H36: 3.309 | I36: 5.09 | J36: 6.324 | K36: 6.325 | L36: 9.581 | M36: 10.975 | N36: 12.406 | O36: 12.35 | P36: 13.16 | Q36: 15.02 | R36: 13.988 | S36: 15.544 | T36: 17.214 | U36: 19.63 | V36: 23.321 | W36: 27.94 | X36: 30.994 | Y36: 38.108 | Z36: 40.763 | AA36: 40.878 | AB36: 41.474 | AC36: 42.554 | AD36: 43.654 | AE36: 44.479 | AF36: 45.392 | AG36: 55.091 | AH36: 61.346 | AI36: 63.499 | AJ36: 68.898
A38: Foreign (Billion LC) | B38: =B1 -> 1989 | C38: =C1 -> 1990 | D38: =D1 -> 1991 | E38: =E1 -> 1992 | F38: =F1 -> 1993 | G38: =G1 -> 1994 | H38: =H1 -> 1995 | I38: =I1 -> 1996 | ... AJ38: =AJ1 -> 2023 | AL38: Foreign (% of Total Debt) | AM38: =B1 -> 1989 | AN38: =C1 -> 1990 | AO38: =D1 -> 1991 | AP38: =E1 -> 1992 | AQ38: =F1 -> 1993 | AR38: =G1 -> 1994 | AS38: =H1 -> 1995 | AT38: =I1 -> 1996 | ... BU38: =AJ1 -> 2023
A39: Australia | B39: … | C39: … | D39: … | E39: … | F39: … | G39: … | H39: … | I39: … | J39: … | K39: … | L39: … | M39: … | N39: … | O39: … | P39: 23.614 | Q39: ='Table 2. Foreign'!E2 -> 27.535 | R39: ='Table 2. Foreign'!I2 -> 31.699 | S39: ='Table 2. Foreign'!M2 -> 31.193 | T39: ='Table 2. Foreign'!Q2 -> 39.621 | U39: ='Table 2. Foreign'!U2 -> 38.261 | V39: ='Table 2. Foreign'!Y2 -> 71.158 | W39: ='Table 2. Foreign'!AC2 -> 123.528 | X39: ='Table 2. Foreign'!AG2 -> 167.797 | Y39: ='Table 2. Foreign'!AK2 -> 182.97 | Z39: ='Table 2. Foreign'!AO2 -> 205.116 | AA39: ='Table 2. Foreign'!AS2 -> 234.477 | AB39: ='Table 2. Foreign'!AW2 -> 255.694 | AC39: ='Table 2. Foreign'!BA2 -> 257.978 | AD39: ='Table 2. Foreign'!BE2 -> 290.687 | AE39: ='Table 2. Foreign'!BI2 -> 304.959 | AF39: ='Table 2. Foreign'!BM2 -> 321.615 | AG39: ='Table 2. Foreign'!BQ2 -> 418.498 | AH39: ='Table 2. Foreign'!BU2 -> 401.683 | AI39: ='Table 2. Foreign'!BY2 -> 429.769 | AJ39: ='Table 2. Foreign'!CC2 -> 440.803 | AL39: Australia | AM39: =IF(ISNUMBER(B39/B$2),B39/B$2,"…") -> … | AN39: =IF(ISNUMBER(C39/C$2),C39/C$2,"…") -> … | AO39: =IF(ISNUMBER(D39/D$2),D39/D$2,"…") -> … | AP39: =IF(ISNUMBER(E39/E$2),E39/E$2,"…") -> … | AQ39: =IF(ISNUMBER(F39/F$2),F39/F$2,"…") -> … | AR39: =IF(ISNUMBER(G39/G$2),G39/G$2,"…") -> … | AS39: =IF(ISNUMBER(H39/H$2),H39/H$2,"…") -> … | AT39: =IF(ISNUMBER(I39/I$2),I39/I$2,"…") -> … | ... BU39: =IF(ISNUMBER(AJ39/AJ$2),AJ39/AJ$2,"…") -> 0.33570616
A40: Austria | B40: … | C40: … | D40: … | E40: … | F40: … | G40: … | H40: 35.525 | I40: 35.533 | J40: 34.426 | K40: 46.972 | L40: 64.331 | M40: 73.696 | N40: 88.053 | O40: 97.675 | P40: 104.675 | Q40: ='Table 2. Foreign'!E3 -> 113.284 | R40: ='Table 2. Foreign'!I3 -> 125.263 | S40: ='Table 2. Foreign'!M3 -> 139.635 | T40: ='Table 2. Foreign'!Q3 -> 145.137 | U40: ='Table 2. Foreign'!U3 -> 159.52 | V40: ='Table 2. Foreign'!Y3 -> 175.875 | W40: ='Table 2. Foreign'!AC3 -> 185.271 | X40: ='Table 2. Foreign'!AG3 -> 192.996 | Y40: ='Table 2. Foreign'!AK3 -> 199.025 | Z40: ='Table 2. Foreign'!AO3 -> 200.46 | AA40: ='Table 2. Foreign'!AS3 -> 214.497 | AB40: ='Table 2. Foreign'!AW3 -> 216.167 | AC40: ='Table 2. Foreign'!BA3 -> 208.313 | AD40: ='Table 2. Foreign'!BE3 -> 194.681 | AE40: ='Table 2. Foreign'!BI3 -> 187.715 | AF40: ='Table 2. Foreign'!BM3 -> 187.452 | AG40: ='Table 2. Foreign'!BQ3 -> 202.618 | AH40: ='Table 2. Foreign'!BU3 -> 186.389 | AI40: ='Table 2. Foreign'!BY3 -> 200.901 | AJ40: ='Table 2. Foreign'!CC3 -> 222.671 | AL40: Austria | AM40: =IF(ISNUMBER(B40/B$3),B40/B$3,"…") -> … | AN40: =IF(ISNUMBER(C40/C$3),C40/C$3,"…") -> … | AO40: =IF(ISNUMBER(D40/D$3),D40/D$3,"…") -> … | AP40: =IF(ISNUMBER(E40/E$3),E40/E$3,"…") -> … | AQ40: =IF(ISNUMBER(F40/F$3),F40/F$3,"…") -> … | AR40: =IF(ISNUMBER(G40/G$3),G40/G$3,"…") -> … | AS40: =IF(ISNUMBER(H40/H$3),H40/H$3,"…") -> 0.28351955 | AT40: =IF(ISNUMBER(I40/I$3),I40/I$3,"…") -> 0.2838099 | ... BU40: =IF(ISNUMBER(AJ40/AJ$3),AJ40/AJ$3,"…") -> 0.59901434
A41: Belgium | B41: … | C41: … | D41: … | E41: … | F41: … | G41: … | H41: 65.311 | I41: 61.392 | J41: 64.776 | K41: 70.597 | L41: 85.642 | M41: 107.618 | N41: 121.962 | O41: 135.723 | P41: 140.721 | Q41: ='Table 2. Foreign'!E4 -> 144.483 | R41: ='Table 2. Foreign'!I4 -> 150.757 | S41: ='Table 2. Foreign'!M4 -> 154.655 | T41: ='Table 2. Foreign'!Q4 -> 171.689 | U41: ='Table 2. Foreign'!U4 -> 191.069 | V41: ='Table 2. Foreign'!Y4 -> 193.349 | W41: ='Table 2. Foreign'!AC4 -> 196.752 | X41: ='Table 2. Foreign'!AG4 -> 180.429 | Y41: ='Table 2. Foreign'!AK4 -> 187.177 | Z41: ='Table 2. Foreign'!AO4 -> 203.771 | AA41: ='Table 2. Foreign'!AS4 -> 234.219 | AB41: ='Table 2. Foreign'!AW4 -> 234.354 | AC41: ='Table 2. Foreign'!BA4 -> 242.333 | AD41: ='Table 2. Foreign'!BE4 -> 235.301 | AE41: ='Table 2. Foreign'!BI4 -> 244.141 | AF41: ='Table 2. Foreign'!BM4 -> 261.031 | AG41: ='Table 2. Foreign'!BQ4 -> 283.314 | AH41: ='Table 2. Foreign'!BU4 -> 284.152 | AI41: ='Table 2. Foreign'!BY4 -> 308.9 | AJ41: ='Table 2. Foreign'!CC4 -> 326.362 | AL41: Belgium | AM41: =IF(ISNUMBER(B41/B$4),B41/B$4,"…") -> … | AN41: =IF(ISNUMBER(C41/C$4),C41/C$4,"…") -> … | AO41: =IF(ISNUMBER(D41/D$4),D41/D$4,"…") -> … | AP41: =IF(ISNUMBER(E41/E$4),E41/E$4,"…") -> … | AQ41: =IF(ISNUMBER(F41/F$4),F41/F$4,"…") -> … | AR41: =IF(ISNUMBER(G41/G$4),G41/G$4,"…") -> … | AS41: =IF(ISNUMBER(H41/H$4),H41/H$4,"…") -> 0.22669559 | AT41: =IF(ISNUMBER(I41/I$4),I41/I$4,"…") -> 0.22075512 | ... BU41: =IF(ISNUMBER(AJ41/AJ$4),AJ41/AJ$4,"…") -> 0.53067768
A42: Canada | B42: … | C42: … | D42: … | E42: … | F42: … | G42: … | H42: … | I42: … | J42: … | K42: 244.471 | L42: 226.661 | M42: 210.061 | N42: 202.55 | O42: 213.497 | P42: 180.002 | Q42: ='Table 2. Foreign'!E5 -> 167.556 | R42: ='Table 2. Foreign'!I5 -> 160.169 | S42: ='Table 2. Foreign'!M5 -> 167.016 | T42: ='Table 2. Foreign'!Q5 -> 146.306 | U42: ='Table 2. Foreign'!U5 -> 171.943 | V42: ='Table 2. Foreign'!Y5 -> 207.658 | W42: ='Table 2. Foreign'!AC5 -> 262.584 | X42: ='Table 2. Foreign'!AG5 -> 321.157 | Y42: ='Table 2. Foreign'!AK5 -> 370.606 | Z42: ='Table 2. Foreign'!AO5 -> 364.288 | AA42: ='Table 2. Foreign'!AS5 -> 364.557 | AB42: ='Table 2. Foreign'!AW5 -> 400.65 | AC42: ='Table 2. Foreign'!BA5 -> 422.496 | AD42: ='Table 2. Foreign'!BE5 -> 457.383 | AE42: ='Table 2. Foreign'!BI5 -> 443.929 | AF42: ='Table 2. Foreign'!BM5 -> 438.321 | AG42: ='Table 2. Foreign'!BQ5 -> 550.371 | AH42: ='Table 2. Foreign'!BU5 -> 638.793 | AI42: ='Table 2. Foreign'!BY5 -> 626.362 | AJ42: ='Table 2. Foreign'!CC5 -> 663.178 | AL42: Canada | AM42: =IF(ISNUMBER(B42/B$5),B42/B$5,"…") -> … | AN42: =IF(ISNUMBER(C42/C$5),C42/C$5,"…") -> … | AO42: =IF(ISNUMBER(D42/D$5),D42/D$5,"…") -> … | AP42: =IF(ISNUMBER(E42/E$5),E42/E$5,"…") -> … | AQ42: =IF(ISNUMBER(F42/F$5),F42/F$5,"…") -> … | AR42: =IF(ISNUMBER(G42/G$5),G42/G$5,"…") -> … | AS42: =IF(ISNUMBER(H42/H$5),H42/H$5,"…") -> … | AT42: =IF(ISNUMBER(I42/I$5),I42/I$5,"…") -> … | ... BU42: =IF(ISNUMBER(AJ42/AJ$5),AJ42/AJ$5,"…") -> 0.24086441
A43: Czech Republic | B43: … | C43: … | D43: … | E43: … | F43: … | G43: … | H43: 67.678 | I43: 55.953 | J43: 59.589 | K43: 40.542 | L43: 36.578 | M43: 36.683 | N43: 30.534 | O43: 35.462 | P43: 62.86 | Q43: ='Table 2. Foreign'!E6 -> 178.892 | R43: ='Table 2. Foreign'!I6 -> 244.388 | S43: ='Table 2. Foreign'!M6 -> 264.785 | T43: ='Table 2. Foreign'!Q6 -> 290.494 | U43: ='Table 2. Foreign'!U6 -> 320.045 | V43: ='Table 2. Foreign'!Y6 -> 394.471 | W43: ='Table 2. Foreign'!AC6 -> 454.746 | X43: ='Table 2. Foreign'!AG6 -> 489.918 | Y43: ='Table 2. Foreign'!AK6 -> 536.495 | Z43: ='Table 2. Foreign'!AO6 -> 598.357 | AA43: ='Table 2. Foreign'!AS6 -> 539.187 | AB43: ='Table 2. Foreign'!AW6 -> 677.453 | AC43: ='Table 2. Foreign'!BA6 -> 785.939 | AD43: ='Table 2. Foreign'!BE6 -> 795.192 | AE43: ='Table 2. Foreign'!BI6 -> 686.316 | AF43: ='Table 2. Foreign'!BM6 -> 667.951 | AG43: ='Table 2. Foreign'!BQ6 -> 691.237 | AH43: ='Table 2. Foreign'!BU6 -> 793.376 | AI43: ='Table 2. Foreign'!BY6 -> 893.744 | AJ43: ='Table 2. Foreign'!CC6 -> 850.046 | AL43: Czech Republic | AM43: =IF(ISNUMBER(B43/B$6),B43/B$6,"…") -> … | AN43: =IF(ISNUMBER(C43/C$6),C43/C$6,"…") -> … | AO43: =IF(ISNUMBER(D43/D$6),D43/D$6,"…") -> … | AP43: =IF(ISNUMBER(E43/E$6),E43/E$6,"…") -> … | AQ43: =IF(ISNUMBER(F43/F$6),F43/F$6,"…") -> … | AR43: =IF(ISNUMBER(G43/G$6),G43/G$6,"…") -> … | AS43: =IF(ISNUMBER(H43/H$6),H43/H$6,"…") -> 0.31245614 | AT43: =IF(ISNUMBER(I43/I$6),I43/I$6,"…") -> 0.26417847 | ... BU43: =IF(ISNUMBER(AJ43/AJ$6),AJ43/AJ$6,"…") -> 0.26284647
A44: Denmark | B44: … | C44: … | D44: … | E44: … | F44: … | G44: … | H44: 319.619 | I44: 287.161 | J44: 280.03 | K44: 244.533 | L44: 287.161 | M44: 280.03 | N44: 244.533 | O44: 251.399 | P44: 189.358 | Q44: ='Table 2. Foreign'!E7 -> 203.111 | R44: ='Table 2. Foreign'!I7 -> 196.523 | S44: ='Table 2. Foreign'!M7 -> 191.532 | T44: ='Table 2. Foreign'!Q7 -> 197.948 | U44: ='Table 2. Foreign'!U7 -> 255.577 | V44: ='Table 2. Foreign'!Y7 -> 277.821 | W44: ='Table 2. Foreign'!AC7 -> 279.232 | X44: ='Table 2. Foreign'!AG7 -> 344.163 | Y44: ='Table 2. Foreign'!AK7 -> 343.495 | Z44: ='Table 2. Foreign'!AO7 -> 317.549 | AA44: ='Table 2. Foreign'!AS7 -> 316.678 | AB44: ='Table 2. Foreign'!AW7 -> 273.819 | AC44: ='Table 2. Foreign'!BA7 -> 234.469 | AD44: ='Table 2. Foreign'!BE7 -> 239.678 | AE44: ='Table 2. Foreign'!BI7 -> 208.38 | AF44: ='Table 2. Foreign'!BM7 -> 200.249 | AG44: ='Table 2. Foreign'!BQ7 -> 321.313 | AH44: ='Table 2. Foreign'!BU7 -> 241.09 | AI44: ='Table 2. Foreign'!BY7 -> 209.972 | AJ44: ='Table 2. Foreign'!CC7 -> 214.863 | AL44: Denmark | AM44: =IF(ISNUMBER(B44/B$7),B44/B$7,"…") -> … | AN44: =IF(ISNUMBER(C44/C$7),C44/C$7,"…") -> … | AO44: =IF(ISNUMBER(D44/D$7),D44/D$7,"…") -> … | AP44: =IF(ISNUMBER(E44/E$7),E44/E$7,"…") -> … | AQ44: =IF(ISNUMBER(F44/F$7),F44/F$7,"…") -> … | AR44: =IF(ISNUMBER(G44/G$7),G44/G$7,"…") -> … | AS44: =IF(ISNUMBER(H44/H$7),H44/H$7,"…") -> 0.42166095 | AT44: =IF(ISNUMBER(I44/I$7),I44/I$7,"…") -> 0.37744611 | ... BU44: =IF(ISNUMBER(AJ44/AJ$7),AJ44/AJ$7,"…") -> 0.22807468
A45: Finland | B45: … | C45: … | D45: … | E45: … | F45: … | G45: … | H45: 32.489 | I45: 35.155 | J45: 36.615 | K45: 36.116 | L45: 38.834 | M45: 36.931 | N45: 40.076 | O45: 46.504 | P45: 50.567 | Q45: ='Table 2. Foreign'!E8 -> 55.714 | R45: ='Table 2. Foreign'!I8 -> 52.312 | S45: ='Table 2. Foreign'!M8 -> 52.57 | T45: ='Table 2. Foreign'!Q8 -> 50.772 | U45: ='Table 2. Foreign'!U8 -> 49.902 | V45: ='Table 2. Foreign'!Y8 -> 61.343 | W45: ='Table 2. Foreign'!AC8 -> 70.829 | X45: ='Table 2. Foreign'!AG8 -> 76.096 | Y45: ='Table 2. Foreign'!AK8 -> 86.257 | Z45: ='Table 2. Foreign'!AO8 -> 92.003 | AA45: ='Table 2. Foreign'!AS8 -> 99.261 | AB45: ='Table 2. Foreign'!AW8 -> 102.199 | AC45: ='Table 2. Foreign'!BA8 -> 95.116 | AD45: ='Table 2. Foreign'!BE8 -> 91.83 | AE45: ='Table 2. Foreign'!BI8 -> 87.527 | AF45: ='Table 2. Foreign'!BM8 -> 89.033 | AG45: ='Table 2. Foreign'!BQ8 -> 100.104 | AH45: ='Table 2. Foreign'!BU8 -> 85.114 | AI45: ='Table 2. Foreign'!BY8 -> 94.661 | AJ45: ='Table 2. Foreign'!CC8 -> 108.714 | AL45: Finland | AM45: =IF(ISNUMBER(B45/B$8),B45/B$8,"…") -> … | AN45: =IF(ISNUMBER(C45/C$8),C45/C$8,"…") -> … | AO45: =IF(ISNUMBER(D45/D$8),D45/D$8,"…") -> … | AP45: =IF(ISNUMBER(E45/E$8),E45/E$8,"…") -> … | AQ45: =IF(ISNUMBER(F45/F$8),F45/F$8,"…") -> … | AR45: =IF(ISNUMBER(G45/G$8),G45/G$8,"…") -> … | AS45: =IF(ISNUMBER(H45/H$8),H45/H$8,"…") -> 0.57502655 | AT45: =IF(ISNUMBER(I45/I$8),I45/I$8,"…") -> 0.6092721 | ... BU45: =IF(ISNUMBER(AJ45/AJ$8),AJ45/AJ$8,"…") -> 0.51555964
A46: France | B46: … | C46: … | D46: … | E46: … | F46: … | G46: … | H46: 243.721 | I46: 287.283 | J46: 317.958 | K46: 341.935 | L46: 364.344 | M46: 382.443 | N46: 400.109 | O46: 416.103 | P46: 452.327 | Q46: ='Table 2. Foreign'!E9 -> 503.776 | R46: ='Table 2. Foreign'!I9 -> 543.939 | S46: ='Table 2. Foreign'!M9 -> 565.869 | T46: ='Table 2. Foreign'!Q9 -> 588.632 | U46: ='Table 2. Foreign'!U9 -> 626.377 | V46: ='Table 2. Foreign'!Y9 -> 672.992 | W46: ='Table 2. Foreign'!AC9 -> 746.379 | X46: ='Table 2. Foreign'!AG9 -> 837.657 | Y46: ='Table 2. Foreign'!AK9 -> 917.593 | Z46: ='Table 2. Foreign'!AO9 -> 975.345 | AA46: ='Table 2. Foreign'!AS9 -> 1024.1 | AB46: ='Table 2. Foreign'!AW9 -> 1052.611 | AC46: ='Table 2. Foreign'!BA9 -> 1028.083 | AD46: ='Table 2. Foreign'!BE9 -> 1009.436 | AE46: ='Table 2. Foreign'!BI9 -> 1136.167 | AF46: ='Table 2. Foreign'!BM9 -> 1201.604 | AG46: ='Table 2. Foreign'!BQ9 -> 1331.191 | AH46: ='Table 2. Foreign'!BU9 -> 1291.532 | AI46: ='Table 2. Foreign'!BY9 -> 1389.484 | AJ46: ='Table 2. Foreign'!CC9 -> 1545.56 | AL46: France | AM46: =IF(ISNUMBER(B46/B$9),B46/B$9,"…") -> … | AN46: =IF(ISNUMBER(C46/C$9),C46/C$9,"…") -> … | AO46: =IF(ISNUMBER(D46/D$9),D46/D$9,"…") -> … | AP46: =IF(ISNUMBER(E46/E$9),E46/E$9,"…") -> … | AQ46: =IF(ISNUMBER(F46/F$9),F46/F$9,"…") -> … | AR46: =IF(ISNUMBER(G46/G$9),G46/G$9,"…") -> … | AS46: =IF(ISNUMBER(H46/H$9),H46/H$9,"…") -> 0.34101161 | AT46: =IF(ISNUMBER(I46/I$9),I46/I$9,"…") -> 0.38035615 | ... BU46: =IF(ISNUMBER(AJ46/AJ$9),AJ46/AJ$9,"…") -> 0.49834654
A47: Germany | B47: … | C47: … | D47: 158.397 | E47: 219.644 | F47: 277.83 | G47: 288.945 | H47: 388.869 | I47: 420.466 | J47: 443.016 | K47: 478.073 | L47: 522.182 | M47: 561.135 | N47: 581.54 | O47: 618.822 | P47: 663.352 | Q47: ='Table 2. Foreign'!E10 -> 703.152 | R47: ='Table 2. Foreign'!I10 -> 756.575 | S47: ='Table 2. Foreign'!M10 -> 814.241 | T47: ='Table 2. Foreign'!Q10 -> 859.992 | U47: ='Table 2. Foreign'!U10 -> 898.749 | V47: ='Table 2. Foreign'!Y10 -> 976.879 | W47: ='Table 2. Foreign'!AC10 -> 1119.653 | X47: ='Table 2. Foreign'!AG10 -> 1220.442 | Y47: ='Table 2. Foreign'!AK10 -> 1274.998 | Z47: ='Table 2. Foreign'!AO10 -> 1289.06 | AA47: ='Table 2. Foreign'!AS10 -> 1303.326 | AB47: ='Table 2. Foreign'!AW10 -> 1214.071 | AC47: ='Table 2. Foreign'!BA10 -> 1110.577 | AD47: ='Table 2. Foreign'!BE10 -> 1028.201 | AE47: ='Table 2. Foreign'!BI10 -> 972.052 | AF47: ='Table 2. Foreign'!BM10 -> 989.606 | AG47: ='Table 2. Foreign'!BQ10 -> 1067.615 | AH47: ='Table 2. Foreign'!BU10 -> 1038.353 | AI47: ='Table 2. Foreign'!BY10 -> 1040.734 | AJ47: ='Table 2. Foreign'!CC10 -> 1185.373 | AL47: Germany | AM47: =IF(ISNUMBER(B47/B$10),B47/B$10,"…") -> … | AN47: =IF(ISNUMBER(C47/C$10),C47/C$10,"…") -> … | AO47: =IF(ISNUMBER(D47/D$10),D47/D$10,"…") -> 0.268424 | AP47: =IF(ISNUMBER(E47/E$10),E47/E$10,"…") -> 0.31328484 | AQ47: =IF(ISNUMBER(F47/F$10),F47/F$10,"…") -> 0.34982372 | AR47: =IF(ISNUMBER(G47/G$10),G47/G$10,"…") -> 0.32531524 | AS47: =IF(ISNUMBER(H47/H$10),H47/H$10,"…") -> 0.36009723 | AT47: =IF(ISNUMBER(I47/I$10),I47/I$10,"…") -> 0.37686296 | ... BU47: =IF(ISNUMBER(AJ47/AJ$10),AJ47/AJ$10,"…") -> 0.45040784
A48: Greece | B48: … | C48: … | D48: … | E48: … | F48: … | G48: … | H48: … | I48: … | J48: … | K48: … | L48: … | M48: … | N48: … | O48: … | P48: 97.497 | Q48: ='Table 2. Foreign'!E11 -> 117.719 | R48: ='Table 2. Foreign'!I11 -> 140.662 | S48: ='Table 2. Foreign'!M11 -> 146.663 | T48: ='Table 2. Foreign'!Q11 -> 172.75 | U48: ='Table 2. Foreign'!U11 -> 195.027 | V48: ='Table 2. Foreign'!Y11 -> 223.988 | W48: ='Table 2. Foreign'!AC11 -> 227.87 | X48: ='Table 2. Foreign'!AG11 -> 263.25 | Y48: ='Table 2. Foreign'!AK11 -> 253.545 | Z48: ='Table 2. Foreign'!AO11 -> 278.273 | AA48: ='Table 2. Foreign'!AS11 -> 274.023 | AB48: ='Table 2. Foreign'!AW11 -> 270.154 | AC48: ='Table 2. Foreign'!BA11 -> 274.256 | AD48: ='Table 2. Foreign'!BE11 -> 277.802 | AE48: ='Table 2. Foreign'!BI11 -> 298.36 | AF48: ='Table 2. Foreign'!BM11 -> 293.866 | AG48: ='Table 2. Foreign'!BQ11 -> 285.684 | AH48: ='Table 2. Foreign'!BU11 -> 280.606 | AI48: ='Table 2. Foreign'!BY11 -> 272.898 | AJ48: ='Table 2. Foreign'!CC11 -> 270.429 | AL48: Greece | AM48: =IF(ISNUMBER(B48/B$11),B48/B$11,"…") -> … | AN48: =IF(ISNUMBER(C48/C$11),C48/C$11,"…") -> … | AO48: =IF(ISNUMBER(D48/D$11),D48/D$11,"…") -> … | AP48: =IF(ISNUMBER(E48/E$11),E48/E$11,"…") -> … | AQ48: =IF(ISNUMBER(F48/F$11),F48/F$11,"…") -> … | AR48: =IF(ISNUMBER(G48/G$11),G48/G$11,"…") -> … | AS48: =IF(ISNUMBER(H48/H$11),H48/H$11,"…") -> … | AT48: =IF(ISNUMBER(I48/I$11),I48/I$11,"…") -> … | ... BU48: =IF(ISNUMBER(AJ48/AJ$11),AJ48/AJ$11,"…") -> 0.73267335
A49: Ireland | B49: … | C49: … | D49: … | E49: … | F49: … | G49: … | H49: … | I49: … | J49: … | K49: … | L49: … | M49: … | N49: … | O49: 19.431 | P49: 22.753 | Q49: ='Table 2. Foreign'!E12 -> 25.253 | R49: ='Table 2. Foreign'!I12 -> 26.525 | S49: ='Table 2. Foreign'!M12 -> 26.779 | T49: ='Table 2. Foreign'!Q12 -> 29.777 | U49: ='Table 2. Foreign'!U12 -> 57.142 | V49: ='Table 2. Foreign'!Y12 -> 74.282 | W49: ='Table 2. Foreign'!AC12 -> 79.616 | X49: ='Table 2. Foreign'!AG12 -> 102.683 | Y49: ='Table 2. Foreign'!AK12 -> 123.166 | Z49: ='Table 2. Foreign'!AO12 -> 124.8 | AA49: ='Table 2. Foreign'!AS12 -> 131.048 | AB49: ='Table 2. Foreign'!AW12 -> 129.942 | AC49: ='Table 2. Foreign'!BA12 -> 120.836 | AD49: ='Table 2. Foreign'!BE12 -> 121.344 | AE49: ='Table 2. Foreign'!BI12 -> 125.291 | AF49: ='Table 2. Foreign'!BM12 -> 139.404 | AG49: ='Table 2. Foreign'!BQ12 -> 124.313 | AH49: ='Table 2. Foreign'!BU12 -> 129.637 | AI49: ='Table 2. Foreign'!BY12 -> 120.218 | AJ49: ='Table 2. Foreign'!CC12 -> 119.761 | AL49: Ireland | AM49: =IF(ISNUMBER(B49/B$12),B49/B$12,"…") -> … | AN49: =IF(ISNUMBER(C49/C$12),C49/C$12,"…") -> … | AO49: =IF(ISNUMBER(D49/D$12),D49/D$12,"…") -> … | AP49: =IF(ISNUMBER(E49/E$12),E49/E$12,"…") -> … | AQ49: =IF(ISNUMBER(F49/F$12),F49/F$12,"…") -> … | AR49: =IF(ISNUMBER(G49/G$12),G49/G$12,"…") -> … | AS49: =IF(ISNUMBER(H49/H$12),H49/H$12,"…") -> … | AT49: =IF(ISNUMBER(I49/I$12),I49/I$12,"…") -> … | ... BU49: =IF(ISNUMBER(AJ49/AJ$12),AJ49/AJ$12,"…") -> 0.54258259
A50: Italy | B50: 26.362 | C50: 36.432 | D50: 46.117 | E50: 60.667 | F50: 107.101 | G50: 157.231 | H50: 177.619 | I50: 219.361 | J50: 272.913 | K50: 339.843 | L50: 400.203 | M50: 460.294 | N50: 450.194 | O50: 465.477 | P50: 516.59 | Q50: ='Table 2. Foreign'!E13 -> 530.411 | R50: ='Table 2. Foreign'!I13 -> 610.404 | S50: ='Table 2. Foreign'!M13 -> 659.674 | T50: ='Table 2. Foreign'!Q13 -> 657.128 | U50: ='Table 2. Foreign'!U13 -> 675.772 | V50: ='Table 2. Foreign'!Y13 -> 750.805 | W50: ='Table 2. Foreign'!AC13 -> 733.457 | X50: ='Table 2. Foreign'!AG13 -> 691.298 | Y50: ='Table 2. Foreign'!AK13 -> 654.271 | Z50: ='Table 2. Foreign'!AO13 -> 670.581 | AA50: ='Table 2. Foreign'!AS13 -> 729.295 | AB50: ='Table 2. Foreign'!AW13 -> 753.989 | AC50: ='Table 2. Foreign'!BA13 -> 740.015 | AD50: ='Table 2. Foreign'!BE13 -> 743.731 | AE50: ='Table 2. Foreign'!BI13 -> 693.762 | AF50: ='Table 2. Foreign'!BM13 -> 773.61 | AG50: ='Table 2. Foreign'!BQ13 -> 772.503 | AH50: ='Table 2. Foreign'!BU13 -> 785.802 | AI50: ='Table 2. Foreign'!BY13 -> 740.812 | AJ50: ='Table 2. Foreign'!CC13 -> 793.736 | AL50: Italy | AM50: =IF(ISNUMBER(B50/B$13),B50/B$13,"…") -> 0.034921182 | AN50: =IF(ISNUMBER(C50/C$13),C50/C$13,"…") -> 0.043392091 | AO50: =IF(ISNUMBER(D50/D$13),D50/D$13,"…") -> 0.04865689 | AP50: =IF(ISNUMBER(E50/E$13),E50/E$13,"…") -> 0.065892256 | AQ50: =IF(ISNUMBER(F50/F$13),F50/F$13,"…") -> 0.11008428 | AR50: =IF(ISNUMBER(G50/G$13),G50/G$13,"…") -> 0.1516649 | AS50: =IF(ISNUMBER(H50/H$13),H50/H$13,"…") -> 0.16197246 | AT50: =IF(ISNUMBER(I50/I$13),I50/I$13,"…") -> 0.17404078 | ... BU50: =IF(ISNUMBER(AJ50/AJ$13),AJ50/AJ$13,"…") -> 0.27671627
A51: Japan | B51: … | C51: … | D51: … | E51: … | F51: … | G51: … | H51: … | I51: … | J51: … | K51: … | L51: … | M51: … | N51: … | O51: … | P51: 23355.982 | Q51: ='Table 2. Foreign'!E14 -> 34018.987 | R51: ='Table 2. Foreign'!I14 -> 41823.901 | S51: ='Table 2. Foreign'!M14 -> 48919.338 | T51: ='Table 2. Foreign'!Q14 -> 67729.635 | U51: ='Table 2. Foreign'!U14 -> 62773.385 | V51: ='Table 2. Foreign'!Y14 -> 58862.784 | W51: ='Table 2. Foreign'!AC14 -> 64639.248 | X51: ='Table 2. Foreign'!AG14 -> 85217.867 | Y51: ='Table 2. Foreign'!AK14 -> 88724.909 | Z51: ='Table 2. Foreign'!AO14 -> 90656.741 | AA51: ='Table 2. Foreign'!AS14 -> 97668.108 | AB51: ='Table 2. Foreign'!AW14 -> 113036.35 | AC51: ='Table 2. Foreign'!BA14 -> 118102.82 | AD51: ='Table 2. Foreign'!BE14 -> 126589.86 | AE51: ='Table 2. Foreign'!BI14 -> 142276.54 | AF51: ='Table 2. Foreign'!BM14 -> 149401.37 | AG51: ='Table 2. Foreign'!BQ14 -> 168697.34 | AH51: ='Table 2. Foreign'!BU14 -> 183413.37 | AI51: ='Table 2. Foreign'!BY14 -> 196317.28 | AJ51: ='Table 2. Foreign'!CC14 -> 184870.8 | AL51: Japan | AM51: =IF(ISNUMBER(B51/B$14),B51/B$14,"…") -> … | AN51: =IF(ISNUMBER(C51/C$14),C51/C$14,"…") -> … | AO51: =IF(ISNUMBER(D51/D$14),D51/D$14,"…") -> … | AP51: =IF(ISNUMBER(E51/E$14),E51/E$14,"…") -> … | AQ51: =IF(ISNUMBER(F51/F$14),F51/F$14,"…") -> … | AR51: =IF(ISNUMBER(G51/G$14),G51/G$14,"…") -> … | AS51: =IF(ISNUMBER(H51/H$14),H51/H$14,"…") -> … | AT51: =IF(ISNUMBER(I51/I$14),I51/I$14,"…") -> … | ... BU51: =IF(ISNUMBER(AJ51/AJ$14),AJ51/AJ$14,"…") -> 0.14246799
A52: Korea | B52: … | C52: … | D52: … | E52: … | F52: … | G52: 5667.046 | H52: 5138.74 | I52: 5139.827 | J52: 15816.7 | K52: 23693.533 | L52: 26892.159 | M52: 28254.945 | N52: 27687.642 | O52: 24041.731 | P52: 16922.878 | Q52: ='Table 2. Foreign'!E15 -> 13869.701 | R52: ='Table 2. Foreign'!I15 -> 12460.71 | S52: ='Table 2. Foreign'!M15 -> 14076.375 | T52: ='Table 2. Foreign'!Q15 -> 34452.956 | U52: ='Table 2. Foreign'!U15 -> 31249.127 | V52: ='Table 2. Foreign'!Y15 -> 39921.061 | W52: ='Table 2. Foreign'!AC15 -> 57466.73 | X52: ='Table 2. Foreign'!AG15 -> 69011.05 | Y52: ='Table 2. Foreign'!AK15 -> 65143.124 | Z52: ='Table 2. Foreign'!AO15 -> 66461 | AA52: ='Table 2. Foreign'!AS15 -> 71680.701 | AB52: ='Table 2. Foreign'!AW15 -> 73637.698 | AC52: ='Table 2. Foreign'!BA15 -> 77942.812 | AD52: ='Table 2. Foreign'!BE15 -> 83716.839 | AE52: ='Table 2. Foreign'!BI15 -> 93356.207 | AF52: ='Table 2. Foreign'!BM15 -> 105585.69 | AG52: ='Table 2. Foreign'!BQ15 -> 129916.45 | AH52: ='Table 2. Foreign'!BU15 -> 171373.4 | AI52: ='Table 2. Foreign'!BY15 -> 197579.67 | AJ52: ='Table 2. Foreign'!CC15 -> 220284.96 | AL52: Korea | AM52: =IF(ISNUMBER(B52/B$15),B52/B$15,"…") -> … | AN52: =IF(ISNUMBER(C52/C$15),C52/C$15,"…") -> … | AO52: =IF(ISNUMBER(D52/D$15),D52/D$15,"…") -> … | AP52: =IF(ISNUMBER(E52/E$15),E52/E$15,"…") -> … | AQ52: =IF(ISNUMBER(F52/F$15),F52/F$15,"…") -> … | AR52: =IF(ISNUMBER(G52/G$15),G52/G$15,"…") -> 0.21220719 | AS52: =IF(ISNUMBER(H52/H$15),H52/H$15,"…") -> 0.19093543 | AT52: =IF(ISNUMBER(I52/I$15),I52/I$15,"…") -> 0.18643101 | ... BU52: =IF(ISNUMBER(AJ52/AJ$15),AJ52/AJ$15,"…") -> 0.20845117
A53: Netherlands | B53: … | C53: … | D53: … | E53: … | F53: … | G53: … | H53: 61.924 | I53: 57.139 | J53: 57.587 | K53: 68.54 | L53: 89.366 | M53: 100.572 | N53: 116.381 | O53: 129.917 | P53: 141.604 | Q53: ='Table 2. Foreign'!E16 -> 156.187 | R53: ='Table 2. Foreign'!I16 -> 172.833 | S53: ='Table 2. Foreign'!M16 -> 168.249 | T53: ='Table 2. Foreign'!Q16 -> 169.074 | U53: ='Table 2. Foreign'!U16 -> 251.327 | V53: ='Table 2. Foreign'!Y16 -> 248.516 | W53: ='Table 2. Foreign'!AC16 -> 240.206 | X53: ='Table 2. Foreign'!AG16 -> 237.6 | Y53: ='Table 2. Foreign'!AK16 -> 243.129 | Z53: ='Table 2. Foreign'!AO16 -> 247.485 | AA53: ='Table 2. Foreign'!AS16 -> 254.066 | AB53: ='Table 2. Foreign'!AW16 -> 227.142 | AC53: ='Table 2. Foreign'!BA16 -> 196.733 | AD53: ='Table 2. Foreign'!BE16 -> 163.565 | AE53: ='Table 2. Foreign'!BI16 -> 158.687 | AF53: ='Table 2. Foreign'!BM16 -> 157.215 | AG53: ='Table 2. Foreign'!BQ16 -> 165.191 | AH53: ='Table 2. Foreign'!BU16 -> 155.219 | AI53: ='Table 2. Foreign'!BY16 -> 191.182 | AJ53: ='Table 2. Foreign'!CC16 -> 190.786 | AL53: Netherlands | AM53: =IF(ISNUMBER(B53/B$16),B53/B$16,"…") -> … | AN53: =IF(ISNUMBER(C53/C$16),C53/C$16,"…") -> … | AO53: =IF(ISNUMBER(D53/D$16),D53/D$16,"…") -> … | AP53: =IF(ISNUMBER(E53/E$16),E53/E$16,"…") -> … | AQ53: =IF(ISNUMBER(F53/F$16),F53/F$16,"…") -> … | AR53: =IF(ISNUMBER(G53/G$16),G53/G$16,"…") -> … | AS53: =IF(ISNUMBER(H53/H$16),H53/H$16,"…") -> 0.24582771 | AT53: =IF(ISNUMBER(I53/I$16),I53/I$16,"…") -> 0.23021354 | ... BU53: =IF(ISNUMBER(AJ53/AJ$16),AJ53/AJ$16,"…") -> 0.39625894
A54: New Zealand | B54: … | C54: … | D54: … | E54: … | F54: 7.241 | G54: 10.271 | H54: 11.521 | I54: 14.886 | J54: 14.565 | K54: 12.777 | L54: 10.306 | M54: 8.627 | N54: 9.542 | O54: 11.985 | P54: 12.848 | Q54: ='Table 2. Foreign'!E17 -> 14.06 | R54: ='Table 2. Foreign'!I17 -> 14.199 | S54: ='Table 2. Foreign'!M17 -> 12.022 | T54: ='Table 2. Foreign'!Q17 -> 15.027 | U54: ='Table 2. Foreign'!U17 -> 14.816 | V54: ='Table 2. Foreign'!Y17 -> 17.545 | W54: ='Table 2. Foreign'!AC17 -> 26.487 | X54: ='Table 2. Foreign'!AG17 -> 33.91 | Y54: ='Table 2. Foreign'!AK17 -> 41.585 | Z54: ='Table 2. Foreign'!AO17 -> 44.876 | AA54: ='Table 2. Foreign'!AS17 -> 45.996 | AB54: ='Table 2. Foreign'!AW17 -> 47.935 | AC54: ='Table 2. Foreign'!BA17 -> 46.737 | AD54: ='Table 2. Foreign'!BE17 -> 43.398 | AE54: ='Table 2. Foreign'!BI17 -> 41.688 | AF54: ='Table 2. Foreign'!BM17 -> 39.994 | AG54: ='Table 2. Foreign'!BQ17 -> 39.641 | AH54: ='Table 2. Foreign'!BU17 -> 53.092 | AI54: ='Table 2. Foreign'!BY17 -> 66.429 | AJ54: ='Table 2. Foreign'!CC17 -> 80.308 | AL54: New Zealand | AM54: =IF(ISNUMBER(B54/B$17),B54/B$17,"…") -> … | AN54: =IF(ISNUMBER(C54/C$17),C54/C$17,"…") -> … | AO54: =IF(ISNUMBER(D54/D$17),D54/D$17,"…") -> … | AP54: =IF(ISNUMBER(E54/E$17),E54/E$17,"…") -> … | AQ54: =IF(ISNUMBER(F54/F$17),F54/F$17,"…") -> 0.25254604 | AR54: =IF(ISNUMBER(G54/G$17),G54/G$17,"…") -> 0.33836271 | AS54: =IF(ISNUMBER(H54/H$17),H54/H$17,"…") -> 0.36782453 | AT54: =IF(ISNUMBER(I54/I$17),I54/I$17,"…") -> 0.46421555 | ... BU54: =IF(ISNUMBER(AJ54/AJ$17),AJ54/AJ$17,"…") -> 0.41748804
A55: Norway | B55: … | C55: … | D55: … | E55: … | F55: … | G55: … | H55: … | I55: … | J55: … | K55: … | L55: … | M55: … | N55: … | O55: … | P55: 358.775 | Q55: ='Table 2. Foreign'!E18 -> 460.27 | R55: ='Table 2. Foreign'!I18 -> 504.934 | S55: ='Table 2. Foreign'!M18 -> 823.08 | T55: ='Table 2. Foreign'!Q18 -> 829.195 | U55: ='Table 2. Foreign'!U18 -> 843.339 | V55: ='Table 2. Foreign'!Y18 -> 439.528 | W55: ='Table 2. Foreign'!AC18 -> 540.333 | X55: ='Table 2. Foreign'!AG18 -> 278.655 | Y55: ='Table 2. Foreign'!AK18 -> 305.21 | Z55: ='Table 2. Foreign'!AO18 -> 360.64 | AA55: ='Table 2. Foreign'!AS18 -> 285.406 | AB55: ='Table 2. Foreign'!AW18 -> 405.225 | AC55: ='Table 2. Foreign'!BA18 -> 492.169 | AD55: ='Table 2. Foreign'!BE18 -> 552.86 | AE55: ='Table 2. Foreign'!BI18 -> 680.649 | AF55: ='Table 2. Foreign'!BM18 -> 715.196 | AG55: ='Table 2. Foreign'!BQ18 -> 787.896 | AH55: ='Table 2. Foreign'!BU18 -> 1001.585 | AI55: ='Table 2. Foreign'!BY18 -> 1239.421 | AJ55: ='Table 2. Foreign'!CC18 -> 1374.615 | AL55: Norway | AM55: =IF(ISNUMBER(B55/B$18),B55/B$18,"…") -> … | AN55: =IF(ISNUMBER(C55/C$18),C55/C$18,"…") -> … | AO55: =IF(ISNUMBER(D55/D$18),D55/D$18,"…") -> … | AP55: =IF(ISNUMBER(E55/E$18),E55/E$18,"…") -> … | AQ55: =IF(ISNUMBER(F55/F$18),F55/F$18,"…") -> … | AR55: =IF(ISNUMBER(G55/G$18),G55/G$18,"…") -> … | AS55: =IF(ISNUMBER(H55/H$18),H55/H$18,"…") -> … | AT55: =IF(ISNUMBER(I55/I$18),I55/I$18,"…") -> … | ... BU55: =IF(ISNUMBER(AJ55/AJ$18),AJ55/AJ$18,"…") -> 0.60528236
A56: Portugal | B56: … | C56: … | D56: … | E56: … | F56: … | G56: … | H56: 11.371 | I56: 12.804 | J56: 16.396 | K56: 19.614 | L56: 27.776 | M56: 33.919 | N56: 42.754 | O56: 49.333 | P56: 55.419 | Q56: ='Table 2. Foreign'!E19 -> 63.211 | R56: ='Table 2. Foreign'!I19 -> 76.675 | S56: ='Table 2. Foreign'!M19 -> 82.981 | T56: ='Table 2. Foreign'!Q19 -> 90.456 | U56: ='Table 2. Foreign'!U19 -> 98.005 | V56: ='Table 2. Foreign'!Y19 -> 108.972 | W56: ='Table 2. Foreign'!AC19 -> 109.853 | X56: ='Table 2. Foreign'!AG19 -> 130.106 | Y56: ='Table 2. Foreign'!AK19 -> 141.294 | Z56: ='Table 2. Foreign'!AO19 -> 147.635 | AA56: ='Table 2. Foreign'!AS19 -> 158.913 | AB56: ='Table 2. Foreign'!AW19 -> 153.995 | AC56: ='Table 2. Foreign'!BA19 -> 139.645 | AD56: ='Table 2. Foreign'!BE19 -> 131.125 | AE56: ='Table 2. Foreign'!BI19 -> 127.597 | AF56: ='Table 2. Foreign'!BM19 -> 129.274 | AG56: ='Table 2. Foreign'!BQ19 -> 132.483 | AH56: ='Table 2. Foreign'!BU19 -> 121.826 | AI56: ='Table 2. Foreign'!BY19 -> 121.718 | AJ56: ='Table 2. Foreign'!CC19 -> 110.328 | AL56: Portugal | AM56: =IF(ISNUMBER(B56/B$19),B56/B$19,"…") -> … | AN56: =IF(ISNUMBER(C56/C$19),C56/C$19,"…") -> … | AO56: =IF(ISNUMBER(D56/D$19),D56/D$19,"…") -> … | AP56: =IF(ISNUMBER(E56/E$19),E56/E$19,"…") -> … | AQ56: =IF(ISNUMBER(F56/F$19),F56/F$19,"…") -> … | AR56: =IF(ISNUMBER(G56/G$19),G56/G$19,"…") -> … | AS56: =IF(ISNUMBER(H56/H$19),H56/H$19,"…") -> 0.20125664 | AT56: =IF(ISNUMBER(I56/I$19),I56/I$19,"…") -> 0.2095581 | ... BU56: =IF(ISNUMBER(AJ56/AJ$19),AJ56/AJ$19,"…") -> 0.42134207
A57: Slovenia | B57: … | C57: … | D57: … | E57: … | F57: … | G57: … | H57: 0.3 | I57: 0.934 | J57: 1.151 | K57: 1.229 | L57: 1.635 | M57: 2.102 | N57: 2.383 | O57: 2.405 | P57: 2.288 | Q57: ='Table 2. Foreign'!E20 -> 2.14 | R57: ='Table 2. Foreign'!I20 -> 1.991 | S57: ='Table 2. Foreign'!M20 -> 2.305 | T57: ='Table 2. Foreign'!Q20 -> 3.029 | U57: ='Table 2. Foreign'!U20 -> 3.692 | V57: ='Table 2. Foreign'!Y20 -> 6.427 | W57: ='Table 2. Foreign'!AC20 -> 7.936 | X57: ='Table 2. Foreign'!AG20 -> 9.562 | Y57: ='Table 2. Foreign'!AK20 -> 11.364 | Z57: ='Table 2. Foreign'!AO20 -> 15.631 | AA57: ='Table 2. Foreign'!AS20 -> 20.783 | AB57: ='Table 2. Foreign'!AW20 -> 21.603 | AC57: ='Table 2. Foreign'!BA20 -> 20.077 | AD57: ='Table 2. Foreign'!BE20 -> 19.787 | AE57: ='Table 2. Foreign'!BI20 -> 19.362 | AF57: ='Table 2. Foreign'!BM20 -> 19.103 | AG57: ='Table 2. Foreign'!BQ20 -> 21.558 | AH57: ='Table 2. Foreign'!BU20 -> 19.827 | AI57: ='Table 2. Foreign'!BY20 -> 21.049 | AJ57: ='Table 2. Foreign'!CC20 -> 23.154 | AL57: Slovenia | AM57: =IF(ISNUMBER(B57/B$20),B57/B$20,"…") -> … | AN57: =IF(ISNUMBER(C57/C$20),C57/C$20,"…") -> … | AO57: =IF(ISNUMBER(D57/D$20),D57/D$20,"…") -> … | AP57: =IF(ISNUMBER(E57/E$20),E57/E$20,"…") -> … | AQ57: =IF(ISNUMBER(F57/F$20),F57/F$20,"…") -> … | AR57: =IF(ISNUMBER(G57/G$20),G57/G$20,"…") -> … | AS57: =IF(ISNUMBER(H57/H$20),H57/H$20,"…") -> 0.10760402 | AT57: =IF(ISNUMBER(I57/I$20),I57/I$20,"…") -> 0.26384181 | ... BU57: =IF(ISNUMBER(AJ57/AJ$20),AJ57/AJ$20,"…") -> 0.52936738
A58: Spain | B58: … | C58: … | D58: … | E58: … | F58: … | G58: … | H58: 64.077 | I58: 66.659 | J58: 77.044 | K58: 83.54 | L58: 109.215 | M58: 143.436 | N58: 155.976 | O58: 166.595 | P58: 152.366 | Q58: ='Table 2. Foreign'!E21 -> 176.153 | R58: ='Table 2. Foreign'!I21 -> 187.062 | S58: ='Table 2. Foreign'!M21 -> 196.58 | T58: ='Table 2. Foreign'!Q21 -> 183.681 | U58: ='Table 2. Foreign'!U21 -> 207.317 | V58: ='Table 2. Foreign'!Y21 -> 245.987 | W58: ='Table 2. Foreign'!AC21 -> 277.705 | X58: ='Table 2. Foreign'!AG21 -> 267.085 | Y58: ='Table 2. Foreign'!AK21 -> 333.625 | Z58: ='Table 2. Foreign'!AO21 -> 377.175 | AA58: ='Table 2. Foreign'!AS21 -> 433.667 | AB58: ='Table 2. Foreign'!AW21 -> 478.794 | AC58: ='Table 2. Foreign'!BA21 -> 494.4 | AD58: ='Table 2. Foreign'!BE21 -> 513.089 | AE58: ='Table 2. Foreign'!BI21 -> 533.1 | AF58: ='Table 2. Foreign'!BM21 -> 582.192 | AG58: ='Table 2. Foreign'!BQ21 -> 589.91 | AH58: ='Table 2. Foreign'!BU21 -> 587.199 | AI58: ='Table 2. Foreign'!BY21 -> 585.867 | AJ58: ='Table 2. Foreign'!CC21 -> 627.238 | AL58: Spain | AM58: =IF(ISNUMBER(B58/B$21),B58/B$21,"…") -> … | AN58: =IF(ISNUMBER(C58/C$21),C58/C$21,"…") -> … | AO58: =IF(ISNUMBER(D58/D$21),D58/D$21,"…") -> … | AP58: =IF(ISNUMBER(E58/E$21),E58/E$21,"…") -> … | AQ58: =IF(ISNUMBER(F58/F$21),F58/F$21,"…") -> … | AR58: =IF(ISNUMBER(G58/G$21),G58/G$21,"…") -> … | AS58: =IF(ISNUMBER(H58/H$21),H58/H$21,"…") -> 0.21676928 | AT58: =IF(ISNUMBER(I58/I$21),I58/I$21,"…") -> 0.20554733 | ... BU58: =IF(ISNUMBER(AJ58/AJ$21),AJ58/AJ$21,"…") -> 0.3981518
A59: Sweden | B59: … | C59: … | D59: … | E59: … | F59: … | G59: … | H59: 617.657 | I59: 654.724 | J59: 658.488 | K59: 654.597 | L59: 563.167 | M59: 452.133 | N59: 491.81 | O59: 488.958 | P59: 506.454 | Q59: ='Table 2. Foreign'!E22 -> 487.633 | R59: ='Table 2. Foreign'!I22 -> 427.099 | S59: ='Table 2. Foreign'!M22 -> 315.114 | T59: ='Table 2. Foreign'!Q22 -> 331.35 | U59: ='Table 2. Foreign'!U22 -> 335.292 | V59: ='Table 2. Foreign'!Y22 -> 359.699 | W59: ='Table 2. Foreign'!AC22 -> 393.426 | X59: ='Table 2. Foreign'!AG22 -> 425.831 | Y59: ='Table 2. Foreign'!AK22 -> 479.006 | Z59: ='Table 2. Foreign'!AO22 -> 582.149 | AA59: ='Table 2. Foreign'!AS22 -> 760.724 | AB59: ='Table 2. Foreign'!AW22 -> 702.691 | AC59: ='Table 2. Foreign'!BA22 -> 554.432 | AD59: ='Table 2. Foreign'!BE22 -> 445.252 | AE59: ='Table 2. Foreign'!BI22 -> 458.767 | AF59: ='Table 2. Foreign'!BM22 -> 520.489 | AG59: ='Table 2. Foreign'!BQ22 -> 529.638 | AH59: ='Table 2. Foreign'!BU22 -> 376.235 | AI59: ='Table 2. Foreign'!BY22 -> 296.038 | AJ59: ='Table 2. Foreign'!CC22 -> 331.26 | AL59: Sweden | AM59: =IF(ISNUMBER(B59/B$22),B59/B$22,"…") -> … | AN59: =IF(ISNUMBER(C59/C$22),C59/C$22,"…") -> … | AO59: =IF(ISNUMBER(D59/D$22),D59/D$22,"…") -> … | AP59: =IF(ISNUMBER(E59/E$22),E59/E$22,"…") -> … | AQ59: =IF(ISNUMBER(F59/F$22),F59/F$22,"…") -> … | AR59: =IF(ISNUMBER(G59/G$22),G59/G$22,"…") -> … | AS59: =IF(ISNUMBER(H59/H$22),H59/H$22,"…") -> 0.47149389 | AT59: =IF(ISNUMBER(I59/I$22),I59/I$22,"…") -> 0.48245376 | ... BU59: =IF(ISNUMBER(AJ59/AJ$22),AJ59/AJ$22,"…") -> 0.16949473
A60: Switzerland | B60: … | C60: … | D60: … | E60: … | F60: … | G60: … | H60: … | I60: … | J60: … | K60: … | L60: 7.185 | M60: 8.812 | N60: 11.053 | O60: 12.353 | P60: 19.952 | Q60: ='Table 2. Foreign'!E23 -> 27.532 | R60: ='Table 2. Foreign'!I23 -> 46.432 | S60: ='Table 2. Foreign'!M23 -> 58.19 | T60: ='Table 2. Foreign'!Q23 -> 49.182 | U60: ='Table 2. Foreign'!U23 -> 22.466 | V60: ='Table 2. Foreign'!Y23 -> 18.649 | W60: ='Table 2. Foreign'!AC23 -> 18.347 | X60: ='Table 2. Foreign'!AG23 -> 22.758 | Y60: ='Table 2. Foreign'!AK23 -> 30.828 | Z60: ='Table 2. Foreign'!AO23 -> 29.033 | AA60: ='Table 2. Foreign'!AS23 -> 34.277 | AB60: ='Table 2. Foreign'!AW23 -> 32.344 | AC60: ='Table 2. Foreign'!BA23 -> 30.205 | AD60: ='Table 2. Foreign'!BE23 -> 27.992 | AE60: ='Table 2. Foreign'!BI23 -> 26.387 | AF60: ='Table 2. Foreign'!BM23 -> 25.362 | AG60: ='Table 2. Foreign'!BQ23 -> 19.307 | AH60: ='Table 2. Foreign'!BU23 -> 21.796 | AI60: ='Table 2. Foreign'!BY23 -> 25.072 | AJ60: ='Table 2. Foreign'!CC23 -> 26.063 | AL60: Switzerland | AM60: =IF(ISNUMBER(B60/B$23),B60/B$23,"…") -> … | AN60: =IF(ISNUMBER(C60/C$23),C60/C$23,"…") -> … | AO60: =IF(ISNUMBER(D60/D$23),D60/D$23,"…") -> … | AP60: =IF(ISNUMBER(E60/E$23),E60/E$23,"…") -> … | AQ60: =IF(ISNUMBER(F60/F$23),F60/F$23,"…") -> … | AR60: =IF(ISNUMBER(G60/G$23),G60/G$23,"…") -> … | AS60: =IF(ISNUMBER(H60/H$23),H60/H$23,"…") -> … | AT60: =IF(ISNUMBER(I60/I$23),I60/I$23,"…") -> … | ... BU60: =IF(ISNUMBER(AJ60/AJ$23),AJ60/AJ$23,"…") -> 0.13024792
A61: United Kingdom | B61: 27.007 | C61: 26.648 | D61: 32.97 | E61: 42.608 | F61: 62.736 | G61: 60.724 | H61: 64.348 | I61: 68.467 | J61: 64.471 | K61: 64.606 | L61: 56.102 | M61: 56.158 | N61: 56.184 | O61: 51.731 | P61: 64.588 | Q61: ='Table 2. Foreign'!E24 -> 92.126 | R61: ='Table 2. Foreign'!I24 -> 115.67 | S61: ='Table 2. Foreign'!M24 -> 144.584 | T61: ='Table 2. Foreign'!Q24 -> 171.042 | U61: ='Table 2. Foreign'!U24 -> 220.081 | V61: ='Table 2. Foreign'!Y24 -> 245.344 | W61: ='Table 2. Foreign'!AC24 -> 333.408 | X61: ='Table 2. Foreign'!AG24 -> 378.296 | Y61: ='Table 2. Foreign'!AK24 -> 408.743 | Z61: ='Table 2. Foreign'!AO24 -> 422.943 | AA61: ='Table 2. Foreign'!AS24 -> 384.439 | AB61: ='Table 2. Foreign'!AW24 -> 445.531 | AC61: ='Table 2. Foreign'!BA24 -> 466.485 | AD61: ='Table 2. Foreign'!BE24 -> 482.194 | AE61: ='Table 2. Foreign'!BI24 -> 498.766 | AF61: ='Table 2. Foreign'!BM24 -> 546.559 | AG61: ='Table 2. Foreign'!BQ24 -> 582.51 | AH61: ='Table 2. Foreign'!BU24 -> 638.482 | AI61: ='Table 2. Foreign'!BY24 -> 720.127 | AJ61: ='Table 2. Foreign'!CC24 -> 784.59 | AL61: United Kingdom | AM61: =IF(ISNUMBER(B61/B$24),B61/B$24,"…") -> 0.13977549 | AN61: =IF(ISNUMBER(C61/C$24),C61/C$24,"…") -> 0.14056261 | AO61: =IF(ISNUMBER(D61/D$24),D61/D$24,"…") -> 0.16261887 | AP61: =IF(ISNUMBER(E61/E$24),E61/E$24,"…") -> 0.17157745 | AQ61: =IF(ISNUMBER(F61/F$24),F61/F$24,"…") -> 0.19349108 | AR61: =IF(ISNUMBER(G61/G$24),G61/G$24,"…") -> 0.18400097 | AS61: =IF(ISNUMBER(H61/H$24),H61/H$24,"…") -> 0.16765019 | AT61: =IF(ISNUMBER(I61/I$24),I61/I$24,"…") -> 0.16817524 | ... BU61: =IF(ISNUMBER(AJ61/AJ$24),AJ61/AJ$24,"…") -> 0.28835923
A62: United States | B62: 425.742 | C62: 440.563 | D62: 478.689 | E62: 522.939 | F62: 597.351 | G62: 635.571 | H62: 820.899 | I62: 1045.234 | J62: 1159.069 | K62: 1173.052 | L62: 1066.125 | M62: 1029.426 | N62: 1103.208 | O62: 1296.998 | P62: 1483.622 | Q62: ='Table 2. Foreign'!E25 -> 1911.083 | R62: ='Table 2. Foreign'!I25 -> 2052.901 | S62: ='Table 2. Foreign'!M25 -> 2188.785 | T62: ='Table 2. Foreign'!Q25 -> 2426.886 | U62: ='Table 2. Foreign'!U25 -> 3067.404 | V62: ='Table 2. Foreign'!Y25 -> 3659.262 | W62: ='Table 2. Foreign'!AC25 -> 4355.57 | X62: ='Table 2. Foreign'!AG25 -> 4883.984 | Y62: ='Table 2. Foreign'!AK25 -> 5383.369 | Z62: ='Table 2. Foreign'!AO25 -> 5163.791 | AA62: ='Table 2. Foreign'!AS25 -> 5544.812 | AB62: ='Table 2. Foreign'!AW25 -> 5481.482 | AC62: ='Table 2. Foreign'!BA25 -> 5418.246 | AD62: ='Table 2. Foreign'!BE25 -> 5598.714 | AE62: ='Table 2. Foreign'!BI25 -> 5613.951 | AF62: ='Table 2. Foreign'!BM25 -> 6093.719 | AG62: ='Table 2. Foreign'!BQ25 -> 6152.427 | AH62: ='Table 2. Foreign'!BU25 -> 6872.62 | AI62: ='Table 2. Foreign'!BY25 -> 6436.248 | AJ62: ='Table 2. Foreign'!CC25 -> 6620.327 | AL62: United States | AM62: =IF(ISNUMBER(B62/B$25),B62/B$25,"…") -> 0.13656454 | AN62: =IF(ISNUMBER(C62/C$25),C62/C$25,"…") -> 0.12947606 | AO62: =IF(ISNUMBER(D62/D$25),D62/D$25,"…") -> 0.12646741 | AP62: =IF(ISNUMBER(E62/E$25),E62/E$25,"…") -> 0.12557985 | AQ62: =IF(ISNUMBER(F62/F$25),F62/F$25,"…") -> 0.13230447 | AR62: =IF(ISNUMBER(G62/G$25),G62/G$25,"…") -> 0.13485146 | AS62: =IF(ISNUMBER(H62/H$25),H62/H$25,"…") -> 0.16718536 | AT62: =IF(ISNUMBER(I62/I$25),I62/I$25,"…") -> 0.20416661 | ... BU62: =IF(ISNUMBER(AJ62/AJ$25),AJ62/AJ$25,"…") -> 0.21340235
A63: Cyprus | B63: … | C63: … | D63: … | E63: … | F63: … | G63: … | H63: 1.413 | I63: 1.154 | J63: 1.35 | K63: 1.76 | L63: 1.788 | M63: 1.964 | N63: 1.814 | O63: 3.28 | P63: 3.638 | Q63: 4.307 | R63: 4.18 | S63: 3.875 | T63: 3.959 | U63: 4.092 | V63: 6.012 | W63: 7.366 | X63: 8.898 | Y63: 9.837 | Z63: 13.245 | AA63: 15.191 | AB63: 16.807 | AC63: 17.56 | AD63: 16.88 | AE63: 16.543 | AF63: 17.035 | AG63: 20.438 | AH63: 14.945 | AI63: 14.367 | AJ63: 14.136 | AL63: Cyprus | AM63: =IF(ISNUMBER(B63/B$26),B63/B$26,"…") -> … | AN63: =IF(ISNUMBER(C63/C$26),C63/C$26,"…") -> … | AO63: =IF(ISNUMBER(D63/D$26),D63/D$26,"…") -> … | AP63: =IF(ISNUMBER(E63/E$26),E63/E$26,"…") -> … | AQ63: =IF(ISNUMBER(F63/F$26),F63/F$26,"…") -> … | AR63: =IF(ISNUMBER(G63/G$26),G63/G$26,"…") -> … | AS63: =IF(ISNUMBER(H63/H$26),H63/H$26,"…") -> 0.37861736 | AT63: =IF(ISNUMBER(I63/I$26),I63/I$26,"…") -> 0.28529048 | ... BU63: =IF(ISNUMBER(AJ63/AJ$26),AJ63/AJ$26,"…") -> 0.6125845
A64: Estonia | B64: … | C64: … | D64: … | E64: … | F64: … | G64: … | H64: 0.155 | I64: 0.165 | J64: 0.177 | K64: 0.206 | L64: 0.217 | M64: 0.208 | N64: 0.193 | O64: 0.226 | P64: 0.249 | Q64: 0.259 | R64: 0.268 | S64: 0.332 | T64: 0.237 | U64: 0.243 | V64: 0.382 | W64: 0.381 | X64: 0.395 | Y64: 1.103 | Z64: 1.236 | AA64: 1.399 | AB64: 1.361 | AC64: 1.346 | AD64: 1.326 | AE64: 1.281 | AF64: 1.688 | AG64: 3.52 | AH64: 3.8 | AI64: 4.867 | AJ64: 5.862 | AL64: Estonia | AM64: =IF(ISNUMBER(B64/B$27),B64/B$27,"…") -> … | AN64: =IF(ISNUMBER(C64/C$27),C64/C$27,"…") -> … | AO64: =IF(ISNUMBER(D64/D$27),D64/D$27,"…") -> … | AP64: =IF(ISNUMBER(E64/E$27),E64/E$27,"…") -> … | AQ64: =IF(ISNUMBER(F64/F$27),F64/F$27,"…") -> … | AR64: =IF(ISNUMBER(G64/G$27),G64/G$27,"…") -> … | AS64: =IF(ISNUMBER(H64/H$27),H64/H$27,"…") -> 0.65677966 | AT64: =IF(ISNUMBER(I64/I$27),I64/I$27,"…") -> 0.59566787 | ... BU64: =IF(ISNUMBER(AJ64/AJ$27),AJ64/AJ$27,"…") -> 0.76050856
A65: Iceland | B65: … | C65: … | D65: … | E65: … | F65: … | G65: … | H65: 135.543 | I65: 140.751 | J65: 140.882 | K65: 135.645 | L65: 138.882 | M65: 167.206 | N65: 239.843 | O65: 227.219 | P65: 220.857 | Q65: 212.383 | R65: 154.446 | S65: 244.482 | T65: 243.794 | U65: 532.3 | V65: 638.926 | W65: 491.942 | X65: 661.591 | Y65: 635.56 | Z65: 556.859 | AA65: 580.669 | AB65: 545.418 | AC65: 391.677 | AD65: 247.799 | AE65: 249.539 | AF65: 296.441 | AG65: 305.24 | AH65: 388.663 | AI65: 312.715 | AJ65: 289.044 | AL65: Iceland | AM65: =IF(ISNUMBER(B65/B$28),B65/B$28,"…") -> … | AN65: =IF(ISNUMBER(C65/C$28),C65/C$28,"…") -> … | AO65: =IF(ISNUMBER(D65/D$28),D65/D$28,"…") -> … | AP65: =IF(ISNUMBER(E65/E$28),E65/E$28,"…") -> … | AQ65: =IF(ISNUMBER(F65/F$28),F65/F$28,"…") -> … | AR65: =IF(ISNUMBER(G65/G$28),G65/G$28,"…") -> … | AS65: =IF(ISNUMBER(H65/H$28),H65/H$28,"…") -> 0.50649263 | AT65: =IF(ISNUMBER(I65/I$28),I65/I$28,"…") -> 0.51285312 | ... BU65: =IF(ISNUMBER(AJ65/AJ$28),AJ65/AJ$28,"…") -> 0.10746896
A66: Israel | B66: … | C66: … | D66: … | E66: … | F66: … | G66: … | H66: … | I66: … | J66: … | K66: 115.018 | L66: 115.701 | M66: 111.346 | N66: 119.442 | O66: 129.826 | P66: 129.87 | Q66: 134.011 | R66: 142.026 | S66: 139.372 | T66: 121.477 | U66: 105.812 | V66: 108.635 | W66: 99.838 | X66: 115.887 | Y66: 110.351 | Z66: 98.458 | AA66: 107.597 | AB66: 103.438 | AC66: 101.054 | AD66: 102.582 | AE66: 122.927 | AF66: 118.79 | AG66: 179.725 | AH66: 193.784 | AI66: 195.801 | AJ66: 217.58 | AL66: Israel | AM66: =IF(ISNUMBER(B66/B$29),B66/B$29,"…") -> … | AN66: =IF(ISNUMBER(C66/C$29),C66/C$29,"…") -> … | AO66: =IF(ISNUMBER(D66/D$29),D66/D$29,"…") -> … | AP66: =IF(ISNUMBER(E66/E$29),E66/E$29,"…") -> … | AQ66: =IF(ISNUMBER(F66/F$29),F66/F$29,"…") -> … | AR66: =IF(ISNUMBER(G66/G$29),G66/G$29,"…") -> … | AS66: =IF(ISNUMBER(H66/H$29),H66/H$29,"…") -> … | AT66: =IF(ISNUMBER(I66/I$29),I66/I$29,"…") -> … | ... BU66: =IF(ISNUMBER(AJ66/AJ$29),AJ66/AJ$29,"…") -> 0.19030975
A67: Latvia | B67: … | C67: … | D67: … | E67: 0.016 | F67: 0.096 | G67: 0.141 | H67: 0.182 | I67: 0.212 | J67: 0.249 | K67: 0.317 | L67: 0.833 | M67: 0.863 | N67: 1.087 | O67: 1.055 | P67: 0.68 | Q67: 0.841 | R67: 0.824 | S67: 0.882 | T67: 1.037 | U67: 2.291 | V67: 5.348 | W67: 6.82 | X67: 6.978 | Y67: 7.355 | Z67: 7.263 | AA67: 7.734 | AB67: 6.481 | AC67: 7.334 | AD67: 7.442 | AE67: 8.001 | AF67: 8.373 | AG67: 8.573 | AH67: 9.439 | AI67: 10.22 | AJ67: 11.714 | AL67: Latvia | AM67: =IF(ISNUMBER(B67/B$30),B67/B$30,"…") -> … | AN67: =IF(ISNUMBER(C67/C$30),C67/C$30,"…") -> … | AO67: =IF(ISNUMBER(D67/D$30),D67/D$30,"…") -> … | AP67: =IF(ISNUMBER(E67/E$30),E67/E$30,"…") -> … | AQ67: =IF(ISNUMBER(F67/F$30),F67/F$30,"…") -> … | AR67: =IF(ISNUMBER(G67/G$30),G67/G$30,"…") -> … | AS67: =IF(ISNUMBER(H67/H$30),H67/H$30,"…") -> 0.32442068 | AT67: =IF(ISNUMBER(I67/I$30),I67/I$30,"…") -> 0.33865815 | ... BU67: =IF(ISNUMBER(AJ67/AJ$30),AJ67/AJ$30,"…") -> 0.66636327
A68: Lithuania | B68: … | C68: … | D68: … | E68: 0.008 | F68: 0.127 | G68: 0.181 | H68: 0.684 | I68: 1.038 | J68: 1.089 | K68: 1.315 | L68: 2.095 | M68: 2.132 | N68: 2.127 | O68: 2.043 | P68: 2.106 | Q68: 2.142 | R68: 2.32 | S68: 2.96 | T68: 3.252 | U68: 3.232 | V68: 5.482 | W68: 7.662 | X68: 8.726 | Y68: 10.045 | Z68: 9.537 | AA68: 10.816 | AB68: 11.434 | AC68: 10.924 | AD68: 12.225 | AE68: 11.179 | AF68: 13.24 | AG68: 16.017 | AH68: 15.884 | AI68: 15.763 | AJ68: 17.412 | AL68: Lithuania | AM68: =IF(ISNUMBER(B68/B$31),B68/B$31,"…") -> … | AN68: =IF(ISNUMBER(C68/C$31),C68/C$31,"…") -> … | AO68: =IF(ISNUMBER(D68/D$31),D68/D$31,"…") -> … | AP68: =IF(ISNUMBER(E68/E$31),E68/E$31,"…") -> … | AQ68: =IF(ISNUMBER(F68/F$31),F68/F$31,"…") -> 0.2504931 | AR68: =IF(ISNUMBER(G68/G$31),G68/G$31,"…") -> 0.23691099 | AS68: =IF(ISNUMBER(H68/H$31),H68/H$31,"…") -> 0.76424581 | AT68: =IF(ISNUMBER(I68/I$31),I68/I$31,"…") -> 0.76775148 | ... BU68: =IF(ISNUMBER(AJ68/AJ$31),AJ68/AJ$31,"…") -> 0.63183105
A69: Luxembourg | B69: … | C69: … | D69: … | E69: … | F69: … | G69: … | H69: 0.044 | I69: 0.043 | J69: 0.042 | K69: 0.121 | L69: 0.12 | M69: 0.13 | N69: 0.129 | O69: 0.131 | P69: 0.13 | Q69: 0.086 | R69: 0.17 | S69: 0.201 | T69: 0.202 | U69: 1.1 | V69: 1.377 | W69: 2.763 | X69: 2.747 | Y69: 3.505 | Z69: 4.777 | AA69: 4.926 | AB69: 4.247 | AC69: 3.964 | AD69: 5.397 | AE69: 5.381 | AF69: 6.407 | AG69: 7.979 | AH69: 8.9 | AI69: 9.996 | AJ69: 11.588 | AL69: Luxembourg | AM69: =IF(ISNUMBER(B69/B$32),B69/B$32,"…") -> … | AN69: =IF(ISNUMBER(C69/C$32),C69/C$32,"…") -> … | AO69: =IF(ISNUMBER(D69/D$32),D69/D$32,"…") -> … | AP69: =IF(ISNUMBER(E69/E$32),E69/E$32,"…") -> … | AQ69: =IF(ISNUMBER(F69/F$32),F69/F$32,"…") -> … | AR69: =IF(ISNUMBER(G69/G$32),G69/G$32,"…") -> … | AS69: =IF(ISNUMBER(H69/H$32),H69/H$32,"…") -> 0.027329193 | AT69: =IF(ISNUMBER(I69/I$32),I69/I$32,"…") -> 0.026708075 | ... BU69: =IF(ISNUMBER(AJ69/AJ$32),AJ69/AJ$32,"…") -> 0.57190801
A70: Malta | B70: … | C70: … | D70: … | E70: … | F70: … | G70: … | H70: 0.162 | I70: 0.158 | J70: 0.159 | K70: 0.182 | L70: 0.429 | M70: 0.434 | N70: 0.421 | O70: 0.401 | P70: 0.401 | Q70: 0.433 | R70: 0.441 | S70: 0.391 | T70: 0.306 | U70: 0.456 | V70: 0.398 | W70: 0.371 | X70: 0.345 | Y70: 0.301 | Z70: 0.371 | AA70: 0.448 | AB70: 0.48 | AC70: 0.574 | AD70: 0.693 | AE70: 0.742 | AF70: 0.85 | AG70: 1.25 | AH70: 2.715 | AI70: 3.091 | AJ70: 3.776 | AL70: Malta | AM70: =IF(ISNUMBER(B70/B$33),B70/B$33,"…") -> … | AN70: =IF(ISNUMBER(C70/C$33),C70/C$33,"…") -> … | AO70: =IF(ISNUMBER(D70/D$33),D70/D$33,"…") -> … | AP70: =IF(ISNUMBER(E70/E$33),E70/E$33,"…") -> … | AQ70: =IF(ISNUMBER(F70/F$33),F70/F$33,"…") -> … | AR70: =IF(ISNUMBER(G70/G$33),G70/G$33,"…") -> … | AS70: =IF(ISNUMBER(H70/H$33),H70/H$33,"…") -> 0.16735537 | AT70: =IF(ISNUMBER(I70/I$33),I70/I$33,"…") -> 0.13423959 | ... BU70: =IF(ISNUMBER(AJ70/AJ$33),AJ70/AJ$33,"…") -> 0.3856603
A71: San Marino | B71: … | C71: … | D71: … | E71: … | F71: … | G71: … | H71: … | I71: … | J71: … | K71: … | L71: … | M71: … | N71: … | O71: … | P71: … | Q71: … | R71: … | S71: … | T71: … | U71: … | V71: … | W71: … | X71: … | Y71: … | Z71: … | AA71: … | AB71: … | AC71: … | AD71: … | AE71: … | AF71: … | AG71: … | AH71: … | AI71: … | AJ71: … | AL71: San Marino | AM71: =IF(ISNUMBER(B71/B$34),B71/B$34,"…") -> … | AN71: =IF(ISNUMBER(C71/C$34),C71/C$34,"…") -> … | AO71: =IF(ISNUMBER(D71/D$34),D71/D$34,"…") -> … | AP71: =IF(ISNUMBER(E71/E$34),E71/E$34,"…") -> … | AQ71: =IF(ISNUMBER(F71/F$34),F71/F$34,"…") -> … | AR71: =IF(ISNUMBER(G71/G$34),G71/G$34,"…") -> … | AS71: =IF(ISNUMBER(H71/H$34),H71/H$34,"…") -> … | AT71: =IF(ISNUMBER(I71/I$34),I71/I$34,"…") -> … | ... BU71: =IF(ISNUMBER(AJ71/AJ$34),AJ71/AJ$34,"…") -> …
A72: Singapore | B72: … | C72: … | D72: … | E72: … | F72: … | G72: … | H72: … | I72: … | J72: … | K72: … | L72: … | M72: … | N72: … | O72: … | P72: … | Q72: … | R72: … | S72: … | T72: … | U72: … | V72: … | W72: … | X72: … | Y72: … | Z72: … | AA72: … | AB72: … | AC72: … | AD72: … | AE72: … | AF72: … | AG72: … | AH72: … | AI72: … | AJ72: … | AL72: Singapore | AM72: =IF(ISNUMBER(B72/B$35),B72/B$35,"…") -> … | AN72: =IF(ISNUMBER(C72/C$35),C72/C$35,"…") -> … | AO72: =IF(ISNUMBER(D72/D$35),D72/D$35,"…") -> … | AP72: =IF(ISNUMBER(E72/E$35),E72/E$35,"…") -> … | AQ72: =IF(ISNUMBER(F72/F$35),F72/F$35,"…") -> … | AR72: =IF(ISNUMBER(G72/G$35),G72/G$35,"…") -> … | AS72: =IF(ISNUMBER(H72/H$35),H72/H$35,"…") -> … | AT72: =IF(ISNUMBER(I72/I$35),I72/I$35,"…") -> … | ... BU72: =IF(ISNUMBER(AJ72/AJ$35),AJ72/AJ$35,"…") -> …
A73: Slovak Republic | B73: … | C73: … | D73: … | E73: … | F73: … | G73: … | H73: 1.43 | I73: 1.798 | J73: 2.525 | K73: 3.573 | L73: 5.001 | M73: 6.487 | N73: 7.171 | O73: 6.427 | P73: 6.503 | Q73: 7.85 | R73: 6.861 | S73: 7.305 | T73: 7.266 | U73: 7.435 | V73: 8.016 | W73: 10.153 | X73: 12.238 | Y73: 17.77 | Z73: 24.638 | AA73: 24.692 | AB73: 22.026 | AC73: 22.246 | AD73: 24.911 | AE73: 25.472 | AF73: 26.033 | AG73: 29.686 | AH73: 29.135 | AI73: 29.456 | AJ73: 35.153 | AL73: Slovak Republic | AM73: =IF(ISNUMBER(B73/B$36),B73/B$36,"…") -> … | AN73: =IF(ISNUMBER(C73/C$36),C73/C$36,"…") -> … | AO73: =IF(ISNUMBER(D73/D$36),D73/D$36,"…") -> … | AP73: =IF(ISNUMBER(E73/E$36),E73/E$36,"…") -> … | AQ73: =IF(ISNUMBER(F73/F$36),F73/F$36,"…") -> … | AR73: =IF(ISNUMBER(G73/G$36),G73/G$36,"…") -> … | AS73: =IF(ISNUMBER(H73/H$36),H73/H$36,"…") -> 0.43215473 | AT73: =IF(ISNUMBER(I73/I$36),I73/I$36,"…") -> 0.35324165 | ... BU73: =IF(ISNUMBER(AJ73/AJ$36),AJ73/AJ$36,"…") -> 0.510218
A75: Foreign Official (Billion LC) | B75: =B38 -> 1989 | C75: =C38 -> 1990 | D75: =D38 -> 1991 | E75: =E38 -> 1992 | F75: =F38 -> 1993 | G75: =G38 -> 1994 | H75: =H38 -> 1995 | I75: =I38 -> 1996 | ... AJ75: =AJ38 -> 2023 | AL75: Foreign Official (% of Total Debt) | AM75: =AM38 -> 1989 | AN75: =AN38 -> 1990 | AO75: =AO38 -> 1991 | AP75: =AP38 -> 1992 | AQ75: =AQ38 -> 1993 | AR75: =AR38 -> 1994 | AS75: =AS38 -> 1995 | AT75: =AT38 -> 1996 | ... BU75: =BU38 -> 2023
A76: Australia | B76: 6.72 | C76: 10.545 | D76: 12.407 | E76: 9.932 | F76: 11.306 | G76: 11.07 | H76: 17.39 | I76: 16.867 | J76: 18.306 | K76: 23.079 | L76: 7.504 | M76: 8.831 | N76: 9.155 | O76: 11.498 | P76: 14.218 | Q76: ='Table 2.1 ForeignOfficial'!E2 -> 15.47 | R76: ='Table 2.1 ForeignOfficial'!I2 -> 18.039 | S76: ='Table 2.1 ForeignOfficial'!M2 -> 21.702 | T76: ='Table 2.1 ForeignOfficial'!Q2 -> 26.503 | U76: ='Table 2.1 ForeignOfficial'!U2 -> 37.789 | V76: ='Table 2.1 ForeignOfficial'!Y2 -> 48.435 | W76: ='Table 2.1 ForeignOfficial'!AC2 -> 72.59 | X76: ='Table 2.1 ForeignOfficial'!AG2 -> 92.509 | Y76: ='Table 2.1 ForeignOfficial'!AK2 -> 109.452 | Z76: ='Table 2.1 ForeignOfficial'!AO2 -> 176.218 | AA76: ='Table 2.1 ForeignOfficial'!AS2 -> 157.991 | AB76: ='Table 2.1 ForeignOfficial'!AW2 -> 187.686 | AC76: ='Table 2.1 ForeignOfficial'!BA2 -> 180.602 | AD76: ='Table 2.1 ForeignOfficial'!BE2 -> 192.365 | AE76: ='Table 2.1 ForeignOfficial'!BI2 -> 190.306 | AF76: ='Table 2.1 ForeignOfficial'!BM2 -> 196.252 | AG76: ='Table 2.1 ForeignOfficial'!BQ2 -> 211.336 | AH76: ='Table 2.1 ForeignOfficial'!BU2 -> 241.04 | AI76: ='Table 2.1 ForeignOfficial'!BY2 -> 292.996 | AJ76: ='Table 2.1 ForeignOfficial'!CC2 -> 318.617 | AL76: Australia | AM76: =IF(ISNUMBER(B76/B$2),B76/B$2,"…") -> 0.081783663 | AN76: =IF(ISNUMBER(C76/C$2),C76/C$2,"…") -> 0.12397714 | AO76: =IF(ISNUMBER(D76/D$2),D76/D$2,"…") -> 0.12302063 | AP76: =IF(ISNUMBER(E76/E$2),E76/E$2,"…") -> 0.082012155 | AQ76: =IF(ISNUMBER(F76/F$2),F76/F$2,"…") -> 0.077263191 | AR76: =IF(ISNUMBER(G76/G$2),G76/G$2,"…") -> 0.066669879 | AS76: =IF(ISNUMBER(H76/H$2),H76/H$2,"…") -> 0.10019763 | AT76: =IF(ISNUMBER(I76/I$2),I76/I$2,"…") -> 0.10108595 | ... BU76: =IF(ISNUMBER(AJ76/AJ$2),AJ76/AJ$2,"…") -> 0.24265191
A77: Austria | B77: 4.229 | C77: 4.678 | D77: 5.052 | E77: 5.077 | F77: 5.816 | G77: 5.988 | H77: 5.912 | I77: 6.181 | J77: 6.782 | K77: 4.964 | L77: 6.588 | M77: 7.898 | N77: 9.258 | O77: 7.904 | P77: 9.617 | Q77: ='Table 2.1 ForeignOfficial'!E3 -> 8.726 | R77: ='Table 2.1 ForeignOfficial'!I3 -> 14.064 | S77: ='Table 2.1 ForeignOfficial'!M3 -> 17.291 | T77: ='Table 2.1 ForeignOfficial'!Q3 -> 20.718 | U77: ='Table 2.1 ForeignOfficial'!U3 -> 39.262 | V77: ='Table 2.1 ForeignOfficial'!Y3 -> 33.176 | W77: ='Table 2.1 ForeignOfficial'!AC3 -> 47.454 | X77: ='Table 2.1 ForeignOfficial'!AG3 -> 54.65 | Y77: ='Table 2.1 ForeignOfficial'!AK3 -> 47.059 | Z77: ='Table 2.1 ForeignOfficial'!AO3 -> 38.347 | AA77: ='Table 2.1 ForeignOfficial'!AS3 -> 33.855 | AB77: ='Table 2.1 ForeignOfficial'!AW3 -> 40.327 | AC77: ='Table 2.1 ForeignOfficial'!BA3 -> 46.304 | AD77: ='Table 2.1 ForeignOfficial'!BE3 -> 49.538 | AE77: ='Table 2.1 ForeignOfficial'!BI3 -> 53.431 | AF77: ='Table 2.1 ForeignOfficial'!BM3 -> 51.46 | AG77: ='Table 2.1 ForeignOfficial'!BQ3 -> 59.561 | AH77: ='Table 2.1 ForeignOfficial'!BU3 -> 54.217 | AI77: ='Table 2.1 ForeignOfficial'!BY3 -> 70.89 | AJ77: ='Table 2.1 ForeignOfficial'!CC3 -> 66.185 | AL77: Austria | AM77: =IF(ISNUMBER(B77/B$3),B77/B$3,"…") -> 0.060328103 | AN77: =IF(ISNUMBER(C77/C$3),C77/C$3,"…") -> 0.063130904 | AO77: =IF(ISNUMBER(D77/D$3),D77/D$3,"…") -> 0.06315 | AP77: =IF(ISNUMBER(E77/E$3),E77/E$3,"…") -> 0.057824601 | AQ77: =IF(ISNUMBER(F77/F$3),F77/F$3,"…") -> 0.05856999 | AR77: =IF(ISNUMBER(G77/G$3),G77/G$3,"…") -> 0.053848921 | AS77: =IF(ISNUMBER(H77/H$3),H77/H$3,"…") -> 0.047182761 | AT77: =IF(ISNUMBER(I77/I$3),I77/I$3,"…") -> 0.04936901 | ... BU77: =IF(ISNUMBER(AJ77/AJ$3),AJ77/AJ$3,"…") -> 0.17804637
A78: Belgium | B78: 5.267 | C78: 5.828 | D78: 6.293 | E78: 6.324 | F78: 7.245 | G78: 7.458 | H78: 7.365 | I78: 7.699 | J78: 8.448 | K78: 6.183 | L78: 8.206 | M78: 9.838 | N78: 11.532 | O78: 10.044 | P78: 12.765 | Q78: ='Table 2.1 ForeignOfficial'!E4 -> 16.872 | R78: ='Table 2.1 ForeignOfficial'!I4 -> 23.924 | S78: ='Table 2.1 ForeignOfficial'!M4 -> 34.679 | T78: ='Table 2.1 ForeignOfficial'!Q4 -> 38.744 | U78: ='Table 2.1 ForeignOfficial'!U4 -> 52.789 | V78: ='Table 2.1 ForeignOfficial'!Y4 -> 65.159 | W78: ='Table 2.1 ForeignOfficial'!AC4 -> 63.192 | X78: ='Table 2.1 ForeignOfficial'!AG4 -> 58.516 | Y78: ='Table 2.1 ForeignOfficial'!AK4 -> 37.78 | Z78: ='Table 2.1 ForeignOfficial'!AO4 -> 42.723 | AA78: ='Table 2.1 ForeignOfficial'!AS4 -> 48.899 | AB78: ='Table 2.1 ForeignOfficial'!AW4 -> 50.944 | AC78: ='Table 2.1 ForeignOfficial'!BA4 -> 52.118 | AD78: ='Table 2.1 ForeignOfficial'!BE4 -> 55.681 | AE78: ='Table 2.1 ForeignOfficial'!BI4 -> 51.466 | AF78: ='Table 2.1 ForeignOfficial'!BM4 -> 62.891 | AG78: ='Table 2.1 ForeignOfficial'!BQ4 -> 63.116 | AH78: ='Table 2.1 ForeignOfficial'!BU4 -> 71.032 | AI78: ='Table 2.1 ForeignOfficial'!BY4 -> 83.917 | AJ78: ='Table 2.1 ForeignOfficial'!CC4 -> 76.82 | AL78: Belgium | AM78: =IF(ISNUMBER(B78/B$4),B78/B$4,"…") -> 0.028226152 | AN78: =IF(ISNUMBER(C78/C$4),C78/C$4,"…") -> 0.028291262 | AO78: =IF(ISNUMBER(D78/D$4),D78/D$4,"…") -> 0.028682771 | AP78: =IF(ISNUMBER(E78/E$4),E78/E$4,"…") -> 0.025971253 | AQ78: =IF(ISNUMBER(F78/F$4),F78/F$4,"…") -> 0.02776926 | AR78: =IF(ISNUMBER(G78/G$4),G78/G$4,"…") -> 0.026759957 | AS78: =IF(ISNUMBER(H78/H$4),H78/H$4,"…") -> 0.02556404 | AT78: =IF(ISNUMBER(I78/I$4),I78/I$4,"…") -> 0.027684286 | ... BU78: =IF(ISNUMBER(AJ78/AJ$4),AJ78/AJ$4,"…") -> 0.1249124
A79: Canada | B79: 6.042 | C79: 9.26 | D79: 10.664 | E79: 8.51 | F79: 9.906 | G79: 11.802 | H79: 17.301 | I79: 18.027 | J79: 16.734 | K79: 21.269 | L79: 7.7 | M79: 8.066 | N79: 8.001 | O79: 11.243 | P79: 14.753 | Q79: ='Table 2.1 ForeignOfficial'!E5 -> 15.791 | R79: ='Table 2.1 ForeignOfficial'!I5 -> 16.403 | S79: ='Table 2.1 ForeignOfficial'!M5 -> 20.544 | T79: ='Table 2.1 ForeignOfficial'!Q5 -> 22.856 | U79: ='Table 2.1 ForeignOfficial'!U5 -> 36.851 | V79: ='Table 2.1 ForeignOfficial'!Y5 -> 46.147 | W79: ='Table 2.1 ForeignOfficial'!AC5 -> 73.506 | X79: ='Table 2.1 ForeignOfficial'!AG5 -> 103.499 | Y79: ='Table 2.1 ForeignOfficial'!AK5 -> 124.24 | Z79: ='Table 2.1 ForeignOfficial'!AO5 -> 181.966 | AA79: ='Table 2.1 ForeignOfficial'!AS5 -> 188.506 | AB79: ='Table 2.1 ForeignOfficial'!AW5 -> 214.812 | AC79: ='Table 2.1 ForeignOfficial'!BA5 -> 223.182 | AD79: ='Table 2.1 ForeignOfficial'!BE5 -> 232.803 | AE79: ='Table 2.1 ForeignOfficial'!BI5 -> 229.405 | AF79: ='Table 2.1 ForeignOfficial'!BM5 -> 229.818 | AG79: ='Table 2.1 ForeignOfficial'!BQ5 -> 271.494 | AH79: ='Table 2.1 ForeignOfficial'!BU5 -> 316.766 | AI79: ='Table 2.1 ForeignOfficial'!BY5 -> 309.655 | AJ79: ='Table 2.1 ForeignOfficial'!CC5 -> 338.991 | AL79: Canada | AM79: =IF(ISNUMBER(B79/B$5),B79/B$5,"…") -> 0.012126881 | AN79: =IF(ISNUMBER(C79/C$5),C79/C$5,"…") -> 0.017130193 | AO79: =IF(ISNUMBER(D79/D$5),D79/D$5,"…") -> 0.017870998 | AP79: =IF(ISNUMBER(E79/E$5),E79/E$5,"…") -> 0.013068643 | AQ79: =IF(ISNUMBER(F79/F$5),F79/F$5,"…") -> 0.013861583 | AR79: =IF(ISNUMBER(G79/G$5),G79/G$5,"…") -> 0.015339983 | AS79: =IF(ISNUMBER(H79/H$5),H79/H$5,"…") -> 0.021364323 | AT79: =IF(ISNUMBER(I79/I$5),I79/I$5,"…") -> 0.021712606 | ... BU79: =IF(ISNUMBER(AJ79/AJ$5),AJ79/AJ$5,"…") -> 0.12312059
A80: Czech Republic | B80: … | C80: … | D80: … | E80: … | F80: 0 | G80: 0 | H80: 0 | I80: 0 | J80: 0 | K80: 0 | L80: 0 | M80: 0 | N80: 0.1 | O80: 2.5 | P80: 11.7 | Q80: ='Table 2.1 ForeignOfficial'!E6 -> 20.7 | R80: ='Table 2.1 ForeignOfficial'!I6 -> 29.7 | S80: ='Table 2.1 ForeignOfficial'!M6 -> 36.7 | T80: ='Table 2.1 ForeignOfficial'!Q6 -> 38.7 | U80: ='Table 2.1 ForeignOfficial'!U6 -> 46.8 | V80: ='Table 2.1 ForeignOfficial'!Y6 -> 57.9 | W80: ='Table 2.1 ForeignOfficial'!AC6 -> 67.2 | X80: ='Table 2.1 ForeignOfficial'!AG6 -> 71.3 | Y80: ='Table 2.1 ForeignOfficial'!AK6 -> 82.572 | Z80: ='Table 2.1 ForeignOfficial'!AO6 -> 85.531 | AA80: ='Table 2.1 ForeignOfficial'!AS6 -> 77.055 | AB80: ='Table 2.1 ForeignOfficial'!AW6 -> 129.699 | AC80: ='Table 2.1 ForeignOfficial'!BA6 -> 170.172 | AD80: ='Table 2.1 ForeignOfficial'!BE6 -> 131.501 | AE80: ='Table 2.1 ForeignOfficial'!BI6 -> 66.147 | AF80: ='Table 2.1 ForeignOfficial'!BM6 -> 61.273 | AG80: ='Table 2.1 ForeignOfficial'!BQ6 -> 58.384 | AH80: ='Table 2.1 ForeignOfficial'!BU6 -> 109.478 | AI80: ='Table 2.1 ForeignOfficial'!BY6 -> 167.095 | AJ80: ='Table 2.1 ForeignOfficial'!CC6 -> 174.857 | AL80: Czech Republic | AM80: =IF(ISNUMBER(B80/B$6),B80/B$6,"…") -> … | AN80: =IF(ISNUMBER(C80/C$6),C80/C$6,"…") -> … | AO80: =IF(ISNUMBER(D80/D$6),D80/D$6,"…") -> … | AP80: =IF(ISNUMBER(E80/E$6),E80/E$6,"…") -> … | AQ80: =IF(ISNUMBER(F80/F$6),F80/F$6,"…") -> … | AR80: =IF(ISNUMBER(G80/G$6),G80/G$6,"…") -> … | AS80: =IF(ISNUMBER(H80/H$6),H80/H$6,"…") -> 0 | AT80: =IF(ISNUMBER(I80/I$6),I80/I$6,"…") -> 0 | ... BU80: =IF(ISNUMBER(AJ80/AJ$6),AJ80/AJ$6,"…") -> 0.054068303
A81: Denmark | B81: … | C81: … | D81: … | E81: … | F81: … | G81: … | H81: … | I81: … | J81: … | K81: … | L81: … | M81: … | N81: 80.725 | O81: 56.763 | P81: 56.703 | Q81: ='Table 2.1 ForeignOfficial'!E7 -> 75.917 | R81: ='Table 2.1 ForeignOfficial'!I7 -> 68.862 | S81: ='Table 2.1 ForeignOfficial'!M7 -> 63.968 | T81: ='Table 2.1 ForeignOfficial'!Q7 -> 53.403 | U81: ='Table 2.1 ForeignOfficial'!U7 -> 62.506 | V81: ='Table 2.1 ForeignOfficial'!Y7 -> 134.554 | W81: ='Table 2.1 ForeignOfficial'!AC7 -> 113.44 | X81: ='Table 2.1 ForeignOfficial'!AG7 -> 160.287 | Y81: ='Table 2.1 ForeignOfficial'!AK7 -> 185.904 | Z81: ='Table 2.1 ForeignOfficial'!AO7 -> 174.863 | AA81: ='Table 2.1 ForeignOfficial'!AS7 -> 221.379 | AB81: ='Table 2.1 ForeignOfficial'!AW7 -> 196.536 | AC81: ='Table 2.1 ForeignOfficial'!BA7 -> 225.298 | AD81: ='Table 2.1 ForeignOfficial'!BE7 -> 199.096 | AE81: ='Table 2.1 ForeignOfficial'!BI7 -> 173.078 | AF81: ='Table 2.1 ForeignOfficial'!BM7 -> 169.875 | AG81: ='Table 2.1 ForeignOfficial'!BQ7 -> 245.432 | AH81: ='Table 2.1 ForeignOfficial'!BU7 -> 169.744 | AI81: ='Table 2.1 ForeignOfficial'!BY7 -> 140.667 | AJ81: ='Table 2.1 ForeignOfficial'!CC7 -> 150.235 | AL81: Denmark | AM81: =IF(ISNUMBER(B81/B$7),B81/B$7,"…") -> … | AN81: =IF(ISNUMBER(C81/C$7),C81/C$7,"…") -> … | AO81: =IF(ISNUMBER(D81/D$7),D81/D$7,"…") -> … | AP81: =IF(ISNUMBER(E81/E$7),E81/E$7,"…") -> … | AQ81: =IF(ISNUMBER(F81/F$7),F81/F$7,"…") -> … | AR81: =IF(ISNUMBER(G81/G$7),G81/G$7,"…") -> … | AS81: =IF(ISNUMBER(H81/H$7),H81/H$7,"…") -> … | AT81: =IF(ISNUMBER(I81/I$7),I81/I$7,"…") -> … | ... BU81: =IF(ISNUMBER(AJ81/AJ$7),AJ81/AJ$7,"…") -> 0.15947278
A82: Finland | B82: 1.891 | C82: 2.092 | D82: 2.259 | E82: 2.27 | F82: 2.6 | G82: 2.677 | H82: 2.643 | I82: 2.763 | J82: 3.032 | K82: 2.219 | L82: 2.945 | M82: 3.531 | N82: 4.139 | O82: 4.349 | P82: 4.812 | Q82: ='Table 2.1 ForeignOfficial'!E8 -> 5.409 | R82: ='Table 2.1 ForeignOfficial'!I8 -> 6.812 | S82: ='Table 2.1 ForeignOfficial'!M8 -> 11.037 | T82: ='Table 2.1 ForeignOfficial'!Q8 -> 22.034 | U82: ='Table 2.1 ForeignOfficial'!U8 -> 14.984 | V82: ='Table 2.1 ForeignOfficial'!Y8 -> 15.769 | W82: ='Table 2.1 ForeignOfficial'!AC8 -> 25.654 | X82: ='Table 2.1 ForeignOfficial'!AG8 -> 22.956 | Y82: ='Table 2.1 ForeignOfficial'!AK8 -> 22.736 | Z82: ='Table 2.1 ForeignOfficial'!AO8 -> 37.546 | AA82: ='Table 2.1 ForeignOfficial'!AS8 -> 34.894 | AB82: ='Table 2.1 ForeignOfficial'!AW8 -> 26.835 | AC82: ='Table 2.1 ForeignOfficial'!BA8 -> 31.236 | AD82: ='Table 2.1 ForeignOfficial'!BE8 -> 32.886 | AE82: ='Table 2.1 ForeignOfficial'!BI8 -> 36.831 | AF82: ='Table 2.1 ForeignOfficial'!BM8 -> 37.36 | AG82: ='Table 2.1 ForeignOfficial'!BQ8 -> 44.623 | AH82: ='Table 2.1 ForeignOfficial'!BU8 -> 41.484 | AI82: ='Table 2.1 ForeignOfficial'!BY8 -> 51.933 | AJ82: ='Table 2.1 ForeignOfficial'!CC8 -> 55.579 | AL82: Finland | AM82: =IF(ISNUMBER(B82/B$8),B82/B$8,"…") -> 0.12606667 | AN82: =IF(ISNUMBER(C82/C$8),C82/C$8,"…") -> 0.13854305 | AO82: =IF(ISNUMBER(D82/D$8),D82/D$8,"…") -> 0.11073529 | AP82: =IF(ISNUMBER(E82/E$8),E82/E$8,"…") -> 0.07275641 | AQ82: =IF(ISNUMBER(F82/F$8),F82/F$8,"…") -> 0.06088993 | AR82: =IF(ISNUMBER(G82/G$8),G82/G$8,"…") -> 0.051480769 | AS82: =IF(ISNUMBER(H82/H$8),H82/H$8,"…") -> 0.046778761 | AT82: =IF(ISNUMBER(I82/I$8),I82/I$8,"…") -> 0.047885615 | ... BU82: =IF(ISNUMBER(AJ82/AJ$8),AJ82/AJ$8,"…") -> 0.26357497
A83: France | B83: 32.463 | C83: 35.915 | D83: 38.786 | E83: 38.974 | F83: 44.649 | G83: 45.967 | H83: 45.389 | I83: 47.449 | J83: 52.065 | K83: 38.106 | L83: 50.574 | M83: 60.63 | N83: 71.07 | O83: 125.475 | P83: 163.84 | Q83: ='Table 2.1 ForeignOfficial'!E9 -> 131.225 | R83: ='Table 2.1 ForeignOfficial'!I9 -> 157.237 | S83: ='Table 2.1 ForeignOfficial'!M9 -> 161.584 | T83: ='Table 2.1 ForeignOfficial'!Q9 -> 163.727 | U83: ='Table 2.1 ForeignOfficial'!U9 -> 180.209 | V83: ='Table 2.1 ForeignOfficial'!Y9 -> 263.362 | W83: ='Table 2.1 ForeignOfficial'!AC9 -> 349.271 | X83: ='Table 2.1 ForeignOfficial'!AG9 -> 432.521 | Y83: ='Table 2.1 ForeignOfficial'!AK9 -> 413.135 | Z83: ='Table 2.1 ForeignOfficial'!AO9 -> 403.546 | AA83: ='Table 2.1 ForeignOfficial'!AS9 -> 382.343 | AB83: ='Table 2.1 ForeignOfficial'!AW9 -> 354.481 | AC83: ='Table 2.1 ForeignOfficial'!BA9 -> 347.246 | AD83: ='Table 2.1 ForeignOfficial'!BE9 -> 347.739 | AE83: ='Table 2.1 ForeignOfficial'!BI9 -> 419.268 | AF83: ='Table 2.1 ForeignOfficial'!BM9 -> 439.102 | AG83: ='Table 2.1 ForeignOfficial'!BQ9 -> 462.187 | AH83: ='Table 2.1 ForeignOfficial'!BU9 -> 504.06 | AI83: ='Table 2.1 ForeignOfficial'!BY9 -> 586.131 | AJ83: ='Table 2.1 ForeignOfficial'!CC9 -> 577.336 | AL83: France | AM83: =IF(ISNUMBER(B83/B$9),B83/B$9,"…") -> 0.097165519 | AN83: =IF(ISNUMBER(C83/C$9),C83/C$9,"…") -> 0.098966657 | AO83: =IF(ISNUMBER(D83/D$9),D83/D$9,"…") -> 0.10095263 | AP83: =IF(ISNUMBER(E83/E$9),E83/E$9,"…") -> 0.085133246 | AQ83: =IF(ISNUMBER(F83/F$9),F83/F$9,"…") -> 0.082150874 | AR83: =IF(ISNUMBER(G83/G$9),G83/G$9,"…") -> 0.076446034 | AS83: =IF(ISNUMBER(H83/H$9),H83/H$9,"…") -> 0.063507765 | AT83: =IF(ISNUMBER(I83/I$9),I83/I$9,"…") -> 0.062821395 | ... BU83: =IF(ISNUMBER(AJ83/AJ$9),AJ83/AJ$9,"…") -> 0.18615479
A84: Germany | B84: 85.535 | C84: 94.631 | D84: 102.194 | E84: 102.691 | F84: 117.643 | G84: 121.115 | H84: 119.594 | I84: 125.022 | J84: 137.183 | K84: 100.403 | L84: 133.253 | M84: 159.75 | N84: 245.794 | O84: 256.978 | P84: 265.032 | Q84: ='Table 2.1 ForeignOfficial'!E10 -> 302.455 | R84: ='Table 2.1 ForeignOfficial'!I10 -> 360.504 | S84: ='Table 2.1 ForeignOfficial'!M10 -> 431.684 | T84: ='Table 2.1 ForeignOfficial'!Q10 -> 565.945 | U84: ='Table 2.1 ForeignOfficial'!U10 -> 536.364 | V84: ='Table 2.1 ForeignOfficial'!Y10 -> 528.275 | W84: ='Table 2.1 ForeignOfficial'!AC10 -> 587.664 | X84: ='Table 2.1 ForeignOfficial'!AG10 -> 580.956 | Y84: ='Table 2.1 ForeignOfficial'!AK10 -> 681.121 | Z84: ='Table 2.1 ForeignOfficial'!AO10 -> 773.425 | AA84: ='Table 2.1 ForeignOfficial'!AS10 -> 653.829 | AB84: ='Table 2.1 ForeignOfficial'!AW10 -> 627.597 | AC84: ='Table 2.1 ForeignOfficial'!BA10 -> 688.606 | AD84: ='Table 2.1 ForeignOfficial'!BE10 -> 691.205 | AE84: ='Table 2.1 ForeignOfficial'!BI10 -> 746.416 | AF84: ='Table 2.1 ForeignOfficial'!BM10 -> 742.863 | AG84: ='Table 2.1 ForeignOfficial'!BQ10 -> 720.047 | AH84: ='Table 2.1 ForeignOfficial'!BU10 -> 751.232 | AI84: ='Table 2.1 ForeignOfficial'!BY10 -> 743.215 | AJ84: ='Table 2.1 ForeignOfficial'!CC10 -> 750.765 | AL84: Germany | AM84: =IF(ISNUMBER(B84/B$10),B84/B$10,"…") -> 0.1839858 | AN84: =IF(ISNUMBER(C84/C$10),C84/C$10,"…") -> 0.17939526 | AO84: =IF(ISNUMBER(D84/D$10),D84/D$10,"…") -> 0.17318082 | AP84: =IF(ISNUMBER(E84/E$10),E84/E$10,"…") -> 0.14647126 | AQ84: =IF(ISNUMBER(F84/F$10),F84/F$10,"…") -> 0.14812768 | AR84: =IF(ISNUMBER(G84/G$10),G84/G$10,"…") -> 0.13636005 | AS84: =IF(ISNUMBER(H84/H$10),H84/H$10,"…") -> 0.11074544 | AT84: =IF(ISNUMBER(I84/I$10),I84/I$10,"…") -> 0.112057 | ... BU84: =IF(ISNUMBER(AJ84/AJ$10),AJ84/AJ$10,"…") -> 0.28526923
A85: Greece | B85: … | C85: … | D85: … | E85: … | F85: … | G85: … | H85: … | I85: … | J85: … | K85: … | L85: … | M85: … | N85: … | O85: … | P85: 12.702 | Q85: ='Table 2.1 ForeignOfficial'!E11 -> 17.865 | R85: ='Table 2.1 ForeignOfficial'!I11 -> 15.183 | S85: ='Table 2.1 ForeignOfficial'!M11 -> 16.273 | T85: ='Table 2.1 ForeignOfficial'!Q11 -> 17.178 | U85: ='Table 2.1 ForeignOfficial'!U11 -> 15.004 | V85: ='Table 2.1 ForeignOfficial'!Y11 -> 12.303 | W85: ='Table 2.1 ForeignOfficial'!AC11 -> 84.177 | X85: ='Table 2.1 ForeignOfficial'!AG11 -> 125.035 | Y85: ='Table 2.1 ForeignOfficial'!AK11 -> 227.682 | Z85: ='Table 2.1 ForeignOfficial'!AO11 -> 251.397 | AA85: ='Table 2.1 ForeignOfficial'!AS11 -> 247.81 | AB85: ='Table 2.1 ForeignOfficial'!AW11 -> 247.956 | AC85: ='Table 2.1 ForeignOfficial'!BA11 -> 253.417 | AD85: ='Table 2.1 ForeignOfficial'!BE11 -> 255.287 | AE85: ='Table 2.1 ForeignOfficial'!BI11 -> 273.87 | AF85: ='Table 2.1 ForeignOfficial'!BM11 -> 265.033 | AG85: ='Table 2.1 ForeignOfficial'!BQ11 -> 266.337 | AH85: ='Table 2.1 ForeignOfficial'!BU11 -> 267.401 | AI85: ='Table 2.1 ForeignOfficial'!BY11 -> 262.679 | AJ85: ='Table 2.1 ForeignOfficial'!CC11 -> 259.156 | AL85: Greece | AM85: =IF(ISNUMBER(B85/B$11),B85/B$11,"…") -> … | AN85: =IF(ISNUMBER(C85/C$11),C85/C$11,"…") -> … | AO85: =IF(ISNUMBER(D85/D$11),D85/D$11,"…") -> … | AP85: =IF(ISNUMBER(E85/E$11),E85/E$11,"…") -> … | AQ85: =IF(ISNUMBER(F85/F$11),F85/F$11,"…") -> … | AR85: =IF(ISNUMBER(G85/G$11),G85/G$11,"…") -> … | AS85: =IF(ISNUMBER(H85/H$11),H85/H$11,"…") -> … | AT85: =IF(ISNUMBER(I85/I$11),I85/I$11,"…") -> … | ... BU85: =IF(ISNUMBER(AJ85/AJ$11),AJ85/AJ$11,"…") -> 0.70213141
A86: Ireland | B86: … | C86: … | D86: … | E86: … | F86: … | G86: … | H86: … | I86: … | J86: … | K86: … | L86: … | M86: … | N86: … | O86: 4.48 | P86: 3.559 | Q86: ='Table 2.1 ForeignOfficial'!E12 -> 5.429 | R86: ='Table 2.1 ForeignOfficial'!I12 -> 15.389 | S86: ='Table 2.1 ForeignOfficial'!M12 -> 19.952 | T86: ='Table 2.1 ForeignOfficial'!Q12 -> 23.558 | U86: ='Table 2.1 ForeignOfficial'!U12 -> 30.361 | V86: ='Table 2.1 ForeignOfficial'!Y12 -> 25.42 | W86: ='Table 2.1 ForeignOfficial'!AC12 -> 33.521 | X86: ='Table 2.1 ForeignOfficial'!AG12 -> 66.61 | Y86: ='Table 2.1 ForeignOfficial'!AK12 -> 83.337 | Z86: ='Table 2.1 ForeignOfficial'!AO12 -> 85.394 | AA86: ='Table 2.1 ForeignOfficial'!AS12 -> 82.02 | AB86: ='Table 2.1 ForeignOfficial'!AW12 -> 77.734 | AC86: ='Table 2.1 ForeignOfficial'!BA12 -> 74.779 | AD86: ='Table 2.1 ForeignOfficial'!BE12 -> 69.821 | AE86: ='Table 2.1 ForeignOfficial'!BI12 -> 71.397 | AF86: ='Table 2.1 ForeignOfficial'!BM12 -> 68.66 | AG86: ='Table 2.1 ForeignOfficial'!BQ12 -> 65.632 | AH86: ='Table 2.1 ForeignOfficial'!BU12 -> 74.125 | AI86: ='Table 2.1 ForeignOfficial'!BY12 -> 74.117 | AJ86: ='Table 2.1 ForeignOfficial'!CC12 -> 68.809 | AL86: Ireland | AM86: =IF(ISNUMBER(B86/B$12),B86/B$12,"…") -> … | AN86: =IF(ISNUMBER(C86/C$12),C86/C$12,"…") -> … | AO86: =IF(ISNUMBER(D86/D$12),D86/D$12,"…") -> … | AP86: =IF(ISNUMBER(E86/E$12),E86/E$12,"…") -> … | AQ86: =IF(ISNUMBER(F86/F$12),F86/F$12,"…") -> … | AR86: =IF(ISNUMBER(G86/G$12),G86/G$12,"…") -> … | AS86: =IF(ISNUMBER(H86/H$12),H86/H$12,"…") -> … | AT86: =IF(ISNUMBER(I86/I$12),I86/I$12,"…") -> … | ... BU86: =IF(ISNUMBER(AJ86/AJ$12),AJ86/AJ$12,"…") -> 0.31174227
A87: Italy | B87: 14.839 | C87: 16.417 | D87: 17.73 | E87: 17.816 | F87: 20.41 | G87: 21.012 | H87: 20.748 | I87: 21.69 | J87: 23.8 | K87: 17.419 | L87: 23.118 | M87: 27.715 | N87: 32.487 | O87: 33.843 | P87: 29.411 | Q87: ='Table 2.1 ForeignOfficial'!E13 -> 39.375 | R87: ='Table 2.1 ForeignOfficial'!I13 -> 38.757 | S87: ='Table 2.1 ForeignOfficial'!M13 -> 44.672 | T87: ='Table 2.1 ForeignOfficial'!Q13 -> 39.633 | U87: ='Table 2.1 ForeignOfficial'!U13 -> 54.958 | V87: ='Table 2.1 ForeignOfficial'!Y13 -> 70.137 | W87: ='Table 2.1 ForeignOfficial'!AC13 -> 64.779 | X87: ='Table 2.1 ForeignOfficial'!AG13 -> 146.291 | Y87: ='Table 2.1 ForeignOfficial'!AK13 -> 136.039 | Z87: ='Table 2.1 ForeignOfficial'!AO13 -> 110.249 | AA87: ='Table 2.1 ForeignOfficial'!AS13 -> 96.866 | AB87: ='Table 2.1 ForeignOfficial'!AW13 -> 121.418 | AC87: ='Table 2.1 ForeignOfficial'!BA13 -> 131.693 | AD87: ='Table 2.1 ForeignOfficial'!BE13 -> 149.543 | AE87: ='Table 2.1 ForeignOfficial'!BI13 -> 155.255 | AF87: ='Table 2.1 ForeignOfficial'!BM13 -> 150.025 | AG87: ='Table 2.1 ForeignOfficial'!BQ13 -> 175.449 | AH87: ='Table 2.1 ForeignOfficial'!BU13 -> 222.158 | AI87: ='Table 2.1 ForeignOfficial'!BY13 -> 225.418 | AJ87: ='Table 2.1 ForeignOfficial'!CC13 -> 188.714 | AL87: Italy | AM87: =IF(ISNUMBER(B87/B$13),B87/B$13,"…") -> 0.019656908 | AN87: =IF(ISNUMBER(C87/C$13),C87/C$13,"…") -> 0.019553359 | AO87: =IF(ISNUMBER(D87/D$13),D87/D$13,"…") -> 0.018706478 | AP87: =IF(ISNUMBER(E87/E$13),E87/E$13,"…") -> 0.019350494 | AQ87: =IF(ISNUMBER(F87/F$13),F87/F$13,"…") -> 0.020978518 | AR87: =IF(ISNUMBER(G87/G$13),G87/G$13,"…") -> 0.020268159 | AS87: =IF(ISNUMBER(H87/H$13),H87/H$13,"…") -> 0.018920299 | AT87: =IF(ISNUMBER(I87/I$13),I87/I$13,"…") -> 0.017208823 | ... BU87: =IF(ISNUMBER(AJ87/AJ$13),AJ87/AJ$13,"…") -> 0.065790432
A88: Japan | B88: 6524.177 | C88: 8798.286 | D88: 9334.229 | E88: 8274.375 | F88: 7957.283 | G88: 8108.789 | H88: 7738.918 | I88: 9756.343 | J88: 8902.063 | K88: 8933.067 | L88: 8743.468 | M88: 10315.914 | N88: 10459.041 | O88: 10937.68 | P88: 11237.271 | Q88: ='Table 2.1 ForeignOfficial'!E14 -> 13179.534 | R88: ='Table 2.1 ForeignOfficial'!I14 -> 15976.752 | S88: ='Table 2.1 ForeignOfficial'!M14 -> 17055.355 | T88: ='Table 2.1 ForeignOfficial'!Q14 -> 19240.569 | U88: ='Table 2.1 ForeignOfficial'!U14 -> 18091.428 | V88: ='Table 2.1 ForeignOfficial'!Y14 -> 17133.412 | W88: ='Table 2.1 ForeignOfficial'!AC14 -> 21625.782 | X88: ='Table 2.1 ForeignOfficial'!AG14 -> 22345.235 | Y88: ='Table 2.1 ForeignOfficial'!AK14 -> 30186.182 | Z88: ='Table 2.1 ForeignOfficial'!AO14 -> 36554.728 | AA88: ='Table 2.1 ForeignOfficial'!AS14 -> 37766.679 | AB88: ='Table 2.1 ForeignOfficial'!AW14 -> 37632.756 | AC88: ='Table 2.1 ForeignOfficial'!BA14 -> 37144.366 | AD88: ='Table 2.1 ForeignOfficial'!BE14 -> 47800.85 | AE88: ='Table 2.1 ForeignOfficial'!BI14 -> 49650.393 | AF88: ='Table 2.1 ForeignOfficial'!BM14 -> 56777.955 | AG88: ='Table 2.1 ForeignOfficial'!BQ14 -> 60450 | AH88: ='Table 2.1 ForeignOfficial'!BU14 -> 62449.655 | AI88: ='Table 2.1 ForeignOfficial'!BY14 -> 70223.216 | AJ88: ='Table 2.1 ForeignOfficial'!CC14 -> 80162.722 | AL88: Japan | AM88: =IF(ISNUMBER(B88/B$14),B88/B$14,"…") -> 0.029345261 | AN88: =IF(ISNUMBER(C88/C$14),C88/C$14,"…") -> 0.038224166 | AO88: =IF(ISNUMBER(D88/D$14),D88/D$14,"…") -> 0.038584239 | AP88: =IF(ISNUMBER(E88/E$14),E88/E$14,"…") -> 0.031151081 | AQ88: =IF(ISNUMBER(F88/F$14),F88/F$14,"…") -> 0.027441677 | AR88: =IF(ISNUMBER(G88/G$14),G88/G$14,"…") -> 0.02410641 | AS88: =IF(ISNUMBER(H88/H$14),H88/H$14,"…") -> 0.019952764 | AT88: =IF(ISNUMBER(I88/I$14),I88/I$14,"…") -> 0.023272968 | ... BU88: =IF(ISNUMBER(AJ88/AJ$14),AJ88/AJ$14,"…") -> 0.061776232
A89: Korea | B89: … | C89: … | D89: … | E89: … | F89: … | G89: 5632.58 | H89: 5109.456 | I89: 5030.503 | J89: 14836.391 | K89: 18565.698 | L89: 21980.226 | M89: 23635.751 | N89: 23714.514 | O89: 20001.425 | P89: 12337.699 | Q89: ='Table 2.1 ForeignOfficial'!E15 -> 8499.35 | R89: ='Table 2.1 ForeignOfficial'!I15 -> 5519.128 | S89: ='Table 2.1 ForeignOfficial'!M15 -> 5414.439 | T89: ='Table 2.1 ForeignOfficial'!Q15 -> 5673.101 | U89: ='Table 2.1 ForeignOfficial'!U15 -> 7576.165 | V89: ='Table 2.1 ForeignOfficial'!Y15 -> 9037.958 | W89: ='Table 2.1 ForeignOfficial'!AC15 -> 11970.999 | X89: ='Table 2.1 ForeignOfficial'!AG15 -> 18938.128 | Y89: ='Table 2.1 ForeignOfficial'!AK15 -> 25378.075 | Z89: ='Table 2.1 ForeignOfficial'!AO15 -> 31729.682 | AA89: ='Table 2.1 ForeignOfficial'!AS15 -> 48135.822 | AB89: ='Table 2.1 ForeignOfficial'!AW15 -> 55338.714 | AC89: ='Table 2.1 ForeignOfficial'!BA15 -> 63200.132 | AD89: ='Table 2.1 ForeignOfficial'!BE15 -> 64851.065 | AE89: ='Table 2.1 ForeignOfficial'!BI15 -> 78277.886 | AF89: ='Table 2.1 ForeignOfficial'!BM15 -> 90946.706 | AG89: ='Table 2.1 ForeignOfficial'!BQ15 -> 92194.188 | AH89: ='Table 2.1 ForeignOfficial'!BU15 -> 118461.93 | AI89: ='Table 2.1 ForeignOfficial'!BY15 -> 129080.36 | AJ89: ='Table 2.1 ForeignOfficial'!CC15 -> 134055.2 | AL89: Korea | AM89: =IF(ISNUMBER(B89/B$15),B89/B$15,"…") -> … | AN89: =IF(ISNUMBER(C89/C$15),C89/C$15,"…") -> … | AO89: =IF(ISNUMBER(D89/D$15),D89/D$15,"…") -> … | AP89: =IF(ISNUMBER(E89/E$15),E89/E$15,"…") -> … | AQ89: =IF(ISNUMBER(F89/F$15),F89/F$15,"…") -> … | AR89: =IF(ISNUMBER(G89/G$15),G89/G$15,"…") -> 0.21091658 | AS89: =IF(ISNUMBER(H89/H$15),H89/H$15,"…") -> 0.18984735 | AT89: =IF(ISNUMBER(I89/I$15),I89/I$15,"…") -> 0.18246562 | ... BU89: =IF(ISNUMBER(AJ89/AJ$15),AJ89/AJ$15,"…") -> 0.1268537
A90: Netherlands | B90: 9.668 | C90: 10.696 | D90: 11.551 | E90: 11.607 | F90: 13.297 | G90: 13.69 | H90: 13.518 | I90: 14.131 | J90: 15.506 | K90: 11.349 | L90: 15.062 | M90: 18.057 | N90: 21.166 | O90: 27.428 | P90: 26.072 | Q90: ='Table 2.1 ForeignOfficial'!E16 -> 32.478 | R90: ='Table 2.1 ForeignOfficial'!I16 -> 50.527 | S90: ='Table 2.1 ForeignOfficial'!M16 -> 66.201 | T90: ='Table 2.1 ForeignOfficial'!Q16 -> 65.506 | U90: ='Table 2.1 ForeignOfficial'!U16 -> 89.062 | V90: ='Table 2.1 ForeignOfficial'!Y16 -> 96.496 | W90: ='Table 2.1 ForeignOfficial'!AC16 -> 113.234 | X90: ='Table 2.1 ForeignOfficial'!AG16 -> 129.58 | Y90: ='Table 2.1 ForeignOfficial'!AK16 -> 115.851 | Z90: ='Table 2.1 ForeignOfficial'!AO16 -> 132.192 | AA90: ='Table 2.1 ForeignOfficial'!AS16 -> 135.2 | AB90: ='Table 2.1 ForeignOfficial'!AW16 -> 132.822 | AC90: ='Table 2.1 ForeignOfficial'!BA16 -> 145.42 | AD90: ='Table 2.1 ForeignOfficial'!BE16 -> 136.638 | AE90: ='Table 2.1 ForeignOfficial'!BI16 -> 141.354 | AF90: ='Table 2.1 ForeignOfficial'!BM16 -> 137.509 | AG90: ='Table 2.1 ForeignOfficial'!BQ16 -> 148.836 | AH90: ='Table 2.1 ForeignOfficial'!BU16 -> 150.461 | AI90: ='Table 2.1 ForeignOfficial'!BY16 -> 160.282 | AJ90: ='Table 2.1 ForeignOfficial'!CC16 -> 114.797 | AL90: Netherlands | AM90: =IF(ISNUMBER(B90/B$16),B90/B$16,"…") -> 0.054714205 | AN90: =IF(ISNUMBER(C90/C$16),C90/C$16,"…") -> 0.05753631 | AO90: =IF(ISNUMBER(D90/D$16),D90/D$16,"…") -> 0.058753815 | AP90: =IF(ISNUMBER(E90/E$16),E90/E$16,"…") -> 0.053711245 | AQ90: =IF(ISNUMBER(F90/F$16),F90/F$16,"…") -> 0.058116259 | AR90: =IF(ISNUMBER(G90/G$16),G90/G$16,"…") -> 0.058131635 | AS90: =IF(ISNUMBER(H90/H$16),H90/H$16,"…") -> 0.053664152 | AT90: =IF(ISNUMBER(I90/I$16),I90/I$16,"…") -> 0.056933924 | ... BU90: =IF(ISNUMBER(AJ90/AJ$16),AJ90/AJ$16,"…") -> 0.23843121
A91: New Zealand | B91: … | C91: … | D91: … | E91: … | F91: … | G91: … | H91: … | I91: … | J91: … | K91: … | L91: … | M91: … | N91: 1.751 | O91: 1.462 | P91: 1.163 | Q91: ='Table 2.1 ForeignOfficial'!E17 -> 1.135 | R91: ='Table 2.1 ForeignOfficial'!I17 -> 1.341 | S91: ='Table 2.1 ForeignOfficial'!M17 -> 1.099 | T91: ='Table 2.1 ForeignOfficial'!Q17 -> 1.765 | U91: ='Table 2.1 ForeignOfficial'!U17 -> 2.931 | V91: ='Table 2.1 ForeignOfficial'!Y17 -> 3.132 | W91: ='Table 2.1 ForeignOfficial'!AC17 -> 3.374 | X91: ='Table 2.1 ForeignOfficial'!AG17 -> 3.996 | Y91: ='Table 2.1 ForeignOfficial'!AK17 -> 4.675 | Z91: ='Table 2.1 ForeignOfficial'!AO17 -> 5.829 | AA91: ='Table 2.1 ForeignOfficial'!AS17 -> 6.792 | AB91: ='Table 2.1 ForeignOfficial'!AW17 -> 7.804 | AC91: ='Table 2.1 ForeignOfficial'!BA17 -> 7.797 | AD91: ='Table 2.1 ForeignOfficial'!BE17 -> 8.293 | AE91: ='Table 2.1 ForeignOfficial'!BI17 -> 9.623 | AF91: ='Table 2.1 ForeignOfficial'!BM17 -> 10.312 | AG91: ='Table 2.1 ForeignOfficial'!BQ17 -> 15.585 | AH91: ='Table 2.1 ForeignOfficial'!BU17 -> 17.314 | AI91: ='Table 2.1 ForeignOfficial'!BY17 -> 14.923 | AJ91: ='Table 2.1 ForeignOfficial'!CC17 -> 22.191 | AL91: New Zealand | AM91: =IF(ISNUMBER(B91/B$17),B91/B$17,"…") -> … | AN91: =IF(ISNUMBER(C91/C$17),C91/C$17,"…") -> … | AO91: =IF(ISNUMBER(D91/D$17),D91/D$17,"…") -> … | AP91: =IF(ISNUMBER(E91/E$17),E91/E$17,"…") -> … | AQ91: =IF(ISNUMBER(F91/F$17),F91/F$17,"…") -> … | AR91: =IF(ISNUMBER(G91/G$17),G91/G$17,"…") -> … | AS91: =IF(ISNUMBER(H91/H$17),H91/H$17,"…") -> … | AT91: =IF(ISNUMBER(I91/I$17),I91/I$17,"…") -> … | ... BU91: =IF(ISNUMBER(AJ91/AJ$17),AJ91/AJ$17,"…") -> 0.11536182
A92: Norway | B92: … | C92: … | D92: … | E92: … | F92: … | G92: … | H92: … | I92: … | J92: … | K92: … | L92: … | M92: … | N92: 13.345 | O92: 23.831 | P92: 17.716 | Q92: ='Table 2.1 ForeignOfficial'!E18 -> 19.714 | R92: ='Table 2.1 ForeignOfficial'!I18 -> 24.869 | S92: ='Table 2.1 ForeignOfficial'!M18 -> 31.828 | T92: ='Table 2.1 ForeignOfficial'!Q18 -> 50.655 | U92: ='Table 2.1 ForeignOfficial'!U18 -> 94.201 | V92: ='Table 2.1 ForeignOfficial'!Y18 -> 95.87 | W92: ='Table 2.1 ForeignOfficial'!AC18 -> 103.839 | X92: ='Table 2.1 ForeignOfficial'!AG18 -> 115.774 | Y92: ='Table 2.1 ForeignOfficial'!AK18 -> 120.385 | Z92: ='Table 2.1 ForeignOfficial'!AO18 -> 165.088 | AA92: ='Table 2.1 ForeignOfficial'!AS18 -> 204.799 | AB92: ='Table 2.1 ForeignOfficial'!AW18 -> 252.978 | AC92: ='Table 2.1 ForeignOfficial'!BA18 -> 243.392 | AD92: ='Table 2.1 ForeignOfficial'!BE18 -> 247.855 | AE92: ='Table 2.1 ForeignOfficial'!BI18 -> 302.253 | AF92: ='Table 2.1 ForeignOfficial'!BM18 -> 310.984 | AG92: ='Table 2.1 ForeignOfficial'!BQ18 -> 370.871 | AH92: ='Table 2.1 ForeignOfficial'!BU18 -> 417.155 | AI92: ='Table 2.1 ForeignOfficial'!BY18 -> 447.646 | AJ92: ='Table 2.1 ForeignOfficial'!CC18 -> 511.811 | AL92: Norway | AM92: =IF(ISNUMBER(B92/B$18),B92/B$18,"…") -> … | AN92: =IF(ISNUMBER(C92/C$18),C92/C$18,"…") -> … | AO92: =IF(ISNUMBER(D92/D$18),D92/D$18,"…") -> … | AP92: =IF(ISNUMBER(E92/E$18),E92/E$18,"…") -> … | AQ92: =IF(ISNUMBER(F92/F$18),F92/F$18,"…") -> … | AR92: =IF(ISNUMBER(G92/G$18),G92/G$18,"…") -> … | AS92: =IF(ISNUMBER(H92/H$18),H92/H$18,"…") -> … | AT92: =IF(ISNUMBER(I92/I$18),I92/I$18,"…") -> … | ... BU92: =IF(ISNUMBER(AJ92/AJ$18),AJ92/AJ$18,"…") -> 0.22536504
A93: Portugal | B93: … | C93: … | D93: … | E93: … | F93: … | G93: … | H93: … | I93: … | J93: … | K93: 2.719 | L93: 3.779 | M93: 4.48 | N93: 5.538 | O93: 6.55 | P93: 7.834 | Q93: ='Table 2.1 ForeignOfficial'!E19 -> 10.995 | R93: ='Table 2.1 ForeignOfficial'!I19 -> 11.216 | S93: ='Table 2.1 ForeignOfficial'!M19 -> 12.445 | T93: ='Table 2.1 ForeignOfficial'!Q19 -> 16.708 | U93: ='Table 2.1 ForeignOfficial'!U19 -> 15.701 | V93: ='Table 2.1 ForeignOfficial'!Y19 -> 18.589 | W93: ='Table 2.1 ForeignOfficial'!AC19 -> 38.465 | X93: ='Table 2.1 ForeignOfficial'!AG19 -> 78.856 | Y93: ='Table 2.1 ForeignOfficial'!AK19 -> 103.43 | Z93: ='Table 2.1 ForeignOfficial'!AO19 -> 108.272 | AA93: ='Table 2.1 ForeignOfficial'!AS19 -> 110.26 | AB93: ='Table 2.1 ForeignOfficial'!AW19 -> 102.392 | AC93: ='Table 2.1 ForeignOfficial'!BA19 -> 95.084 | AD93: ='Table 2.1 ForeignOfficial'!BE19 -> 79.682 | AE93: ='Table 2.1 ForeignOfficial'!BI19 -> 73.386 | AF93: ='Table 2.1 ForeignOfficial'!BM19 -> 70.243 | AG93: ='Table 2.1 ForeignOfficial'!BQ19 -> 70.328 | AH93: ='Table 2.1 ForeignOfficial'!BU19 -> 75.002 | AI93: ='Table 2.1 ForeignOfficial'!BY19 -> 77.928 | AJ93: ='Table 2.1 ForeignOfficial'!CC19 -> 74.33 | AL93: Portugal | AM93: =IF(ISNUMBER(B93/B$19),B93/B$19,"…") -> … | AN93: =IF(ISNUMBER(C93/C$19),C93/C$19,"…") -> … | AO93: =IF(ISNUMBER(D93/D$19),D93/D$19,"…") -> … | AP93: =IF(ISNUMBER(E93/E$19),E93/E$19,"…") -> … | AQ93: =IF(ISNUMBER(F93/F$19),F93/F$19,"…") -> … | AR93: =IF(ISNUMBER(G93/G$19),G93/G$19,"…") -> … | AS93: =IF(ISNUMBER(H93/H$19),H93/H$19,"…") -> … | AT93: =IF(ISNUMBER(I93/I$19),I93/I$19,"…") -> … | ... BU93: =IF(ISNUMBER(AJ93/AJ$19),AJ93/AJ$19,"…") -> 0.28386589
A94: Slovenia | B94: … | C94: … | D94: … | E94: … | F94: 0.116 | G94: 0.143 | H94: 0.166 | I94: 0.227 | J94: 0.211 | K94: 0.194 | L94: 0.197 | M94: 0.202 | N94: 0.583 | O94: 0.468 | P94: 0.382 | Q94: ='Table 2.1 ForeignOfficial'!E20 -> 0.381 | R94: ='Table 2.1 ForeignOfficial'!I20 -> 0.363 | S94: ='Table 2.1 ForeignOfficial'!M20 -> 0.241 | T94: ='Table 2.1 ForeignOfficial'!Q20 -> 0.203 | U94: ='Table 2.1 ForeignOfficial'!U20 -> 0.289 | V94: ='Table 2.1 ForeignOfficial'!Y20 -> 0.297 | W94: ='Table 2.1 ForeignOfficial'!AC20 -> 0.392 | X94: ='Table 2.1 ForeignOfficial'!AG20 -> 0.439 | Y94: ='Table 2.1 ForeignOfficial'!AK20 -> 1.321 | Z94: ='Table 2.1 ForeignOfficial'!AO20 -> 1.996 | AA94: ='Table 2.1 ForeignOfficial'!AS20 -> 2.643 | AB94: ='Table 2.1 ForeignOfficial'!AW20 -> 3.881 | AC94: ='Table 2.1 ForeignOfficial'!BA20 -> 4.734 | AD94: ='Table 2.1 ForeignOfficial'!BE20 -> 4.754 | AE94: ='Table 2.1 ForeignOfficial'!BI20 -> 4.963 | AF94: ='Table 2.1 ForeignOfficial'!BM20 -> 5.107 | AG94: ='Table 2.1 ForeignOfficial'!BQ20 -> 5.397 | AH94: ='Table 2.1 ForeignOfficial'!BU20 -> 6.931 | AI94: ='Table 2.1 ForeignOfficial'!BY20 -> 8.546 | AJ94: ='Table 2.1 ForeignOfficial'!CC20 -> 8.854 | AL94: Slovenia | AM94: =IF(ISNUMBER(B94/B$20),B94/B$20,"…") -> … | AN94: =IF(ISNUMBER(C94/C$20),C94/C$20,"…") -> … | AO94: =IF(ISNUMBER(D94/D$20),D94/D$20,"…") -> … | AP94: =IF(ISNUMBER(E94/E$20),E94/E$20,"…") -> … | AQ94: =IF(ISNUMBER(F94/F$20),F94/F$20,"…") -> … | AR94: =IF(ISNUMBER(G94/G$20),G94/G$20,"…") -> … | AS94: =IF(ISNUMBER(H94/H$20),H94/H$20,"…") -> 0.05954089 | AT94: =IF(ISNUMBER(I94/I$20),I94/I$20,"…") -> 0.064124294 | ... BU94: =IF(ISNUMBER(AJ94/AJ$20),AJ94/AJ$20,"…") -> 0.20242804
A95: Spain | B95: 4.015 | C95: 4.442 | D95: 4.797 | E95: 4.82 | F95: 5.522 | G95: 5.685 | H95: 5.613 | I95: 5.868 | J95: 6.439 | K95: 4.713 | L95: 6.254 | M95: 7.498 | N95: 8.789 | O95: 7.408 | P95: 9.686 | Q95: ='Table 2.1 ForeignOfficial'!E21 -> 14.375 | R95: ='Table 2.1 ForeignOfficial'!I21 -> 17.247 | S95: ='Table 2.1 ForeignOfficial'!M21 -> 32.034 | T95: ='Table 2.1 ForeignOfficial'!Q21 -> 51.65 | U95: ='Table 2.1 ForeignOfficial'!U21 -> 62.725 | V95: ='Table 2.1 ForeignOfficial'!Y21 -> 58.601 | W95: ='Table 2.1 ForeignOfficial'!AC21 -> 50.428 | X95: ='Table 2.1 ForeignOfficial'!AG21 -> 81.127 | Y95: ='Table 2.1 ForeignOfficial'!AK21 -> 68.308 | Z95: ='Table 2.1 ForeignOfficial'!AO21 -> 52.89 | AA95: ='Table 2.1 ForeignOfficial'!AS21 -> 47.322 | AB95: ='Table 2.1 ForeignOfficial'!AW21 -> 73.848 | AC95: ='Table 2.1 ForeignOfficial'!BA21 -> 89.437 | AD95: ='Table 2.1 ForeignOfficial'!BE21 -> 100.62 | AE95: ='Table 2.1 ForeignOfficial'!BI21 -> 115.156 | AF95: ='Table 2.1 ForeignOfficial'!BM21 -> 121.491 | AG95: ='Table 2.1 ForeignOfficial'!BQ21 -> 146.495 | AH95: ='Table 2.1 ForeignOfficial'!BU21 -> 170.628 | AI95: ='Table 2.1 ForeignOfficial'!BY21 -> 192.563 | AJ95: ='Table 2.1 ForeignOfficial'!CC21 -> 170.355 | AL95: Spain | AM95: =IF(ISNUMBER(B95/B$21),B95/B$21,"…") -> 0.026982527 | AN95: =IF(ISNUMBER(C95/C$21),C95/C$21,"…") -> 0.025587558 | AO95: =IF(ISNUMBER(D95/D$21),D95/D$21,"…") -> 0.024574795 | AP95: =IF(ISNUMBER(E95/E$21),E95/E$21,"…") -> 0.023206548 | AQ95: =IF(ISNUMBER(F95/F$21),F95/F$21,"…") -> 0.023628584 | AR95: =IF(ISNUMBER(G95/G$21),G95/G$21,"…") -> 0.022285378 | AS95: =IF(ISNUMBER(H95/H$21),H95/H$21,"…") -> 0.018988498 | AT95: =IF(ISNUMBER(I95/I$21),I95/I$21,"…") -> 0.018094357 | ... BU95: =IF(ISNUMBER(AJ95/AJ$21),AJ95/AJ$21,"…") -> 0.10813623
A96: Sweden | B96: … | C96: … | D96: … | E96: … | F96: … | G96: … | H96: … | I96: … | J96: … | K96: … | L96: … | M96: … | N96: 35.391 | O96: 60.99 | P96: 65.572 | Q96: ='Table 2.1 ForeignOfficial'!E22 -> 94.543 | R96: ='Table 2.1 ForeignOfficial'!I22 -> 66.837 | S96: ='Table 2.1 ForeignOfficial'!M22 -> 89.678 | T96: ='Table 2.1 ForeignOfficial'!Q22 -> 119.224 | U96: ='Table 2.1 ForeignOfficial'!U22 -> 151.559 | V96: ='Table 2.1 ForeignOfficial'!Y22 -> 165.271 | W96: ='Table 2.1 ForeignOfficial'!AC22 -> 178.32 | X96: ='Table 2.1 ForeignOfficial'!AG22 -> 194.67 | Y96: ='Table 2.1 ForeignOfficial'!AK22 -> 202.866 | Z96: ='Table 2.1 ForeignOfficial'!AO22 -> 278.951 | AA96: ='Table 2.1 ForeignOfficial'!AS22 -> 412.659 | AB96: ='Table 2.1 ForeignOfficial'!AW22 -> 440.414 | AC96: ='Table 2.1 ForeignOfficial'!BA22 -> 382.365 | AD96: ='Table 2.1 ForeignOfficial'!BE22 -> 331.95 | AE96: ='Table 2.1 ForeignOfficial'!BI22 -> 403.655 | AF96: ='Table 2.1 ForeignOfficial'!BM22 -> 486.916 | AG96: ='Table 2.1 ForeignOfficial'!BQ22 -> 245.211 | AH96: ='Table 2.1 ForeignOfficial'!BU22 -> 210.944 | AI96: ='Table 2.1 ForeignOfficial'!BY22 -> 233.548 | AJ96: ='Table 2.1 ForeignOfficial'!CC22 -> 287.071 | AL96: Sweden | AM96: =IF(ISNUMBER(B96/B$22),B96/B$22,"…") -> … | AN96: =IF(ISNUMBER(C96/C$22),C96/C$22,"…") -> … | AO96: =IF(ISNUMBER(D96/D$22),D96/D$22,"…") -> … | AP96: =IF(ISNUMBER(E96/E$22),E96/E$22,"…") -> … | AQ96: =IF(ISNUMBER(F96/F$22),F96/F$22,"…") -> … | AR96: =IF(ISNUMBER(G96/G$22),G96/G$22,"…") -> … | AS96: =IF(ISNUMBER(H96/H$22),H96/H$22,"…") -> … | AT96: =IF(ISNUMBER(I96/I$22),I96/I$22,"…") -> … | ... BU96: =IF(ISNUMBER(AJ96/AJ$22),AJ96/AJ$22,"…") -> 0.14688469
A97: Switzerland | B97: 8.728 | C97: 7.607 | D97: 8.344 | E97: 6.094 | F97: 5.572 | G97: 3.798 | H97: 4.112 | I97: 4.892 | J97: 6.292 | K97: 5.734 | L97: 5.093 | M97: 6.668 | N97: 6.573 | O97: 10.039 | P97: 6.37 | Q97: ='Table 2.1 ForeignOfficial'!E23 -> 5.255 | R97: ='Table 2.1 ForeignOfficial'!I23 -> 6.126 | S97: ='Table 2.1 ForeignOfficial'!M23 -> 8.586 | T97: ='Table 2.1 ForeignOfficial'!Q23 -> 9.217 | U97: ='Table 2.1 ForeignOfficial'!U23 -> 8.039 | V97: ='Table 2.1 ForeignOfficial'!Y23 -> 7.197 | W97: ='Table 2.1 ForeignOfficial'!AC23 -> 8.199 | X97: ='Table 2.1 ForeignOfficial'!AG23 -> 5.192 | Y97: ='Table 2.1 ForeignOfficial'!AK23 -> 15.002 | Z97: ='Table 2.1 ForeignOfficial'!AO23 -> 20.635 | AA97: ='Table 2.1 ForeignOfficial'!AS23 -> 19.236 | AB97: ='Table 2.1 ForeignOfficial'!AW23 -> 19.834 | AC97: ='Table 2.1 ForeignOfficial'!BA23 -> 12.001 | AD97: ='Table 2.1 ForeignOfficial'!BE23 -> 13.439 | AE97: ='Table 2.1 ForeignOfficial'!BI23 -> 10.763 | AF97: ='Table 2.1 ForeignOfficial'!BM23 -> 11.386 | AG97: ='Table 2.1 ForeignOfficial'!BQ23 -> 13.172 | AH97: ='Table 2.1 ForeignOfficial'!BU23 -> 14.041 | AI97: ='Table 2.1 ForeignOfficial'!BY23 -> 20.335 | AJ97: ='Table 2.1 ForeignOfficial'!CC23 -> 15.29 | AL97: Switzerland | AM97: =IF(ISNUMBER(B97/B$23),B97/B$23,"…") -> 0.10399886 | AN97: =IF(ISNUMBER(C97/C$23),C97/C$23,"…") -> 0.079283354 | AO97: =IF(ISNUMBER(D97/D$23),D97/D$23,"…") -> 0.077280726 | AP97: =IF(ISNUMBER(E97/E$23),E97/E$23,"…") -> 0.047778841 | AQ97: =IF(ISNUMBER(F97/F$23),F97/F$23,"…") -> 0.037558559 | AR97: =IF(ISNUMBER(G97/G$23),G97/G$23,"…") -> 0.023587718 | AS97: =IF(ISNUMBER(H97/H$23),H97/H$23,"…") -> 0.023929654 | AT97: =IF(ISNUMBER(I97/I$23),I97/I$23,"…") -> 0.027079539 | ... BU97: =IF(ISNUMBER(AJ97/AJ$23),AJ97/AJ$23,"…") -> 0.076410649
A98: United Kingdom | B98: 6.007 | C98: 8.626 | D98: 9.871 | E98: 11.71 | F98: 13.698 | G98: 15.106 | H98: 15.158 | I98: 19.789 | J98: 19.144 | K98: 17.917 | L98: 22.848 | M98: 25.148 | N98: 27.921 | O98: 31.349 | P98: 36.087 | Q98: ='Table 2.1 ForeignOfficial'!E24 -> 49.997 | R98: ='Table 2.1 ForeignOfficial'!I24 -> 68.068 | S98: ='Table 2.1 ForeignOfficial'!M24 -> 90.683 | T98: ='Table 2.1 ForeignOfficial'!Q24 -> 121.118 | U98: ='Table 2.1 ForeignOfficial'!U24 -> 153.913 | V98: ='Table 2.1 ForeignOfficial'!Y24 -> 162.295 | W98: ='Table 2.1 ForeignOfficial'!AC24 -> 174.119 | X98: ='Table 2.1 ForeignOfficial'!AG24 -> 172.133 | Y98: ='Table 2.1 ForeignOfficial'!AK24 -> 196.342 | Z98: ='Table 2.1 ForeignOfficial'!AO24 -> 209.819 | AA98: ='Table 2.1 ForeignOfficial'!AS24 -> 184.479 | AB98: ='Table 2.1 ForeignOfficial'!AW24 -> 239.678 | AC98: ='Table 2.1 ForeignOfficial'!BA24 -> 236.735 | AD98: ='Table 2.1 ForeignOfficial'!BE24 -> 243.337 | AE98: ='Table 2.1 ForeignOfficial'!BI24 -> 258.407 | AF98: ='Table 2.1 ForeignOfficial'!BM24 -> 261.15 | AG98: ='Table 2.1 ForeignOfficial'!BQ24 -> 272.084 | AH98: ='Table 2.1 ForeignOfficial'!BU24 -> 298.392 | AI98: ='Table 2.1 ForeignOfficial'!BY24 -> 442.068 | AJ98: ='Table 2.1 ForeignOfficial'!CC24 -> 428.652 | AL98: United Kingdom | AM98: =IF(ISNUMBER(B98/B$24),B98/B$24,"…") -> 0.031089397 | AN98: =IF(ISNUMBER(C98/C$24),C98/C$24,"…") -> 0.04550034 | AO98: =IF(ISNUMBER(D98/D$24),D98/D$24,"…") -> 0.048687014 | AP98: =IF(ISNUMBER(E98/E$24),E98/E$24,"…") -> 0.047154805 | AQ98: =IF(ISNUMBER(F98/F$24),F98/F$24,"…") -> 0.042247526 | AR98: =IF(ISNUMBER(G98/G$24),G98/G$24,"…") -> 0.045772983 | AS98: =IF(ISNUMBER(H98/H$24),H98/H$24,"…") -> 0.039492162 | AT98: =IF(ISNUMBER(I98/I$24),I98/I$24,"…") -> 0.048607648 | ... BU98: =IF(ISNUMBER(AJ98/AJ$24),AJ98/AJ$24,"…") -> 0.15754185
A99: United States | B99: … | C99: … | D99: … | E99: … | F99: … | G99: 412.5 | H99: 486.1 | I99: 603.6 | J99: 599.5 | K99: 593.5 | L99: 623.6 | M99: 609.2 | N99: 619.4 | O99: 760.1 | P99: 933.9 | Q99: ='Table 2.1 ForeignOfficial'!E25 -> 1233.3 | R99: ='Table 2.1 ForeignOfficial'!I25 -> 1305.1 | S99: ='Table 2.1 ForeignOfficial'!M25 -> 1449 | T99: ='Table 2.1 ForeignOfficial'!Q25 -> 1641.1 | U99: ='Table 2.1 ForeignOfficial'!U25 -> 2138.3 | V99: ='Table 2.1 ForeignOfficial'!Y25 -> 2700.1 | W99: ='Table 2.1 ForeignOfficial'!AC25 -> 3189.3 | X99: ='Table 2.1 ForeignOfficial'!AG25 -> 3620.6 | Y99: ='Table 2.1 ForeignOfficial'!AK25 -> 4032.8 | Z99: ='Table 2.1 ForeignOfficial'!AO25 -> 4054.6 | AA99: ='Table 2.1 ForeignOfficial'!AS25 -> 4122.6 | AB99: ='Table 2.1 ForeignOfficial'!AW25 -> 4091.6 | AC99: ='Table 2.1 ForeignOfficial'!BA25 -> 3813.4 | AD99: ='Table 2.1 ForeignOfficial'!BE25 -> 4024 | AE99: ='Table 2.1 ForeignOfficial'!BI25 -> 3956.8 | AF99: ='Table 2.1 ForeignOfficial'!BM25 -> 4076.9 | AG99: ='Table 2.1 ForeignOfficial'!BQ25 -> 4186.5 | AH99: ='Table 2.1 ForeignOfficial'!BU25 -> 4117.7 | AI99: ='Table 2.1 ForeignOfficial'!BY25 -> 3667.4 | AJ99: ='Table 2.1 ForeignOfficial'!CC25 -> 3786.9 | AL99: United States | AM99: =IF(ISNUMBER(B99/B$25),B99/B$25,"…") -> … | AN99: =IF(ISNUMBER(C99/C$25),C99/C$25,"…") -> … | AO99: =IF(ISNUMBER(D99/D$25),D99/D$25,"…") -> … | AP99: =IF(ISNUMBER(E99/E$25),E99/E$25,"…") -> … | AQ99: =IF(ISNUMBER(F99/F$25),F99/F$25,"…") -> … | AR99: =IF(ISNUMBER(G99/G$25),G99/G$25,"…") -> 0.08752166 | AS99: =IF(ISNUMBER(H99/H$25),H99/H$25,"…") -> 0.098999758 | AT99: =IF(ISNUMBER(I99/I$25),I99/I$25,"…") -> 0.11790179 | ... BU99: =IF(ISNUMBER(AJ99/AJ$25),AJ99/AJ$25,"…") -> 0.12206849
A100: Cyprus | B100: … | C100: … | D100: … | E100: … | F100: … | G100: … | H100: … | I100: … | J100: … | K100: … | L100: … | M100: … | N100: … | O100: … | P100: … | Q100: … | R100: … | S100: … | T100: … | U100: 0.978 | V100: 1.211 | W100: 1.387 | X100: 2.254 | Y100: 4.629 | Z100: 9.41 | AA100: 10.813 | AB100: 11.837 | AC100: 11.834 | AD100: 11.535 | AE100: 10.905 | AF100: 9.114 | AG100: 8.82 | AH100: 9.289 | AI100: 9.322 | AJ100: 9.275 | AL100: Cyprus | AM100: =IF(ISNUMBER(B100/B$26),B100/B$26,"…") -> … | AN100: =IF(ISNUMBER(C100/C$26),C100/C$26,"…") -> … | AO100: =IF(ISNUMBER(D100/D$26),D100/D$26,"…") -> … | AP100: =IF(ISNUMBER(E100/E$26),E100/E$26,"…") -> … | AQ100: =IF(ISNUMBER(F100/F$26),F100/F$26,"…") -> … | AR100: =IF(ISNUMBER(G100/G$26),G100/G$26,"…") -> … | AS100: =IF(ISNUMBER(H100/H$26),H100/H$26,"…") -> … | AT100: =IF(ISNUMBER(I100/I$26),I100/I$26,"…") -> … | ... BU100: =IF(ISNUMBER(AJ100/AJ$26),AJ100/AJ$26,"…") -> 0.40193274
A101: Estonia | B101: 0 | C101: 0 | D101: 0 | E101: 0 | F101: 0 | G101: 0 | H101: 0 | I101: 0 | J101: 0 | K101: 0 | L101: 0 | M101: 0 | N101: 0 | O101: 0 | P101: 0 | Q101: 0 | R101: 0 | S101: 0 | T101: 0 | U101: 0 | V101: 0 | W101: 0 | X101: 0 | Y101: 0 | Z101: 0 | AA101: 0 | AB101: 0.004 | AC101: 0.005 | AD101: 0.005 | AE101: 0.001 | AF101: 0.001 | AG101: 0.041 | AH101: 0.055 | AI101: 0.068 | AJ101: 0.072 | AL101: Estonia | AM101: =IF(ISNUMBER(B101/B$27),B101/B$27,"…") -> … | AN101: =IF(ISNUMBER(C101/C$27),C101/C$27,"…") -> … | AO101: =IF(ISNUMBER(D101/D$27),D101/D$27,"…") -> … | AP101: =IF(ISNUMBER(E101/E$27),E101/E$27,"…") -> … | AQ101: =IF(ISNUMBER(F101/F$27),F101/F$27,"…") -> … | AR101: =IF(ISNUMBER(G101/G$27),G101/G$27,"…") -> … | AS101: =IF(ISNUMBER(H101/H$27),H101/H$27,"…") -> 0 | AT101: =IF(ISNUMBER(I101/I$27),I101/I$27,"…") -> 0 | ... BU101: =IF(ISNUMBER(AJ101/AJ$27),AJ101/AJ$27,"…") -> 0.0093409445
A102: Iceland | B102: 0 | C102: 0 | D102: 0 | E102: 0 | F102: 0 | G102: 0 | H102: 0 | I102: 0 | J102: 0 | K102: 0 | L102: 0 | M102: 0 | N102: 0 | O102: 0 | P102: 0 | Q102: 0 | R102: 0 | S102: 0 | T102: 0 | U102: 0 | V102: 0 | W102: 0 | X102: 0 | Y102: 0 | Z102: 0 | AA102: 0 | AB102: 0 | AC102: 0 | AD102: 0 | AE102: 0 | AF102: 0 | AG102: 0 | AH102: 0 | AI102: 0 | AJ102: 0 | AL102: Iceland | AM102: =IF(ISNUMBER(B102/B$28),B102/B$28,"…") -> 0 | AN102: =IF(ISNUMBER(C102/C$28),C102/C$28,"…") -> 0 | AO102: =IF(ISNUMBER(D102/D$28),D102/D$28,"…") -> 0 | AP102: =IF(ISNUMBER(E102/E$28),E102/E$28,"…") -> 0 | AQ102: =IF(ISNUMBER(F102/F$28),F102/F$28,"…") -> 0 | AR102: =IF(ISNUMBER(G102/G$28),G102/G$28,"…") -> 0 | AS102: =IF(ISNUMBER(H102/H$28),H102/H$28,"…") -> 0 | AT102: =IF(ISNUMBER(I102/I$28),I102/I$28,"…") -> 0 | ... BU102: =IF(ISNUMBER(AJ102/AJ$28),AJ102/AJ$28,"…") -> 0
...

Sheet ExtendedDataset_Currency
A1: Total debt securities in local currency (in percent of total debt securities) | B1: 1989 | C1: =B1+1 -> 1990 | D1: =C1+1 -> 1991 | E1: =D1+1 -> 1992 | F1: =E1+1 -> 1993 | G1: =F1+1 -> 1994 | H1: =G1+1 -> 1995 | I1: =H1+1 -> 1996 | J1: =I1+1 -> 1997 | ... AJ1: =AI1+1 -> 2023
A2: Australia | B2: … | C2: … | D2: … | E2: … | F2: … | G2: 0.939 | H2: 0.939 | I2: 0.942 | J2: 0.939 | K2: 0.935 | L2: 0.965 | M2: 0.968 | N2: 0.979 | O2: 0.974 | P2: 0.972 | Q2: 0.974 | R2: 0.978 | S2: 0.985 | T2: 0.989 | U2: 0.985 | V2: 0.989 | W2: 0.993 | X2: 0.995 | Y2: 0.996 | Z2: 0.997 | AA2: 0.998 | AB2: 0.998 | AC2: 0.999 | AD2: 0.999 | AE2: 0.999 | AF2: 0.999 | AG2: 0.999 | AH2: 0.999 | AI2: 0.999 | AJ2: 0.999
A3: Austria | B3: 0.882 | C3: 0.878 | D3: 0.879 | E3: 0.888 | F3: 0.883 | G3: 0.865 | H3: 0.867 | I3: 0.864 | J3: 0.868 | K3: 0.842 | L3: 0.845 | M3: 0.868 | N3: 0.869 | O3: 0.865 | P3: 0.866 | Q3: 0.866 | R3: 0.858 | S3: 0.89 | T3: 0.908 | U3: 0.88 | V3: 0.905 | W3: 0.922 | X3: 0.928 | Y3: 0.937 | Z3: 0.959 | AA3: 0.957 | AB3: 0.957 | AC3: 0.958 | AD3: 0.972 | AE3: 0.976 | AF3: 0.971 | AG3: 0.95 | AH3: 0.969 | AI3: 0.967 | AJ3: 0.973
A4: Belgium | B4: 0.951 | C4: 0.947 | D4: 0.951 | E4: 0.961 | F4: 0.947 | G4: 0.949 | H4: 0.951 | I4: 0.955 | J4: 0.951 | K4: 0.961 | L4: 0.96 | M4: 0.964 | N4: 0.968 | O4: 0.975 | P4: 0.985 | Q4: 0.989 | R4: 0.988 | S4: 0.99 | T4: 0.993 | U4: 0.966 | V4: 0.984 | W4: 0.978 | X4: 0.962 | Y4: 0.984 | Z4: 0.984 | AA4: 0.985 | AB4: 0.985 | AC4: 0.978 | AD4: 0.974 | AE4: 0.985 | AF4: 0.992 | AG4: 0.989 | AH4: 0.993 | AI4: 0.991 | AJ4: 0.994
A5: Canada | B5: 0.85 | C5: 0.841 | D5: 0.849 | E5: 0.835 | F5: 0.819 | G5: 0.789 | H5: 0.789 | I5: 0.79 | J5: 0.799 | K5: 0.768 | L5: 0.791 | M5: 0.808 | N5: 0.801 | O5: 0.802 | P5: 0.833 | Q5: 0.849 | R5: 0.856 | S5: 0.855 | T5: 0.877 | U5: 0.865 | V5: 0.877 | W5: 0.876 | X5: 0.877 | Y5: 0.881 | Z5: 0.883 | AA5: 0.877 | AB5: 0.873 | AC5: 0.887 | AD5: 0.885 | AE5: 0.879 | AF5: 0.888 | AG5: 0.897 | AH5: 0.902 | AI5: 0.908 | AJ5: 0.907
A6: Czech Republic | B6: … | C6: … | D6: … | E6: … | F6: … | G6: … | H6: … | I6: … | J6: … | K6: … | L6: … | M6: … | N6: … | O6: … | P6: … | Q6: … | R6: … | S6: 0.871 | T6: 0.89 | U6: 0.837 | V6: 0.813 | W6: 0.797 | X6: 0.806 | Y6: 0.785 | Z6: 0.781 | AA6: 0.836 | AB6: 0.848 | AC6: 0.858 | AD6: 0.864 | AE6: 0.897 | AF6: 0.885 | AG6: 0.913 | AH6: 0.96 | AI6: 0.982 | AJ6: 0.986
A7: Denmark | B7: … | C7: … | D7: … | E7: … | F7: … | G7: … | H7: … | I7: … | J7: … | K7: … | L7: 1 | M7: 1 | N7: 1 | O7: 0.927 | P7: 0.955 | Q7: 0.971 | R7: 0.975 | S7: 0.985 | T7: 0.989 | U7: 0.955 | V7: 0.847 | W7: 0.854 | X7: 0.87 | Y7: 0.904 | Z7: 0.915 | AA7: 0.939 | AB7: 0.957 | AC7: 0.985 | AD7: 0.998 | AE7: 0.999 | AF7: 0.999 | AG7: 0.984 | AH7: 0.982 | AI7: 0.98 | AJ7: 0.963
A8: Finland | B8: 0.701 | C8: 0.72 | D8: 0.724 | E8: 0.658 | F8: 0.635 | G8: 0.678 | H8: 0.748 | I8: 0.77 | J8: 0.797 | K8: 0.848 | L8: 0.83 | M8: 0.855 | N8: 0.856 | O8: 0.855 | P8: 0.907 | Q8: 0.922 | R8: 0.906 | S8: 0.913 | T8: 0.942 | U8: 0.93 | V8: 0.944 | W8: 0.87 | X8: 0.896 | Y8: 0.853 | Z8: 0.847 | AA8: 0.826 | AB8: 0.825 | AC8: 0.857 | AD8: 0.849 | AE8: 0.899 | AF8: 0.941 | AG8: 0.965 | AH8: 0.977 | AI8: 0.961 | AJ8: 0.979
A9: France | B9: 1 | C9: 1 | D9: 1 | E9: 0.999 | F9: 0.999 | G9: 0.998 | H9: 0.998 | I9: 0.983 | J9: 0.976 | K9: 0.984 | L9: 0.988 | M9: 0.987 | N9: 0.993 | O9: 0.996 | P9: 0.997 | Q9: 0.984 | R9: 0.978 | S9: 0.981 | T9: 0.983 | U9: 0.979 | V9: 0.969 | W9: 0.967 | X9: 0.961 | Y9: 0.968 | Z9: 0.97 | AA9: 0.972 | AB9: 0.969 | AC9: 0.961 | AD9: 0.963 | AE9: 0.975 | AF9: 0.976 | AG9: 0.963 | AH9: 0.962 | AI9: 0.972 | AJ9: 0.972
A10: Germany | B10: 1 | C10: 1 | D10: 1 | E10: 1 | F10: 1 | G10: 1 | H10: 1 | I10: 1 | J10: 1 | K10: 1 | L10: 1 | M10: 1 | N10: 0.999 | O10: 0.998 | P10: 0.995 | Q10: 0.994 | R10: 0.989 | S10: 0.99 | T10: 0.991 | U10: 0.99 | V10: 0.987 | W10: 0.992 | X10: 0.977 | Y10: 0.963 | Z10: 0.964 | AA10: 0.959 | AB10: 0.949 | AC10: 0.945 | AD10: 0.942 | AE10: 0.949 | AF10: 0.955 | AG10: 0.959 | AH10: 0.97 | AI10: 0.981 | AJ10: 0.989
A11: Greece | B11: … | C11: … | D11: … | E11: … | F11: … | G11: … | H11: 1 | I11: 1 | J11: 1 | K11: 1 | L11: 1 | M11: 1 | N11: 1 | O11: 1 | P11: 1 | Q11: 1 | R11: 1 | S11: 1 | T11: 1 | U11: 0.981 | V11: 0.986 | W11: 0.985 | X11: 0.985 | Y11: 0.974 | Z11: 0.988 | AA11: 0.987 | AB11: 0.986 | AC11: 0.992 | AD11: 1 | AE11: 1 | AF11: 1 | AG11: 1 | AH11: 1 | AI11: 1 | AJ11: 1
A12: Ireland | B12: 1 | C12: 1 | D12: 1 | E12: 1 | F12: 1 | G12: 1 | H12: 1 | I12: 1 | J12: 1 | K12: 1 | L12: 1 | M12: 1 | N12: 1 | O12: 1 | P12: 1 | Q12: 1 | R12: 1 | S12: 1 | T12: 1 | U12: 1 | V12: 0.954 | W12: 0.992 | X12: 0.998 | Y12: 0.997 | Z12: 0.999 | AA12: 0.98 | AB12: 0.993 | AC12: 0.997 | AD12: 0.997 | AE12: 0.996 | AF12: 1 | AG12: 0.985 | AH12: 0.988 | AI12: 1 | AJ12: 1
A13: Italy | B13: 0.988 | C13: 0.989 | D13: 0.989 | E13: 0.989 | F13: 0.979 | G13: 0.975 | H13: 0.972 | I13: 0.968 | J13: 0.965 | K13: 0.965 | L13: 0.961 | M13: 0.952 | N13: 0.95 | O13: 0.95 | P13: 0.951 | Q13: 0.952 | R13: 0.948 | S13: 0.961 | T13: 0.967 | U13: 0.972 | V13: 0.975 | W13: 0.973 | X13: 0.976 | Y13: 0.981 | Z13: 0.985 | AA13: 0.985 | AB13: 0.99 | AC13: 0.993 | AD13: 0.995 | AE13: 0.996 | AF13: 0.993 | AG13: 0.993 | AH13: 0.991 | AI13: 0.991 | AJ13: 0.993
A14: Japan | B14: … | C14: … | D14: … | E14: … | F14: … | G14: … | H14: … | I14: … | J14: … | K14: … | L14: … | M14: … | N14: … | O14: … | P14: … | Q14: … | R14: … | S14: … | T14: … | U14: … | V14: … | W14: … | X14: … | Y14: 1 | Z14: 1 | AA14: 0.999 | AB14: 0.999 | AC14: 0.999 | AD14: 0.999 | AE14: 0.999 | AF14: 0.999 | AG14: 0.999 | AH14: 0.999 | AI14: 0.999 | AJ14: 0.999
A15: Korea | B15: … | C15: … | D15: … | E15: … | F15: … | G15: … | H15: … | I15: … | J15: … | K15: … | L15: … | M15: … | N15: … | O15: 0.955 | P15: 0.966 | Q15: 0.975 | R15: 0.978 | S15: 0.98 | T15: 0.982 | U15: 0.986 | V15: 0.981 | W15: 0.984 | X15: 0.985 | Y15: 0.987 | Z15: 0.988 | AA15: 0.99 | AB15: 0.99 | AC15: 0.991 | AD15: 0.99 | AE15: 0.989 | AF15: 0.99 | AG15: 0.99 | AH15: 0.988 | AI15: 0.988 | AJ15: 0.989
A16: Netherlands | B16: 1 | C16: 1 | D16: 1 | E16: 1 | F16: 1 | G16: 1 | H16: 1 | I16: 1 | J16: 1 | K16: 1 | L16: 1 | M16: 1 | N16: 1 | O16: 1 | P16: 1 | Q16: 1 | R16: 1 | S16: 1 | T16: 1 | U16: 0.957 | V16: 0.981 | W16: 0.982 | X16: 0.976 | Y16: 0.943 | Z16: 0.978 | AA16: 0.979 | AB16: 0.985 | AC16: 0.984 | AD16: 0.997 | AE16: 0.991 | AF16: 0.997 | AG16: 0.999 | AH16: 0.999 | AI16: 0.967 | AJ16: 0.987
A17: New Zealand | B17: … | C17: … | D17: … | E17: … | F17: … | G17: … | H17: … | I17: … | J17: … | K17: … | L17: … | M17: … | N17: … | O17: … | P17: … | Q17: … | R17: … | S17: … | T17: … | U17: … | V17: … | W17: … | X17: … | Y17: … | Z17: … | AA17: … | AB17: … | AC17: … | AD17: … | AE17: … | AF17: … | AG17: … | AH17: … | AI17: … | AJ17: …
A18: Norway | B18: … | C18: … | D18: … | E18: … | F18: … | G18: … | H18: … | I18: … | J18: … | K18: … | L18: … | M18: … | N18: … | O18: … | P18: … | Q18: … | R18: 1 | S18: 1 | T18: 1 | U18: 1 | V18: 1 | W18: 1 | X18: 1 | Y18: 1 | Z18: 1 | AA18: 1 | AB18: 1 | AC18: 1 | AD18: 1 | AE18: 1 | AF18: 1 | AG18: 1 | AH18: 1 | AI18: 1 | AJ18: 1
A19: Portugal | B19: 0.991 | C19: 0.992 | D19: 0.993 | E19: 0.994 | F19: 0.951 | G19: 0.955 | H19: 0.944 | I19: 0.946 | J19: 0.931 | K19: 0.935 | L19: 0.906 | M19: 0.923 | N19: 0.91 | O19: 0.954 | P19: 0.979 | Q19: 0.992 | R19: 0.993 | S19: 0.995 | T19: 0.997 | U19: 0.991 | V19: 0.983 | W19: 0.984 | X19: 0.984 | Y19: 0.987 | Z19: 0.988 | AA19: 0.962 | AB19: 0.968 | AC19: 0.97 | AD19: 0.975 | AE19: 0.975 | AF19: 0.974 | AG19: 0.978 | AH19: 0.983 | AI19: 0.984 | AJ19: 0.986
A20: Slovenia | B20: … | C20: … | D20: … | E20: … | F20: … | G20: … | H20: … | I20: … | J20: … | K20: 0.895 | L20: 0.893 | M20: 0.896 | N20: 0.989 | O20: 0.994 | P20: 0.996 | Q20: 0.998 | R20: 0.999 | S20: 1 | T20: 1 | U20: 1 | V20: 1 | W20: 1 | X20: 1 | Y20: 0.899 | Z20: 0.817 | AA20: 0.72 | AB20: 0.707 | AC20: 0.776 | AD20: 0.863 | AE20: 0.904 | AF20: 0.947 | AG20: 0.96 | AH20: 0.959 | AI20: 0.98 | AJ20: 0.965
A21: Spain | B21: 0.985 | C21: 0.983 | D21: 0.984 | E21: 0.964 | F21: 0.966 | G21: 0.967 | H21: 0.967 | I21: 0.969 | J21: 0.967 | K21: 0.964 | L21: 0.958 | M21: 0.957 | N21: 0.955 | O21: 0.965 | P21: 0.97 | Q21: 0.976 | R21: 0.98 | S21: 0.983 | T21: 0.985 | U21: 0.981 | V21: 0.981 | W21: 0.984 | X21: 0.988 | Y21: 0.994 | Z21: 0.995 | AA21: 0.996 | AB21: 0.996 | AC21: 0.996 | AD21: 0.997 | AE21: 0.999 | AF21: 0.999 | AG21: 0.999 | AH21: 0.999 | AI21: 0.999 | AJ21: 0.999
A22: Sweden | B22: … | C22: … | D22: … | E22: … | F22: … | G22: … | H22: … | I22: … | J22: … | K22: 0.707 | L22: 0.75 | M22: 0.771 | N22: 0.772 | O22: 0.795 | P22: 0.851 | Q22: 0.864 | R22: 0.868 | S22: 0.876 | T22: 0.876 | U22: 0.9 | V22: 0.827 | W22: 0.837 | X22: 0.871 | Y22: 0.87 | Z22: 0.798 | AA22: 0.768 | AB22: 0.74 | AC22: 0.735 | AD22: 0.749 | AE22: 0.757 | AF22: 0.786 | AG22: 0.81 | AH22: 0.847 | AI22: 0.864 | AJ22: 0.964
A23: Switzerland | B23: … | C23: … | D23: … | E23: … | F23: … | G23: … | H23: … | I23: … | J23: … | K23: … | L23: 1 | M23: 1 | N23: 1 | O23: 1 | P23: 1 | Q23: 1 | R23: 1 | S23: 1 | T23: 1 | U23: 1 | V23: 1 | W23: 1 | X23: 1 | Y23: 1 | Z23: 1 | AA23: 1 | AB23: 1 | AC23: 1 | AD23: 1 | AE23: 1 | AF23: 1 | AG23: 1 | AH23: 1 | AI23: 1 | AJ23: 1
A24: United Kingdom | B24: … | C24: … | D24: … | E24: … | F24: … | G24: … | H24: … | I24: … | J24: … | K24: 1 | L24: 1 | M24: 1 | N24: 1 | O24: 1 | P24: 1 | Q24: 1 | R24: 1 | S24: 1 | T24: 1 | U24: 1 | V24: 1 | W24: 1 | X24: 1 | Y24: 1 | Z24: 1 | AA24: 1 | AB24: 1 | AC24: 1 | AD24: 1 | AE24: 1 | AF24: 1 | AG24: 1 | AH24: 1 | AI24: 1 | AJ24: 1
A25: United States | B25: 1 | C25: 1 | D25: 1 | E25: 1 | F25: 1 | G25: 1 | H25: 1 | I25: 1 | J25: 1 | K25: 1 | L25: 1 | M25: 1 | N25: 1 | O25: 1 | P25: 1 | Q25: 1 | R25: 1 | S25: 1 | T25: 1 | U25: 1 | V25: 1 | W25: 1 | X25: 1 | Y25: 1 | Z25: 1 | AA25: 1 | AB25: 1 | AC25: 1 | AD25: 1 | AE25: 1 | AF25: 1 | AG25: 1 | AH25: 1 | AI25: 1 | AJ25: 1
A26: Cyprus | B26: … | C26: … | D26: … | E26: … | F26: … | G26: … | H26: … | I26: … | J26: … | K26: … | L26: … | M26: … | N26: … | O26: … | P26: … | Q26: 1 | R26: 1 | S26: 1 | T26: 1 | U26: 1 | V26: 1 | W26: 1 | X26: 0.995 | Y26: 1 | Z26: 1 | AA26: 1 | AB26: 1 | AC26: 1 | AD26: 1 | AE26: 1 | AF26: 1 | AG26: 1 | AH26: 1 | AI26: 1 | AJ26: 1
A27: Estonia | B27: … | C27: … | D27: … | E27: … | F27: … | G27: … | H27: … | I27: … | J27: … | K27: … | L27: … | M27: … | N27: … | O27: … | P27: … | Q27: … | R27: … | S27: … | T27: … | U27: 1 | V27: 1 | W27: 1 | X27: 0.934 | Y27: 0.932 | Z27: 0.951 | AA27: 0.947 | AB27: 0.951 | AC27: 0.964 | AD27: 0.973 | AE27: 0.985 | AF27: 0.993 | AG27: 1 | AH27: 1 | AI27: 1 | AJ27: 1
A28: Iceland | B28: … | C28: … | D28: … | E28: … | F28: … | G28: … | H28: … | I28: … | J28: … | K28: … | L28: … | M28: … | N28: … | O28: … | P28: … | Q28: … | R28: … | S28: … | T28: … | U28: … | V28: … | W28: … | X28: … | Y28: … | Z28: … | AA28: … | AB28: … | AC28: … | AD28: … | AE28: … | AF28: … | AG28: … | AH28: … | AI28: … | AJ28: …
A29: Israel | B29: … | C29: … | D29: … | E29: … | F29: … | G29: … | H29: 0.695 | I29: 0.688 | J29: 0.68 | K29: 0.619 | L29: 0.624 | M29: 0.643 | N29: 0.674 | O29: 0.68 | P29: 0.736 | Q29: 0.755 | R29: 0.748 | S29: 0.759 | T29: 0.775 | U29: 0.808 | V29: 0.827 | W29: 0.835 | X29: 0.833 | Y29: 0.847 | Z29: 0.857 | AA29: 0.847 | AB29: 0.86 | AC29: 0.868 | AD29: 0.863 | AE29: 0.841 | AF29: 0.855 | AG29: 0.813 | AH29: 0.836 | AI29: 0.804 | AJ29: 0.785
A30: Latvia | B30: … | C30: … | D30: … | E30: … | F30: … | G30: … | H30: … | I30: … | J30: … | K30: … | L30: … | M30: … | N30: … | O30: … | P30: … | Q30: … | R30: … | S30: … | T30: … | U30: … | V30: … | W30: … | X30: 0.824 | Y30: 0.462 | Z30: 0.471 | AA30: 0.605 | AB30: 0.704 | AC30: 0.746 | AD30: 0.883 | AE30: 0.887 | AF30: 0.897 | AG30: 0.969 | AH30: 1 | AI30: 1 | AJ30: 1
A31: Lithuania | B31: … | C31: … | D31: … | E31: … | F31: … | G31: … | H31: … | I31: … | J31: … | K31: … | L31: … | M31: … | N31: … | O31: … | P31: … | Q31: … | R31: … | S31: … | T31: … | U31: … | V31: … | W31: … | X31: … | Y31: 0.487 | Z31: 0.491 | AA31: 0.513 | AB31: 0.604 | AC31: 0.603 | AD31: 0.712 | AE31: 0.694 | AF31: 0.73 | AG31: 0.879 | AH31: 0.935 | AI31: 1 | AJ31: 1
A32: Luxembourg | B32: 1 | C32: 1 | D32: 1 | E32: 1 | F32: 1 | G32: 1 | H32: 1 | I32: 1 | J32: 1 | K32: 1 | L32: 1 | M32: 1 | N32: 1 | O32: 1 | P32: 1 | Q32: 1 | R32: 1 | S32: 1 | T32: … | U32: 1 | V32: 1 | W32: 1 | X32: 1 | Y32: 1 | Z32: 1 | AA32: 1 | AB32: 1 | AC32: 1 | AD32: 1 | AE32: 1 | AF32: 1 | AG32: 1 | AH32: 1 | AI32: 1 | AJ32: 1
A33: Malta | B33: … | C33: … | D33: … | E33: … | F33: … | G33: … | H33: … | I33: … | J33: … | K33: … | L33: … | M33: … | N33: … | O33: … | P33: … | Q33: 1 | R33: 1 | S33: 1 | T33: 1 | U33: 1 | V33: 1 | W33: 1 | X33: 1 | Y33: 1 | Z33: 1 | AA33: 1 | AB33: 1 | AC33: 1 | AD33: 1 | AE33: 1 | AF33: 1 | AG33: 1 | AH33: 1 | AI33: 1 | AJ33: 1
A34: San Marino | B34: … | C34: … | D34: … | E34: … | F34: … | G34: … | H34: … | I34: … | J34: … | K34: … | L34: … | M34: … | N34: … | O34: … | P34: … | Q34: … | R34: … | S34: … | T34: … | U34: … | V34: … | W34: … | X34: … | Y34: … | Z34: … | AA34: … | AB34: … | AC34: … | AD34: … | AE34: … | AF34: … | AG34: … | AH34: … | AI34: … | AJ34: …
A35: Singapore | B35: 1 | C35: 1 | D35: 1 | E35: 1 | F35: 1 | G35: 1 | H35: 1 | I35: 1 | J35: 1 | K35: 1 | L35: 1 | M35: 1 | N35: 1 | O35: 1 | P35: 1 | Q35: 1 | R35: 1 | S35: 1 | T35: 1 | U35: 1 | V35: 1 | W35: 1 | X35: 1 | Y35: 1 | Z35: 1 | AA35: 1 | AB35: 1 | AC35: 1 | AD35: 1 | AE35: 1 | AF35: 1 | AG35: 1 | AH35: 1 | AI35: 1 | AJ35: 1
A36: Slovak Republic | B36: … | C36: … | D36: … | E36: … | F36: 1 | G36: 1 | H36: 1 | I36: 1 | J36: 1 | K36: 0.907 | L36: 0.903 | M36: 0.913 | N36: 0.959 | O36: 0.966 | P36: 1 | Q36: 1 | R36: 1 | S36: 1 | T36: 1 | U36: 1 | V36: 1 | W36: 1 | X36: 1 | Y36: 0.938 | Z36: 0.924 | AA36: 0.91 | AB36: 0.917 | AC36: 0.922 | AD36: 0.931 | AE36: 0.939 | AF36: 0.948 | AG36: 0.96 | AH36: 0.961 | AI36: 0.991 | AJ36: 0.995
A38: Foreign holdings of local currency debt securities (in percent of all foreign holdings) | B38: 1989 | C38: =B38+1 -> 1990 | D38: =C38+1 -> 1991 | E38: =D38+1 -> 1992 | F38: =E38+1 -> 1993 | G38: =F38+1 -> 1994 | H38: =G38+1 -> 1995 | I38: =H38+1 -> 1996 | J38: =I38+1 -> 1997 | ... AJ38: =AI38+1 -> 2023
A39: Australia | B39: … | C39: … | D39: … | E39: … | F39: … | G39: 0.939 | H39: 0.939 | I39: 0.942 | J39: 0.939 | K39: 0.935 | L39: 0.965 | M39: 0.968 | N39: 0.979 | O39: 0.974 | P39: 0.972 | Q39: 0.974 | R39: 0.978 | S39: 0.985 | T39: 0.989 | U39: 0.985 | V39: 0.989 | W39: 0.993 | X39: 0.995 | Y39: 0.996 | Z39: 0.997 | AA39: 0.998 | AB39: 0.998 | AC39: 0.999 | AD39: 0.999 | AE39: 0.999 | AF39: 0.999 | AG39: 0.999 | AH39: 0.999 | AI39: 0.999 | AJ39: 0.999
A40: Austria | B40: 0.882 | C40: 0.878 | D40: 0.879 | E40: 0.888 | F40: 0.883 | G40: 0.865 | H40: 0.867 | I40: 0.864 | J40: 0.868 | K40: 0.842 | L40: 0.845 | M40: 0.868 | N40: 0.869 | O40: 0.865 | P40: 0.866 | Q40: 0.866 | R40: 0.858 | S40: 0.89 | T40: 0.908 | U40: 0.88 | V40: 0.905 | W40: 0.922 | X40: 0.928 | Y40: 0.937 | Z40: 0.959 | AA40: 0.957 | AB40: 0.957 | AC40: 0.958 | AD40: 0.972 | AE40: 0.976 | AF40: 0.971 | AG40: 0.95 | AH40: 0.969 | AI40: 0.967 | AJ40: 0.973
A41: Belgium | B41: 0.951 | C41: 0.947 | D41: 0.951 | E41: 0.961 | F41: 0.947 | G41: 0.949 | H41: 0.951 | I41: 0.955 | J41: 0.951 | K41: 0.961 | L41: 0.96 | M41: 0.964 | N41: 0.968 | O41: 0.975 | P41: 0.985 | Q41: 0.989 | R41: 0.988 | S41: 0.99 | T41: 0.993 | U41: 0.966 | V41: 0.984 | W41: 0.978 | X41: 0.962 | Y41: 0.984 | Z41: 0.984 | AA41: 0.985 | AB41: 0.985 | AC41: 0.978 | AD41: 0.974 | AE41: 0.985 | AF41: 0.992 | AG41: 0.989 | AH41: 0.993 | AI41: 0.991 | AJ41: 0.994
A42: Canada | B42: 0.85 | C42: 0.841 | D42: 0.849 | E42: 0.835 | F42: 0.819 | G42: 0.789 | H42: 0.789 | I42: 0.79 | J42: 0.799 | K42: 0.768 | L42: 0.791 | M42: 0.808 | N42: 0.801 | O42: 0.802 | P42: 0.833 | Q42: 0.849 | R42: 0.856 | S42: 0.855 | T42: 0.877 | U42: 0.865 | V42: 0.877 | W42: 0.876 | X42: 0.877 | Y42: 0.881 | Z42: 0.883 | AA42: 0.877 | AB42: 0.873 | AC42: 0.887 | AD42: 0.885 | AE42: 0.879 | AF42: 0.888 | AG42: 0.897 | AH42: 0.902 | AI42: 0.908 | AJ42: 0.907
A43: Czech Republic | B43: … | C43: … | D43: … | E43: … | F43: … | G43: … | H43: … | I43: … | J43: … | K43: … | L43: … | M43: … | N43: … | O43: … | P43: … | Q43: … | R43: … | S43: 0.871 | T43: 0.89 | U43: 0.837 | V43: 0.813 | W43: 0.797 | X43: 0.806 | Y43: 0.785 | Z43: 0.781 | AA43: 0.836 | AB43: 0.848 | AC43: 0.858 | AD43: 0.864 | AE43: 0.897 | AF43: 0.885 | AG43: 0.913 | AH43: 0.96 | AI43: 0.982 | AJ43: 0.986
A44: Denmark | B44: … | C44: … | D44: … | E44: … | F44: … | G44: … | H44: … | I44: … | J44: … | K44: … | L44: 1 | M44: 1 | N44: 1 | O44: 0.927 | P44: 0.955 | Q44: 0.971 | R44: 0.975 | S44: 0.985 | T44: 0.989 | U44: 0.955 | V44: 0.847 | W44: 0.854 | X44: 0.87 | Y44: 0.904 | Z44: 0.915 | AA44: 0.939 | AB44: 0.957 | AC44: 0.985 | AD44: 0.998 | AE44: 0.999 | AF44: 0.999 | AG44: 0.984 | AH44: 0.982 | AI44: 0.98 | AJ44: 0.963
A45: Finland | B45: 0.701 | C45: 0.72 | D45: 0.724 | E45: 0.658 | F45: 0.635 | G45: 0.678 | H45: 0.748 | I45: 0.77 | J45: 0.797 | K45: 0.848 | L45: 0.83 | M45: 0.855 | N45: 0.856 | O45: 0.855 | P45: 0.907 | Q45: 0.922 | R45: 0.906 | S45: 0.913 | T45: 0.942 | U45: 0.93 | V45: 0.944 | W45: 0.87 | X45: 0.896 | Y45: 0.853 | Z45: 0.847 | AA45: 0.826 | AB45: 0.825 | AC45: 0.857 | AD45: 0.849 | AE45: 0.899 | AF45: 0.941 | AG45: 0.965 | AH45: 0.977 | AI45: 0.961 | AJ45: 0.979
A46: France | B46: 1 | C46: 1 | D46: 1 | E46: 0.999 | F46: 0.999 | G46: 0.998 | H46: 0.998 | I46: 0.983 | J46: 0.976 | K46: 0.984 | L46: 0.988 | M46: 0.987 | N46: 0.993 | O46: 0.996 | P46: 0.997 | Q46: 0.984 | R46: 0.978 | S46: 0.981 | T46: 0.983 | U46: 0.979 | V46: 0.969 | W46: 0.967 | X46: 0.961 | Y46: 0.968 | Z46: 0.97 | AA46: 0.972 | AB46: 0.969 | AC46: 0.961 | AD46: 0.963 | AE46: 0.975 | AF46: 0.976 | AG46: 0.963 | AH46: 0.962 | AI46: 0.972 | AJ46: 0.972
A47: Germany | B47: 1 | C47: 1 | D47: 1 | E47: 1 | F47: 1 | G47: 1 | H47: 1 | I47: 1 | J47: 1 | K47: 1 | L47: 1 | M47: 1 | N47: 0.999 | O47: 0.998 | P47: 0.995 | Q47: 0.994 | R47: 0.989 | S47: 0.99 | T47: 0.991 | U47: 0.99 | V47: 0.987 | W47: 0.992 | X47: 0.977 | Y47: 0.963 | Z47: 0.964 | AA47: 0.959 | AB47: 0.949 | AC47: 0.945 | AD47: 0.942 | AE47: 0.949 | AF47: 0.955 | AG47: 0.959 | AH47: 0.97 | AI47: 0.981 | AJ47: 0.989
A48: Greece | B48: … | C48: … | D48: … | E48: … | F48: … | G48: … | H48: 1 | I48: 1 | J48: 1 | K48: 1 | L48: 1 | M48: 1 | N48: 1 | O48: 1 | P48: 1 | Q48: 1 | R48: 1 | S48: 1 | T48: 1 | U48: 0.981 | V48: 0.986 | W48: 0.985 | X48: 0.985 | Y48: 0.974 | Z48: 0.988 | AA48: 0.987 | AB48: 0.986 | AC48: 0.992 | AD48: 1 | AE48: 1 | AF48: 1 | AG48: 1 | AH48: 1 | AI48: 1 | AJ48: 1
A49: Ireland | B49: 1 | C49: 1 | D49: 1 | E49: 1 | F49: 1 | G49: 1 | H49: 1 | I49: 1 | J49: 1 | K49: 1 | L49: 1 | M49: 1 | N49: 1 | O49: 1 | P49: 1 | Q49: 1 | R49: 1 | S49: 1 | T49: 1 | U49: 1 | V49: 0.954 | W49: 0.992 | X49: 0.998 | Y49: 0.997 | Z49: 0.999 | AA49: 0.98 | AB49: 0.993 | AC49: 0.997 | AD49: 0.997 | AE49: 0.996 | AF49: 1 | AG49: 0.985 | AH49: 0.988 | AI49: 1 | AJ49: 1
A50: Italy | B50: 0.988 | C50: 0.989 | D50: 0.989 | E50: 0.989 | F50: 0.979 | G50: 0.975 | H50: 0.972 | I50: 0.968 | J50: 0.965 | K50: 0.965 | L50: 0.961 | M50: 0.952 | N50: 0.95 | O50: 0.95 | P50: 0.951 | Q50: 0.952 | R50: 0.948 | S50: 0.961 | T50: 0.967 | U50: 0.972 | V50: 0.975 | W50: 0.973 | X50: 0.976 | Y50: 0.981 | Z50: 0.985 | AA50: 0.985 | AB50: 0.99 | AC50: 0.993 | AD50: 0.995 | AE50: 0.996 | AF50: 0.993 | AG50: 0.993 | AH50: 0.991 | AI50: 0.991 | AJ50: 0.993
A51: Japan | B51: … | C51: … | D51: … | E51: … | F51: … | G51: … | H51: … | I51: … | J51: … | K51: … | L51: … | M51: … | N51: … | O51: … | P51: … | Q51: … | R51: … | S51: … | T51: … | U51: … | V51: … | W51: … | X51: … | Y51: 1 | Z51: 1 | AA51: 0.999 | AB51: 0.999 | AC51: 0.999 | AD51: 0.999 | AE51: 0.999 | AF51: 0.999 | AG51: 0.999 | AH51: 0.999 | AI51: 0.999 | AJ51: 0.999
A52: Korea | B52: … | C52: … | D52: … | E52: … | F52: … | G52: … | H52: … | I52: … | J52: … | K52: … | L52: … | M52: … | N52: … | O52: 0.955 | P52: 0.966 | Q52: 0.975 | R52: 0.978 | S52: 0.98 | T52: 0.982 | U52: 0.986 | V52: 0.981 | W52: 0.984 | X52: 0.985 | Y52: 0.987 | Z52: 0.988 | AA52: 0.99 | AB52: 0.99 | AC52: 0.991 | AD52: 0.99 | AE52: 0.989 | AF52: 0.99 | AG52: 0.99 | AH52: 0.988 | AI52: 0.988 | AJ52: 0.989
A53: Netherlands | B53: 1 | C53: 1 | D53: 1 | E53: 1 | F53: 1 | G53: 1 | H53: 1 | I53: 1 | J53: 1 | K53: 1 | L53: 1 | M53: 1 | N53: 1 | O53: 1 | P53: 1 | Q53: 1 | R53: 1 | S53: 1 | T53: 1 | U53: 0.957 | V53: 0.981 | W53: 0.982 | X53: 0.976 | Y53: 0.943 | Z53: 0.978 | AA53: 0.979 | AB53: 0.985 | AC53: 0.984 | AD53: 0.997 | AE53: 0.991 | AF53: 0.997 | AG53: 0.999 | AH53: 0.999 | AI53: 0.967 | AJ53: 0.987
A54: New Zealand | B54: … | C54: … | D54: … | E54: … | F54: … | G54: … | H54: … | I54: … | J54: … | K54: … | L54: … | M54: … | N54: … | O54: … | P54: … | Q54: … | R54: … | S54: … | T54: … | U54: … | V54: … | W54: … | X54: … | Y54: … | Z54: … | AA54: … | AB54: … | AC54: … | AD54: … | AE54: … | AF54: … | AG54: … | AH54: … | AI54: … | AJ54: …
A55: Norway | B55: … | C55: … | D55: … | E55: … | F55: … | G55: … | H55: … | I55: … | J55: … | K55: … | L55: … | M55: … | N55: … | O55: … | P55: … | Q55: … | R55: 1 | S55: 1 | T55: 1 | U55: 1 | V55: 1 | W55: 1 | X55: 1 | Y55: 1 | Z55: 1 | AA55: 1 | AB55: 1 | AC55: 1 | AD55: 1 | AE55: 1 | AF55: 1 | AG55: 1 | AH55: 1 | AI55: 1 | AJ55: 1
A56: Portugal | B56: 0.991 | C56: 0.992 | D56: 0.993 | E56: 0.994 | F56: 0.951 | G56: 0.955 | H56: 0.944 | I56: 0.946 | J56: 0.931 | K56: 0.935 | L56: 0.906 | M56: 0.923 | N56: 0.91 | O56: 0.954 | P56: 0.979 | Q56: 0.992 | R56: 0.993 | S56: 0.995 | T56: 0.997 | U56: 0.991 | V56: 0.983 | W56: 0.984 | X56: 0.984 | Y56: 0.987 | Z56: 0.988 | AA56: 0.962 | AB56: 0.968 | AC56: 0.97 | AD56: 0.975 | AE56: 0.975 | AF56: 0.974 | AG56: 0.978 | AH56: 0.983 | AI56: 0.984 | AJ56: 0.986
A57: Slovenia | B57: … | C57: … | D57: … | E57: … | F57: … | G57: … | H57: … | I57: … | J57: … | K57: 0.895 | L57: 0.893 | M57: 0.896 | N57: 0.989 | O57: 0.994 | P57: 0.996 | Q57: 0.998 | R57: 0.999 | S57: 1 | T57: 1 | U57: 1 | V57: 1 | W57: 1 | X57: 1 | Y57: 0.899 | Z57: 0.817 | AA57: 0.72 | AB57: 0.707 | AC57: 0.776 | AD57: 0.863 | AE57: 0.904 | AF57: 0.947 | AG57: 0.96 | AH57: 0.959 | AI57: 0.98 | AJ57: 0.965
A58: Spain | B58: 0.985 | C58: 0.983 | D58: 0.984 | E58: 0.964 | F58: 0.966 | G58: 0.967 | H58: 0.967 | I58: 0.969 | J58: 0.967 | K58: 0.964 | L58: 0.958 | M58: 0.957 | N58: 0.955 | O58: 0.965 | P58: 0.97 | Q58: 0.976 | R58: 0.98 | S58: 0.983 | T58: 0.985 | U58: 0.981 | V58: 0.981 | W58: 0.984 | X58: 0.988 | Y58: 0.994 | Z58: 0.995 | AA58: 0.996 | AB58: 0.996 | AC58: 0.996 | AD58: 0.997 | AE58: 0.999 | AF58: 0.999 | AG58: 0.999 | AH58: 0.999 | AI58: 0.999 | AJ58: 0.999
A59: Sweden | B59: … | C59: … | D59: … | E59: … | F59: … | G59: … | H59: … | I59: … | J59: … | K59: 0.707 | L59: 0.75 | M59: 0.771 | N59: 0.772 | O59: 0.795 | P59: 0.851 | Q59: 0.864 | R59: 0.868 | S59: 0.876 | T59: 0.876 | U59: 0.9 | V59: 0.827 | W59: 0.837 | X59: 0.871 | Y59: 0.87 | Z59: 0.798 | AA59: 0.768 | AB59: 0.74 | AC59: 0.735 | AD59: 0.749 | AE59: 0.757 | AF59: 0.786 | AG59: 0.81 | AH59: 0.847 | AI59: 0.864 | AJ59: 0.964
A60: Switzerland | B60: … | C60: … | D60: … | E60: … | F60: … | G60: … | H60: … | I60: … | J60: … | K60: … | L60: 1 | M60: 1 | N60: 1 | O60: 1 | P60: 1 | Q60: 1 | R60: 1 | S60: 1 | T60: 1 | U60: 1 | V60: 1 | W60: 1 | X60: 1 | Y60: 1 | Z60: 1 | AA60: 1 | AB60: 1 | AC60: 1 | AD60: 1 | AE60: 1 | AF60: 1 | AG60: 1 | AH60: 1 | AI60: 1 | AJ60: 1
A61: United Kingdom | B61: … | C61: … | D61: … | E61: … | F61: … | G61: … | H61: … | I61: … | J61: … | K61: 1 | L61: 1 | M61: 1 | N61: 1 | O61: 1 | P61: 1 | Q61: 1 | R61: 1 | S61: 1 | T61: 1 | U61: 1 | V61: 1 | W61: 1 | X61: 1 | Y61: 1 | Z61: 1 | AA61: 1 | AB61: 1 | AC61: 1 | AD61: 1 | AE61: 1 | AF61: 1 | AG61: 1 | AH61: 1 | AI61: 1 | AJ61: 1
A62: United States | B62: 1 | C62: 1 | D62: 1 | E62: 1 | F62: 1 | G62: 1 | H62: 1 | I62: 1 | J62: 1 | K62: 1 | L62: 1 | M62: 1 | N62: 1 | O62: 1 | P62: 1 | Q62: 1 | R62: 1 | S62: 1 | T62: 1 | U62: 1 | V62: 1 | W62: 1 | X62: 1 | Y62: 1 | Z62: 1 | AA62: 1 | AB62: 1 | AC62: 1 | AD62: 1 | AE62: 1 | AF62: 1 | AG62: 1 | AH62: 1 | AI62: 1 | AJ62: 1
A63: Cyprus | B63: … | C63: … | D63: … | E63: … | F63: … | G63: … | H63: … | I63: … | J63: … | K63: … | L63: … | M63: … | N63: … | O63: … | P63: … | Q63: 1 | R63: 1 | S63: 1 | T63: 1 | U63: 1 | V63: 1 | W63: 1 | X63: 0.995 | Y63: 1 | Z63: 1 | AA63: 1 | AB63: 1 | AC63: 1 | AD63: 1 | AE63: 1 | AF63: 1 | AG63: 1 | AH63: 1 | AI63: 1 | AJ63: 1
A64: Estonia | B64: … | C64: … | D64: … | E64: … | F64: … | G64: … | H64: … | I64: … | J64: … | K64: … | L64: … | M64: … | N64: … | O64: … | P64: … | Q64: … | R64: … | S64: … | T64: … | U64: 1 | V64: 1 | W64: 1 | X64: 0.934 | Y64: 0.932 | Z64: 0.951 | AA64: 0.947 | AB64: 0.951 | AC64: 0.964 | AD64: 0.973 | AE64: 0.985 | AF64: 0.993 | AG64: 1 | AH64: 1 | AI64: 1 | AJ64: 1
A65: Iceland | B65: … | C65: … | D65: … | E65: … | F65: … | G65: … | H65: … | I65: … | J65: … | K65: … | L65: … | M65: … | N65: … | O65: … | P65: … | Q65: … | R65: … | S65: … | T65: … | U65: … | V65: … | W65: … | X65: … | Y65: … | Z65: … | AA65: … | AB65: … | AC65: … | AD65: … | AE65: … | AF65: … | AG65: … | AH65: … | AI65: … | AJ65: …
A66: Israel | B66: … | C66: … | D66: … | E66: … | F66: … | G66: … | H66: 0.695 | I66: 0.688 | J66: 0.68 | K66: 0.619 | L66: 0.624 | M66: 0.643 | N66: 0.674 | O66: 0.68 | P66: 0.736 | Q66: 0.755 | R66: 0.748 | S66: 0.759 | T66: 0.775 | U66: 0.808 | V66: 0.827 | W66: 0.835 | X66: 0.833 | Y66: 0.847 | Z66: 0.857 | AA66: 0.847 | AB66: 0.86 | AC66: 0.868 | AD66: 0.863 | AE66: 0.841 | AF66: 0.855 | AG66: 0.813 | AH66: 0.836 | AI66: 0.804 | AJ66: 0.785
A67: Latvia | B67: … | C67: … | D67: … | E67: … | F67: … | G67: … | H67: … | I67: … | J67: … | K67: … | L67: … | M67: … | N67: … | O67: … | P67: … | Q67: … | R67: … | S67: … | T67: … | U67: … | V67: … | W67: … | X67: 0.824 | Y67: 0.462 | Z67: 0.471 | AA67: 0.605 | AB67: 0.704 | AC67: 0.746 | AD67: 0.883 | AE67: 0.887 | AF67: 0.897 | AG67: 0.969 | AH67: 1 | AI67: 1 | AJ67: 1
A68: Lithuania | B68: … | C68: … | D68: … | E68: … | F68: … | G68: … | H68: … | I68: … | J68: … | K68: … | L68: … | M68: … | N68: … | O68: … | P68: … | Q68: … | R68: … | S68: … | T68: … | U68: … | V68: … | W68: … | X68: … | Y68: 0.487 | Z68: 0.491 | AA68: 0.513 | AB68: 0.604 | AC68: 0.603 | AD68: 0.712 | AE68: 0.694 | AF68: 0.73 | AG68: 0.879 | AH68: 0.935 | AI68: 1 | AJ68: 1
A69: Luxembourg | B69: 1 | C69: 1 | D69: 1 | E69: 1 | F69: 1 | G69: 1 | H69: 1 | I69: 1 | J69: 1 | K69: 1 | L69: 1 | M69: 1 | N69: 1 | O69: 1 | P69: 1 | Q69: 1 | R69: 1 | S69: 1 | T69: … | U69: 1 | V69: 1 | W69: 1 | X69: 1 | Y69: 1 | Z69: 1 | AA69: 1 | AB69: 1 | AC69: 1 | AD69: 1 | AE69: 1 | AF69: 1 | AG69: 1 | AH69: 1 | AI69: 1 | AJ69: 1
A70: Malta | B70: … | C70: … | D70: … | E70: … | F70: … | G70: … | H70: … | I70: … | J70: … | K70: … | L70: … | M70: … | N70: … | O70: … | P70: … | Q70: 1 | R70: 1 | S70: 1 | T70: 1 | U70: 1 | V70: 1 | W70: 1 | X70: 1 | Y70: 1 | Z70: 1 | AA70: 1 | AB70: 1 | AC70: 1 | AD70: 1 | AE70: 1 | AF70: 1 | AG70: 1 | AH70: 1 | AI70: 1 | AJ70: 1
A71: San Marino | B71: … | C71: … | D71: … | E71: … | F71: … | G71: … | H71: … | I71: … | J71: … | K71: … | L71: … | M71: … | N71: … | O71: … | P71: … | Q71: … | R71: … | S71: … | T71: … | U71: … | V71: … | W71: … | X71: … | Y71: … | Z71: … | AA71: … | AB71: … | AC71: … | AD71: … | AE71: … | AF71: … | AG71: … | AH71: … | AI71: … | AJ71: …
A72: Singapore | B72: 1 | C72: 1 | D72: 1 | E72: 1 | F72: 1 | G72: 1 | H72: 1 | I72: 1 | J72: 1 | K72: 1 | L72: 1 | M72: 1 | N72: 1 | O72: 1 | P72: 1 | Q72: 1 | R72: 1 | S72: 1 | T72: 1 | U72: 1 | V72: 1 | W72: 1 | X72: 1 | Y72: 1 | Z72: 1 | AA72: 1 | AB72: 1 | AC72: 1 | AD72: 1 | AE72: 1 | AF72: 1 | AG72: 1 | AH72: 1 | AI72: 1 | AJ72: 1
A73: Slovak Republic | B73: … | C73: … | D73: … | E73: … | F73: 1 | G73: 1 | H73: 1 | I73: 1 | J73: 1 | K73: 0.907 | L73: 0.903 | M73: 0.913 | N73: 0.959 | O73: 0.966 | P73: 1 | Q73: 1 | R73: 1 | S73: 1 | T73: 1 | U73: 1 | V73: 1 | W73: 1 | X73: 1 | Y73: 0.938 | Z73: 0.924 | AA73: 0.91 | AB73: 0.917 | AC73: 0.922 | AD73: 0.931 | AE73: 0.939 | AF73: 0.948 | AG73: 0.96 | AH73: 0.961 | AI73: 0.991 | AJ73: 0.995

Sheet Chart1

Sheet Chart2

Sheet Chart3

Sheet Chart4

Sheet Chart5
C3: Foreign Holdings of General Government Debt Securities (% of total) | S3: Domestic Central Bank Holdings of General Government Debt (% of total) | AI3: Domestic Bank Holdings of General Government Debt (% of total)
C37: Investorbase of General Government Debt at end-2024Q2 (% of total) | Z37: Foreign Holdings of General Government Debt Securities (% of total)
C56: Italy: Cumulative Net Purchases of General Government Debt by Investor Type, since end-2014 (in billion euros)
AA85: Source: Arslanalp and Tsuda (2014, updated)
AA86: Note: Coverage of debt is general government.

Sheet Table 1. Total
A1: Billion LC | B1: 2004Q1 | C1: 2004Q2 | D1: 2004Q3 | E1: 2004Q4 | F1: 2005Q1 | G1: 2005Q2 | H1: 2005Q3 | I1: 2005Q4 | J1: 2006Q1 | K1: 2006Q2 | L1: 2006Q3 | M1: 2006Q4 | N1: 2007Q1 | O1: 2007Q2 | P1: 2007Q3 | Q1: 2007Q4 | R1: 2008Q1 | S1: 2008Q2 | T1: 2008Q3 | U1: 2008Q4 | V1: 2009Q1 | W1: 2009Q2 | X1: 2009Q3 | Y1: 2009Q4 | Z1: 2010Q1 | AA1: 2010Q2 | AB1: 2010Q3 | AC1: 2010Q4 | AD1: 2011Q1 | AE1: 2011Q2 | AF1: 2011Q3 | AG1: 2011Q4 | AH1: 2012Q1 | AI1: 2012Q2 | AJ1: 2012Q3 | AK1: 2012Q4 | AL1: 2013Q1 | AM1: 2013Q2 | AN1: 2013Q3 | AO1: 2013Q4 | AP1: 2014Q1 | AQ1: 2014Q2 | AR1: 2014Q3 | AS1: 2014Q4 | AT1: 2015Q1 | AU1: 2015Q2 | AV1: 2015Q3 | AW1: 2015Q4 | AX1: 2016Q1 | AY1: 2016Q2 | AZ1: 2016Q3 | BA1: 2016Q4 | BB1: 2017Q1 | BC1: 2017Q2 | BD1: 2017Q3 | BE1: 2017Q4 | BF1: 2018Q1 | BG1: 2018Q2 | BH1: 2018Q3 | BI1: 2018Q4 | BJ1: 2019Q1 | BK1: 2019Q2 | BL1: 2019Q3 | BM1: 2019Q4 | BN1: 2020Q1 | BO1: 2020Q2 | BP1: 2020Q3 | BQ1: 2020Q4 | BR1: 2021Q1 | BS1: 2021Q2 | BT1: 2021Q3 | BU1: 2021Q4 | BV1: 2022Q1 | BW1: 2022Q2 | BX1: 2022Q3 | BY1: 2022Q4 | BZ1: 2023Q1 | CA1: 2023Q2 | CB1: 2023Q3 | CC1: 2023Q4 | CD1: 2024Q1 | CE1: 2024Q2
A2: Australia | B2: 99.676 | C2: 98.403 | D2: 99.463 | E2: 98.371 | F2: 99.262 | G2: 97.174 | H2: 96.75 | I2: 95.67 | J2: 94.639 | K2: 95.197 | L2: 95.502 | M2: 94.371 | N2: 92.995 | O2: 95.899 | P2: 101.526 | Q2: 101.98 | R2: 101.759 | S2: 114.656 | T2: 125.629 | U2: 139.455 | V2: 149.703 | W2: 162.82 | X2: 186.006 | Y2: 197.87 | Z2: 214.904 | AA2: 229.823 | AB2: 244.952 | AC2: 255.388 | AD2: 273.961 | AE2: 294.588 | AF2: 312.671 | AG2: 327.225 | AH2: 340.169 | AI2: 362.1 | AJ2: 377.627 | AK2: 381.15 | AL2: 389.338 | AM2: 397.307 | AN2: 419.97 | AO2: 439.698 | AP2: 458.971 | AQ2: 474.4 | AR2: 491.591 | AS2: 503.236 | AT2: 517.309 | AU2: 528.797 | AV2: 548.925 | AW2: 559.156 | AX2: 572.106 | AY2: 583.194 | AZ2: 605.526 | BA2: 621.359 | BB2: 639.415 | BC2: 661.452 | BD2: 672.99 | BE2: 682.677 | BF2: 691.91 | BG2: 699.904 | BH2: 704.69 | BI2: 711.617 | BJ2: 716.729 | BK2: 723.689 | BL2: 767.143 | BM2: 811.364 | BN2: 862.372 | BO2: 927.777 | BP2: 987.103 | BQ2: 1039.316 | BR2: 1077.043 | BS2: 1116.087 | BT2: 1158.795 | BU2: 1185.387 | BV2: 1204.273 | BW2: 1245.724 | BX2: 1262.723 | BY2: 1268.571 | BZ2: 1272.151 | CA2: 1280.691 | CB2: 1292.84 | CC2: 1313.062 | CD2: 1327.979 | CE2: 1342.26
A3: Austria | B3: 160.907 | C3: 169.004 | D3: 171.083 | E3: 158.546 | F3: 180.542 | G3: 188.732 | H3: 189.145 | I3: 175.204 | J3: 185.166 | K3: 193.804 | L3: 188.695 | M3: 181.304 | N3: 194.673 | O3: 203.676 | P3: 211.968 | Q3: 185.73 | R3: 192.286 | S3: 194.074 | T3: 196.299 | U3: 202.915 | V3: 212.254 | W3: 216.304 | X3: 212.632 | Y3: 231.173 | Z3: 233.802 | AA3: 243.545 | AB3: 245.742 | AC3: 245.985 | AD3: 249.003 | AE3: 251.625 | AF3: 253.177 | AG3: 256.876 | AH3: 261.102 | AI3: 265.899 | AJ3: 262.298 | AK3: 262.565 | AL3: 266.258 | AM3: 266.259 | AN3: 272.356 | AO3: 264.761 | AP3: 266.667 | AQ3: 272.153 | AR3: 268.627 | AS3: 281.289 | AT3: 285.598 | AU3: 291.121 | AV3: 293.893 | AW3: 292.874 | AX3: 298.885 | AY3: 298.679 | AZ3: 292.186 | BA3: 296.693 | BB3: 293.018 | BC3: 295.024 | BD3: 293.451 | BE3: 290.373 | BF3: 289.638 | BG3: 289.982 | BH3: 289.251 | BI3: 285.84 | BJ3: 283.587 | BK3: 282.42 | BL3: 281.964 | BM3: 280.975 | BN3: 289.889 | BO3: 316.714 | BP3: 301.253 | BQ3: 316.36 | BR3: 327.899 | BS3: 335.38 | BT3: 333.64 | BU3: 334.713 | BV3: 349.278 | BW3: 355.292 | BX3: 356.297 | BY3: 351.129 | BZ3: 368.358 | CA3: 366.445 | CB3: 369.771 | CC3: 371.729 | CD3: 383.713 | CE3: 394.78
A4: Belgium | B4: 300.65 | C4: 300.425 | D4: 301.26 | E4: 288.419 | F4: 303.644 | G4: 302.37 | H4: 301.465 | I4: 294.975 | J4: 308.285 | K4: 303.188 | L4: 305.313 | M4: 297.495 | N4: 307.996 | O4: 307.882 | P4: 314.884 | Q4: 300.064 | R4: 314.287 | S4: 313.627 | T4: 319.139 | U4: 327.683 | V4: 345.956 | W4: 348.259 | X4: 353.339 | Y4: 347.224 | Z4: 363.995 | AA4: 369.232 | AB4: 368.896 | AC4: 364.132 | AD4: 381.224 | AE4: 380.304 | AF4: 386.236 | AG4: 389.107 | AH4: 404.786 | AI4: 410.818 | AJ4: 409.816 | AK4: 404.752 | AL4: 424.187 | AM4: 428.112 | AN4: 425.528 | AO4: 414.476 | AP4: 435.366 | AQ4: 438.989 | AR4: 439.199 | AS4: 431.464 | AT4: 450.614 | AU4: 447.107 | AV4: 447.677 | AW4: 438.657 | AX4: 454.315 | AY4: 459.589 | AZ4: 459.416 | BA4: 451.818 | BB4: 462.501 | BC4: 460.32 | BD4: 467.005 | BE4: 454.282 | BF4: 470.162 | BG4: 470.341 | BH4: 470.854 | BI4: 459.669 | BJ4: 478.039 | BK4: 477.757 | BL4: 480.337 | BM4: 467.534 | BN4: 492.437 | BO4: 524.572 | BP4: 516.227 | BQ4: 515.53 | BR4: 537.648 | BS4: 546.836 | BT4: 548.476 | BU4: 548.775 | BV4: 562.336 | BW4: 573.411 | BX4: 574.685 | BY4: 578.336 | BZ4: 599.986 | CA4: 604.353 | CB4: 623.073 | CC4: 614.991 | CD4: 638.812 | CE4: 643.098
A5: Canada | B5: 880.724 | C5: 883.909 | D5: 873.044 | E5: 871.456 | F5: 890.399 | G5: 886.481 | H5: 877.303 | I5: 879.686 | J5: 889.035 | K5: 878.412 | L5: 884.12 | M5: 896.041 | N5: 905.663 | O5: 886.38 | P5: 884.206 | Q5: 890.993 | R5: 898.045 | S5: 922.084 | T5: 936.624 | U5: 1012.48 | V5: 1072.228 | W5: 1102.857 | X5: 1127.007 | Y5: 1154.954 | Z5: 1174.084 | AA5: 1200.435 | AB5: 1224.829 | AC5: 1244.007 | AD5: 1262.625 | AE5: 1297.987 | AF5: 1326.112 | AG5: 1336.885 | AH5: 1348.24 | AI5: 1381.622 | AJ5: 1411.519 | AK5: 1427.99 | AL5: 1458.25 | AM5: 1488.505 | AN5: 1505.539 | AO5: 1508.667 | AP5: 1478.927 | AQ5: 1511.281 | AR5: 1521.484 | AS5: 1531.127 | AT5: 1536.605 | AU5: 1576.778 | AV5: 1596.748 | AW5: 1635.591 | AX5: 1621.807 | AY5: 1647.967 | AZ5: 1670.525 | BA5: 1674.636 | BB5: 1674.138 | BC5: 1716.172 | BD5: 1729.31 | BE5: 1743.514 | BF5: 1759.423 | BG5: 1781.197 | BH5: 1791.141 | BI5: 1813.879 | BJ5: 1832.375 | BK5: 1854.537 | BL5: 1880.276 | BM5: 1882.054 | BN5: 1949.714 | BO5: 2320.38 | BP5: 2322.26 | BQ5: 2354.228 | BR5: 2379.389 | BS5: 2487.717 | BT5: 2517.975 | BU5: 2548.598 | BV5: 2556.904 | BW5: 2573.085 | BX5: 2600.78 | BY5: 2629.466 | BZ5: 2619.045 | CA5: 2663.74 | CB5: 2701.508 | CC5: 2753.325 | CD5: 2830.049 | CE5: 2844.784
A6: Czech Republic | B6: 855.269 | C6: 897.217 | D6: 890.021 | E6: 873.493 | F6: 889.827 | G6: 893.29 | H6: 896.782 | I6: 910.183 | J6: 925.265 | K6: 941.678 | L6: 951.943 | M6: 973.107 | N6: 981.971 | O6: 1023.622 | P6: 1003.559 | Q6: 1054.633 | R6: 1016.468 | S6: 1080.267 | T6: 1086.104 | U6: 1136.774 | V6: 1146.395 | W6: 1271.637 | X6: 1300.731 | Y6: 1319.002 | Z6: 1353.408 | AA6: 1380.654 | AB6: 1510.922 | AC6: 1480.097 | AD6: 1512.954 | AE6: 1522.434 | AF6: 1566.715 | AG6: 1613.65 | AH6: 1716.204 | AI6: 1741.311 | AJ6: 1799.427 | AK6: 1805.307 | AL6: 1846.559 | AM6: 1813.822 | AN6: 1792.178 | AO6: 1840.247 | AP6: 1838.037 | AQ6: 1817.985 | AR6: 1825.03 | AS6: 1818.888 | AT6: 1834.447 | AU6: 1828.043 | AV6: 1827.747 | AW6: 1836.047 | AX6: 1857.285 | AY6: 1850.404 | AZ6: 1811.968 | BA6: 1754.737 | BB6: 1924.121 | BC6: 1923.637 | BD6: 1739.428 | BE6: 1749.677 | BF6: 1833.227 | BG6: 1829.498 | BH6: 1778.581 | BI6: 1734.602 | BJ6: 1835.655 | BK6: 1816.617 | BL6: 1784.633 | BM6: 1740.263 | BN6: 1889.221 | BO6: 2265.056 | BP6: 2173.144 | BQ6: 2149.655 | BR6: 2512.533 | BS6: 2516.927 | BT6: 2433.296 | BU6: 2566.752 | BV6: 2684.15 | BW6: 2793.661 | BX6: 2983.299 | BY6: 2997.632 | BZ6: 3099.459 | CA6: 3150.74 | CB6: 3214.054 | CC6: 3234.002 | CD6: 3337.526 | CE6: 3321.079
A7: Denmark | B7: 734.514 | C7: 748.265 | D7: 763.534 | E7: 697.698 | F7: 711.12 | G7: 716.416 | H7: 666.667 | I7: 625.854 | J7: 587.151 | K7: 596.39 | L7: 599.933 | M7: 559.349 | N7: 552.834 | O7: 538.497 | P7: 539.315 | Q7: 513.925 | R7: 525.446 | S7: 517.16 | T7: 477.165 | U7: 643.16 | V7: 668.465 | W7: 710.757 | X7: 738.555 | Y7: 744.541 | Z7: 792.02 | AA7: 842.214 | AB7: 851.087 | AC7: 836.167 | AD7: 883.001 | AE7: 915.231 | AF7: 969.899 | AG7: 924.011 | AH7: 900.37 | AI7: 929.354 | AJ7: 951.003 | AK7: 922.073 | AL7: 911.287 | AM7: 939.572 | AN7: 955.047 | AO7: 924.613 | AP7: 938.919 | AQ7: 947.275 | AR7: 985.227 | AS7: 964.634 | AT7: 948.497 | AU7: 929.668 | AV7: 927.856 | AW7: 904.464 | AX7: 893.087 | AY7: 903.381 | AZ7: 888.137 | BA7: 876.165 | BB7: 865.039 | BC7: 872.494 | BD7: 879.496 | BE7: 879.176 | BF7: 875.738 | BG7: 868.928 | BH7: 875.683 | BI7: 864.633 | BJ7: 859.56 | BK7: 898.578 | BL7: 894.935 | BM7: 883.091 | BN7: 878.908 | BO7: 1053.216 | BP7: 1070.01 | BQ7: 1076.709 | BR7: 1052.763 | BS7: 1067.222 | BT7: 1076.573 | BU7: 1039.517 | BV7: 977.296 | BW7: 972.873 | BX7: 968.601 | BY7: 969.223 | BZ7: 968.562 | CA7: 984.187 | CB7: 968.875 | CC7: 942.073 | CD7: 939.741 | CE7: 949.202
A8: Finland | B8: 64.653 | C8: 66.964 | D8: 68.546 | E8: 71.335 | F8: 64.482 | G8: 66.02 | H8: 65.658 | I8: 69.397 | J8: 64.571 | K8: 68.98 | L8: 64.712 | M8: 69.532 | N8: 66.05 | O8: 67.806 | P8: 63.619 | Q8: 67.34 | R8: 64.941 | S8: 66.119 | T8: 59.673 | U8: 67.435 | V8: 75.054 | W8: 67.349 | X8: 73.894 | Y8: 80.2 | Z8: 83.731 | AA8: 88.437 | AB8: 89.197 | AC8: 94.286 | AD8: 93.409 | AE8: 93.844 | AF8: 98.361 | AG8: 102.829 | AH8: 104.698 | AI8: 112.013 | AJ8: 110.986 | AK8: 115.931 | AL8: 117.918 | AM8: 122.91 | AN8: 118.488 | AO8: 123.75 | AP8: 127.385 | AQ8: 130.374 | AR8: 129.445 | AS8: 133.42 | AT8: 136.221 | AU8: 140.052 | AV8: 137.492 | AW8: 144.537 | AX8: 146.794 | AY8: 142.416 | AZ8: 143.278 | BA8: 148.088 | BB8: 149.252 | BC8: 148.988 | BD8: 146.417 | BE8: 149.611 | BF8: 148.295 | BG8: 149.147 | BH8: 149.23 | BI8: 151.569 | BJ8: 152.115 | BK8: 157.991 | BL8: 155.885 | BM8: 155.827 | BN8: 168.13 | BO8: 176.815 | BP8: 172.098 | BQ8: 178.148 | BR8: 179.729 | BS8: 181.031 | BT8: 182.161 | BU8: 182.213 | BV8: 185.587 | BW8: 189.295 | BX8: 190.444 | BY8: 197.022 | BZ8: 198.704 | CA8: 203.719 | CB8: 204.267 | CC8: 210.866 | CD8: 213.613 | CE8: 219.326
A9: France | B9: 1082.162 | C9: 1116.597 | D9: 1121.826 | E9: 1134.347 | F9: 1157.643 | G9: 1176.901 | H9: 1183.009 | I9: 1201.471 | J9: 1211.122 | K9: 1208.338 | L9: 1220.495 | M9: 1207.313 | N9: 1244.509 | O9: 1277.565 | P9: 1280.495 | Q9: 1268.859 | R9: 1311.092 | S9: 1330.957 | T9: 1348.71 | U9: 1389.402 | V9: 1472.911 | W9: 1561.746 | X9: 1601.408 | Y9: 1627.182 | Z9: 1672.652 | AA9: 1730.926 | AB9: 1710.061 | AC9: 1722.172 | AD9: 1766.82 | AE9: 1811.73 | AF9: 1806.844 | AG9: 1830.136 | AH9: 1886.815 | AI9: 1922.56 | AJ9: 1902.116 | AK9: 1915.835 | AL9: 1953.497 | AM9: 1996.16 | AN9: 1985.416 | AO9: 2004.704 | AP9: 2048.244 | AQ9: 2067.433 | AR9: 2073.481 | AS9: 2070.579 | AT9: 2123.33 | AU9: 2140.448 | AV9: 2139.415 | AW9: 2134.071 | AX9: 2187.434 | AY9: 2217.127 | AZ9: 2205.921 | BA9: 2190.007 | BB9: 2255.429 | BC9: 2280.623 | BD9: 2278.085 | BE9: 2262.443 | BF9: 2290.69 | BG9: 2304.637 | BH9: 2324.805 | BI9: 2319.775 | BJ9: 2361.169 | BK9: 2377.938 | BL9: 2419.109 | BM9: 2386.133 | BN9: 2444.402 | BO9: 2643.359 | BP9: 2677.932 | BQ9: 2662.105 | BR9: 2750.648 | BS9: 2773.327 | BT9: 2844.625 | BU9: 2826.726 | BV9: 2913.352 | BW9: 2920.15 | BX9: 2961.255 | BY9: 2953.624 | BZ9: 3019.349 | CA9: 3053.172 | CB9: 3094.685 | CC9: 3101.376 | CD9: 3159.531 | CE9: 3228.411
A10: Germany | B10: 1462.632 | C10: 1472.314 | D10: 1490.971 | E10: 1489.671 | F10: 1517.899 | G10: 1532.092 | H10: 1553.598 | I10: 1561.021 | J10: 1580.419 | K10: 1592.812 | L10: 1610.704 | M10: 1610.904 | N10: 1613.974 | O10: 1632.336 | P10: 1612.995 | Q10: 1619.065 | R10: 1637.562 | S10: 1673.211 | T10: 1668.645 | U10: 1687.442 | V10: 1717.521 | W10: 1783.016 | X10: 1791.087 | Y10: 1804.696 | Z10: 1824.334 | AA10: 1865.708 | AB10: 1891.87 | AC10: 2119.242 | AD10: 2123.527 | AE10: 2135.62 | AF10: 2151.381 | AG10: 2155.876 | AH10: 2187.193 | AI10: 2233.428 | AJ10: 2228.223 | AK10: 2234.803 | AL10: 2225.062 | AM10: 2224.046 | AN10: 2204.903 | AO10: 2220.281 | AP10: 2210.656 | AQ10: 2217.507 | AR10: 2219.825 | AS10: 2224.56 | AT10: 2230.448 | AU10: 2195.535 | AV10: 2197.347 | AW10: 2197.474 | AX10: 2207.034 | AY10: 2210.629 | AZ10: 2204.211 | BA10: 2182.375 | BB10: 2158.507 | BC10: 2153.24 | BD10: 2148.063 | BE10: 2132.784 | BF10: 2111.454 | BG10: 2097.484 | BH10: 2098.484 | BI10: 2086.445 | BJ10: 2097.746 | BK10: 2088.853 | BL10: 2106.008 | BM10: 2075.012 | BN10: 2120.158 | BO10: 2290.476 | BP10: 2364.871 | BQ10: 2346.955 | BR10: 2376.264 | BS10: 2426.443 | BT10: 2460.511 | BU10: 2502.817 | BV10: 2504.867 | BW10: 2542.827 | BX10: 2556.375 | BY10: 2569.897 | BZ10: 2597.356 | CA10: 2595.555 | CB10: 2637.724 | CC10: 2631.777 | CD10: 2639.393 | CE10: 2635.103
A11: Greece | B11: 187.837 | C11: 198.359 | D11: 199.794 | E11: 199.282 | F11: 200.892 | G11: 209.098 | H11: 212.478 | I11: 213.976 | J11: 214.744 | K11: 219.515 | L11: 221.659 | M11: 225.73 | N11: 231.675 | O11: 233.269 | P11: 234.171 | Q11: 239.915 | R11: 244.548 | S11: 249.692 | T11: 256.238 | U11: 264.775 | V11: 281.548 | W11: 291.479 | X11: 296.231 | Y11: 301.062 | Z11: 311.473 | AA11: 315.853 | AB11: 328.594 | AC11: 330.57 | AD11: 342.265 | AE11: 342.057 | AF11: 348.354 | AG11: 356.235 | AH11: 281.499 | AI11: 301.787 | AJ11: 301.208 | AK11: 305.085 | AL11: 306.699 | AM11: 317.674 | AN11: 318.007 | AO11: 321.257 | AP11: 320.73 | AQ11: 322.814 | AR11: 319.934 | AS11: 321.631 | AT11: 305.365 | AU11: 303.982 | AV11: 305.909 | AW11: 314.987 | AX11: 312.362 | AY11: 318.532 | AZ11: 314.409 | BA11: 319.425 | BB11: 315.074 | BC11: 313.503 | BD11: 317.902 | BE11: 323.004 | BF11: 328.096 | BG11: 328.919 | BH11: 340.551 | BI11: 341.416 | BJ11: 344.105 | BK11: 342.259 | BL11: 341.026 | BM11: 339.201 | BN11: 338.126 | BO11: 342.371 | BP11: 346.219 | BQ11: 350.798 | BR11: 353.915 | BS11: 363.75 | BT11: 367.001 | BU11: 364.141 | BV11: 368.392 | BW11: 369.817 | BX11: 368.156 | BY11: 368.005 | BZ11: 366.941 | CA11: 369.346 | CB11: 371.483 | CC11: 369.099 | CD11: 368.365 | CE11: 369.442
A12: Ireland | B12: 45.007 | C12: 46.95 | D12: 45.983 | E12: 43.914 | F12: 45.065 | G12: 46.368 | H12: 46.181 | I12: 44.381 | J12: 46.406 | K12: 46.595 | L12: 45.532 | M12: 43.739 | N12: 45.165 | O12: 45.578 | P12: 53.525 | Q12: 47.195 | R12: 51.608 | S12: 60.022 | T12: 71.278 | U12: 79.621 | V12: 89.538 | W12: 101.277 | X12: 103.113 | Y12: 104.703 | Z12: 124.315 | AA12: 123.725 | AB12: 139.244 | AC12: 144.23 | AD12: 155.835 | AE12: 158.671 | AF12: 187.894 | AG12: 189.727 | AH12: 194.274 | AI12: 199.756 | AJ12: 210.431 | AK12: 210.026 | AL12: 218.269 | AM12: 218.381 | AN12: 218.447 | AO12: 215.242 | AP12: 215.004 | AQ12: 209.464 | AR12: 208.228 | AS12: 203.381 | AT12: 203.596 | AU12: 204.118 | AV12: 203.581 | AW12: 201.578 | AX12: 207.115 | AY12: 200.301 | AZ12: 202.374 | BA12: 200.635 | BB12: 208.61 | BC12: 211.248 | BD12: 210.921 | BE12: 201.262 | BF12: 210.229 | BG12: 214.517 | BH12: 215.71 | BI12: 205.848 | BJ12: 215.003 | BK12: 213.752 | BL12: 213.031 | BM12: 203.383 | BN12: 213.612 | BO12: 225.787 | BP12: 227.158 | BQ12: 217.885 | BR12: 230.416 | BS12: 234.525 | BT12: 236.299 | BU12: 236.127 | BV12: 235.182 | BW12: 236.61 | BX12: 236.11 | BY12: 224.78 | BZ12: 223.627 | CA12: 223.081 | CB12: 222.598 | CC12: 220.724 | CD12: 215.843 | CE12: 216.935
A13: Italy | B13: 1525.032 | C13: 1566.697 | D13: 1571.92 | E13: 1526.461 | F13: 1587.711 | G13: 1631.195 | H13: 1616.208 | I13: 1591.65 | J13: 1643.01 | K13: 1676.296 | L13: 1679.001 | M13: 1657.403 | N13: 1686.726 | O13: 1701.398 | P13: 1700.613 | Q13: 1677.725 | R13: 1726.516 | S13: 1729.968 | T13: 1725.417 | U13: 1738.851 | V13: 1817.404 | W13: 1829.546 | X13: 1865.427 | Y13: 1839.486 | Z13: 1876.412 | AA13: 1900.771 | AB13: 1921.134 | AC13: 1921.1 | AD13: 1943.974 | AE13: 1978.078 | AF13: 1960.179 | AG13: 1974.013 | AH13: 2022.083 | AI13: 2050.71 | AJ13: 2064.832 | AK13: 2055.338 | AL13: 2102.225 | AM13: 2143.668 | AN13: 2136.563 | AO13: 2137.088 | AP13: 2188.787 | AQ13: 2237.71 | AR13: 2203.711 | AS13: 2204.424 | AT13: 2254.491 | AU13: 2274.827 | AV13: 2263.185 | AW13: 2241.195 | AX13: 2300.107 | AY13: 2321.446 | AZ13: 2284.299 | BA13: 2287.84 | BB13: 2329.285 | BC13: 2359.327 | BD13: 2362.19 | BE13: 2332.197 | BF13: 2371.663 | BG13: 2391.931 | BH13: 2400.314 | BI13: 2384.631 | BJ13: 2419.833 | BK13: 2447.538 | BL13: 2444.797 | BM13: 2414.252 | BN13: 2438.649 | BO13: 2534.92 | BP13: 2588.277 | BQ13: 2576.629 | BR13: 2655.799 | BS13: 2701.453 | BT13: 2713.647 | BU13: 2685.173 | BV13: 2764.32 | BW13: 2777.098 | BX13: 2745.116 | BY13: 2762.908 | BZ13: 2795.989 | CA13: 2854.203 | CB13: 2849.722 | CC13: 2868.411 | CD13: 2899.178 | CE13: 2952.894
... A25: United States | B25: 6928.154 | C25: 7038.7 | D25: 7150.902 | E25: 7341.928 | F25: 7527.069 | G25: 7482.177 | H25: 7547.372 | I25: 7709.545 | J25: 7868.964 | K25: 7815.563 | L25: 7878.342 | M25: 7981.395 | N25: 8130.356 | O25: 8049.342 | P25: 8168.711 | Q25: 8348.06 | R25: 8564.356 | S25: 8541.495 | T25: 9104.797 | U25: 9758.877 | V25: 10252.947 | W25: 10604.534 | X25: 11019.045 | Y25: 11397.29 | Z25: 11877.537 | AA25: 12236.053 | AB25: 12639.959 | AC25: 13109.307 | AD25: 13349.314 | AE25: 13450.291 | AF25: 13857.337 | AG25: 14243.031 | AH25: 14626.868 | AI25: 14836.889 | AJ25: 15065.672 | AK25: 15409.728 | AL25: 15746.942 | AM25: 15638.473 | AN25: 15790.321 | AO25: 16205.501 | AP25: 16450.633 | AQ25: 16404.282 | AR25: 16624.752 | AS25: 16902.619 | AT25: 16981.977 | AU25: 16992.342 | AV25: 17103.829 | AW25: 17634.537 | AX25: 17876.495 | AY25: 17883.652 | AZ25: 18111.759 | BA25: 18445.034 | BB25: 18422.417 | BC25: 18392.059 | BD25: 18685.738 | BE25: 19024.482 | BF25: 19489.367 | BG25: 19520.503 | BH25: 19834.344 | BI25: 20264.329 | BJ25: 20487.999 | BK25: 20380.893 | BL25: 20925.094 | BM25: 21357.612 | BN25: 21795.03 | BO25: 24495.401 | BP25: 25035.031 | BQ25: 25710.881 | BR25: 26088.572 | BS25: 26250.635 | BT25: 26314.868 | BU25: 27130.289 | BV25: 27859.012 | BW25: 27761.005 | BX25: 28194.438 | BY25: 28499.037 | BZ25: 28813.732 | CA25: 29348.658 | CB25: 30288.047 | CC25: 31022.747 | CD25: 31622.327 | CE25: 32221.907
A27: o/w securities
A28: Billion LC | B28: =B1 -> 2004Q1 | C28: =C1 -> 2004Q2 | D28: =D1 -> 2004Q3 | E28: =E1 -> 2004Q4 | F28: =F1 -> 2005Q1 | G28: =G1 -> 2005Q2 | H28: =H1 -> 2005Q3 | I28: =I1 -> 2005Q4 | ... CE28: =CE1 -> 2024Q2
A29: Australia | B29: 99.638 | C29: 98.403 | D29: 99.463 | E29: 98.371 | F29: 99.262 | G29: 97.174 | H29: 96.75 | I29: 95.67 | J29: 94.639 | K29: 95.197 | L29: 95.502 | M29: 94.371 | N29: 92.995 | O29: 95.899 | P29: 101.526 | Q29: 101.98 | R29: 101.759 | S29: 114.656 | T29: 125.629 | U29: 139.455 | V29: 149.703 | W29: 162.82 | X29: 186.006 | Y29: 197.87 | Z29: 214.904 | AA29: 229.823 | AB29: 244.952 | AC29: 255.388 | AD29: 273.961 | AE29: 294.588 | AF29: 312.671 | AG29: 327.225 | AH29: 340.169 | AI29: 362.1 | AJ29: 377.627 | AK29: 381.15 | AL29: 389.338 | AM29: 397.307 | AN29: 419.97 | AO29: 434.312 | AP29: 453.729 | AQ29: 469.266 | AR29: 486.271 | AS29: 497.711 | AT29: 511.641 | AU29: 523.082 | AV29: 542.664 | AW29: 553.218 | AX29: 566.361 | AY29: 577.315 | AZ29: 599.792 | BA29: 615.559 | BB29: 633.85 | BC29: 655.797 | BD29: 667.358 | BE29: 676.981 | BF29: 685.967 | BG29: 693.963 | BH29: 698.624 | BI29: 705.462 | BJ29: 710.609 | BK29: 717.498 | BL29: 760.831 | BM29: 805.199 | BN29: 855.448 | BO29: 921.499 | BP29: 980.918 | BQ29: 1033.469 | BR29: 1071.217 | BS29: 1110.155 | BT29: 1140.311 | BU29: 1167.208 | BV29: 1186.085 | BW29: 1227.237 | BX29: 1243.973 | BY29: 1249.825 | BZ29: 1253.012 | CA29: 1261.472 | CB29: 1273.454 | CC29: 1294.333 | CD29: 1308.614 | CE29: 1322.895
A30: Austria | B30: 135.997 | C30: 142.153 | D30: 143.252 | E30: 131.107 | F30: 147.682 | G30: 153.001 | H30: 152.406 | I30: 139.566 | J30: 149.105 | K30: 157.447 | L30: 152.435 | M30: 146.197 | N30: 160.393 | O30: 168.829 | P30: 175.939 | Q30: 151.64 | R30: 159.585 | S30: 160.546 | T30: 161.626 | U30: 170.5 | V30: 178.937 | W30: 182.212 | X30: 178.488 | Y30: 187.164 | Z30: 188.739 | AA30: 196.348 | AB30: 197.924 | AC30: 200.274 | AD30: 203.709 | AE30: 205.026 | AF30: 207.588 | AG30: 207.805 | AH30: 211.339 | AI30: 216.048 | AJ30: 213.581 | AK30: 214.41 | AL30: 218.563 | AM30: 219 | AN30: 226.024 | AO30: 217.553 | AP30: 219.419 | AQ30: 224.953 | AR30: 220.6 | AS30: 227.322 | AT30: 231.109 | AU30: 237.333 | AV30: 234.76 | AW30: 236.963 | AX30: 242.754 | AY30: 244.381 | AZ30: 236.922 | BA30: 245.348 | BB30: 239.656 | BC30: 240.618 | BD30: 244.255 | BE30: 242.518 | BF30: 240.152 | BG30: 241.956 | BH30: 242.608 | BI30: 239.39 | BJ30: 237.663 | BK30: 235.68 | BL30: 235.783 | BM30: 235.198 | BN30: 243.413 | BO30: 267.041 | BP30: 253.823 | BQ30: 266.527 | BR30: 280.361 | BS30: 288.351 | BT30: 287.336 | BU30: 287.58 | BV30: 304.142 | BW30: 309.697 | BX30: 309.242 | BY30: 306.577 | BZ30: 323.488 | CA30: 321.936 | CB30: 325.61 | CC30: 326.772 | CD30: 339.459 | CE30: 350.772
A31: Belgium | B31: 259.216 | C31: 258.609 | D31: 260.118 | E31: 246.786 | F31: 254.863 | G31: 257.656 | H31: 256.043 | I31: 249.914 | J31: 262.389 | K31: 257.127 | L31: 256.19 | M31: 250.96 | N31: 253.341 | O31: 260.415 | P31: 266.805 | Q31: 253.418 | R31: 261.781 | S31: 265.656 | T31: 263.891 | U31: 279.149 | V31: 293.539 | W31: 297.006 | X31: 300.485 | Y31: 295.409 | Z31: 308.09 | AA31: 308.299 | AB31: 308.637 | AC31: 307.584 | AD31: 321.668 | AE31: 321.795 | AF31: 325.299 | AG31: 325.1 | AH31: 334.591 | AI31: 340.946 | AJ31: 340.553 | AK31: 335.748 | AL31: 348.752 | AM31: 352.91 | AN31: 347.788 | AO31: 341.042 | AP31: 349.663 | AQ31: 353.306 | AR31: 351.92 | AS31: 345.854 | AT31: 359.256 | AU31: 360.413 | AV31: 360.404 | AW31: 354.508 | AX31: 365.689 | AY31: 374.783 | AZ31: 374.684 | BA31: 367.241 | BB31: 377.823 | BC31: 378.021 | BD31: 384.12 | BE31: 373.006 | BF31: 386.117 | BG31: 385.725 | BH31: 389.554 | BI31: 379.097 | BJ31: 388.838 | BK31: 396.765 | BL31: 398.64 | BM31: 389.137 | BN31: 410.338 | BO31: 440.482 | BP31: 431.681 | BQ31: 436.605 | BR31: 454.497 | BS31: 461.909 | BT31: 462.908 | BU31: 463.477 | BV31: 472.783 | BW31: 484.082 | BX31: 484.101 | BY31: 490.5 | BZ31: 509.036 | CA31: 515.284 | CB31: 535.964 | CC31: 526.891 | CD31: 550.672 | CE31: 553.68
A32: Canada | B32: 776.701 | C32: 780.604 | D32: 769.513 | E32: 764.883 | F32: 784.349 | G32: 779.73 | H32: 770.468 | I32: 771.548 | J32: 781.902 | K32: 769.928 | L32: 770.162 | M32: 780.492 | N32: 790.186 | O32: 773.177 | P32: 766.895 | Q32: 768.919 | R32: 776.285 | S32: 807.781 | T32: 821.838 | U32: 895.578 | V32: 943.386 | W32: 974.427 | X32: 1005.654 | Y32: 1029.827 | Z32: 1041.512 | AA32: 1071.305 | AB32: 1093.125 | AC32: 1109.791 | AD32: 1123.247 | AE32: 1156.369 | AF32: 1183.086 | AG32: 1195.041 | AH32: 1200.345 | AI32: 1236.194 | AJ32: 1265.607 | AK32: 1277.22 | AL32: 1296.286 | AM32: 1328.737 | AN32: 1344.133 | AO32: 1345.079 | AP32: 1321.622 | AQ32: 1347.522 | AR32: 1359.159 | AS32: 1351.968 | AT32: 1357.688 | AU32: 1390.436 | AV32: 1414.543 | AW32: 1431.56 | AX32: 1431.947 | AY32: 1460.124 | AZ32: 1482.558 | BA32: 1487.179 | BB32: 1484.372 | BC32: 1520.866 | BD32: 1530.389 | BE32: 1530.18 | BF32: 1538.996 | BG32: 1563.315 | BH32: 1573.358 | BI32: 1590.521 | BJ32: 1601.123 | BK32: 1624.122 | BL32: 1638.886 | BM32: 1643.495 | BN32: 1699.947 | BO32: 2082.085 | BP32: 2083.001 | BQ32: 2118.427 | BR32: 2146.506 | BS32: 2251.413 | BT32: 2269.62 | BU32: 2296.971 | BV32: 2306.904 | BW32: 2320.617 | BX32: 2341.073 | BY32: 2358.029 | BZ32: 2345.328 | CA32: 2400.935 | CB32: 2427.604 | CC32: 2470.97 | CD32: 2549.433 | CE32: 2564.168
A33: Czech Republic | B33: 592.144 | C33: 653.072 | D33: 648.544 | E33: 642.88 | F33: 660.675 | G33: 674.387 | H33: 694.225 | I33: 710.353 | J33: 717.145 | K33: 737.434 | L33: 751.131 | M33: 799.292 | N33: 813.222 | O33: 854.873 | P33: 835.345 | Q33: 888.9 | R33: 858.496 | S33: 920.791 | T33: 913.453 | U33: 967.082 | V33: 974.128 | W33: 1088.419 | X33: 1112.022 | Y33: 1125.054 | Z33: 1152.175 | AA33: 1183.732 | AB33: 1314.657 | AC33: 1280.259 | AD33: 1320.669 | AE33: 1329.061 | AF33: 1370.018 | AG33: 1408.153 | AH33: 1516.708 | AI33: 1550.901 | AJ33: 1600.631 | AK33: 1603.476 | AL33: 1648.594 | AM33: 1619.763 | AN33: 1599.485 | AO33: 1639.103 | AP33: 1636.745 | AQ33: 1622.612 | AR33: 1630.407 | AS33: 1622.956 | AT33: 1639.146 | AU33: 1630.445 | AV33: 1637.072 | AW33: 1648.33 | AX33: 1674.401 | AY33: 1669.679 | AZ33: 1633.994 | BA33: 1592.89 | BB33: 1767.057 | BC33: 1769.43 | BD33: 1586.422 | BE33: 1602.348 | BF33: 1689.503 | BG33: 1633.961 | BH33: 1591.099 | BI33: 1553.697 | BJ33: 1670.459 | BK33: 1662.03 | BL33: 1636.946 | BM33: 1595.69 | BN33: 1711.439 | BO33: 2095.59 | BP33: 2026.629 | BQ33: 2011.756 | BR33: 2208.868 | BS33: 2295.069 | BT33: 2239.382 | BU33: 2357.797 | BV33: 2488.803 | BW33: 2505.392 | BX33: 2622.808 | BY33: 2597.134 | BZ33: 2797.101 | CA33: 2855.837 | CB33: 2923.382 | CC33: 2943.282 | CD33: 3049.772 | CE33: 3035.217
A34: Denmark | B34: 682.431 | C34: 694.852 | D34: 708.953 | E34: 640.588 | F34: 651.799 | G34: 656.358 | H34: 606.156 | I34: 566.437 | J34: 527.407 | K34: 532.024 | L34: 539.977 | M34: 498.396 | N34: 483.417 | O34: 468.794 | P34: 470.793 | Q34: 447.753 | R34: 457.878 | S34: 446.919 | T34: 411.58 | U34: 576.748 | V34: 600.58 | W34: 641.263 | X34: 670.928 | Y34: 677.827 | Z34: 723.762 | AA34: 768.993 | AB34: 781.366 | AC34: 767.89 | AD34: 812.221 | AE34: 840.876 | AF34: 897.478 | AG34: 848.516 | AH34: 824.936 | AI34: 852.017 | AJ34: 876.134 | AK34: 844.788 | AL34: 832.859 | AM34: 855.785 | AN34: 873.632 | AO34: 838.809 | AP34: 851.9 | AQ34: 855.677 | AR34: 896.479 | AS34: 869.12 | AT34: 864.475 | AU34: 838.174 | AV34: 839.132 | AW34: 808.763 | AX34: 804.574 | AY34: 809.455 | AZ34: 803.89 | BA34: 783.885 | BB34: 781.138 | BC34: 785.768 | BD34: 798.147 | BE34: 789.256 | BF34: 793.973 | BG34: 781.742 | BH34: 794.496 | BI34: 771.788 | BJ34: 775.529 | BK34: 805.636 | BL34: 806.08 | BM34: 788.576 | BN34: 788.333 | BO34: 961.377 | BP34: 986.757 | BQ34: 975.837 | BR34: 958.356 | BS34: 972.708 | BT34: 989.271 | BU34: 940.282 | BV34: 883.326 | BW34: 876.802 | BX34: 872.49 | BY34: 863.788 | BZ34: 873.305 | CA34: 882.539 | CB34: 873.905 | CC34: 845.821 | CD34: 851.981 | CE34: 861.61
A35: Finland | B35: 51.829 | C35: 54.098 | D35: 55.618 | E35: 56.285 | F35: 51.101 | G35: 51.758 | H35: 51.921 | I35: 54.105 | J35: 50.041 | K35: 54.462 | L35: 50.334 | M35: 54.883 | N35: 51.073 | O35: 52.645 | P35: 48.731 | Q35: 51.767 | R35: 49.432 | S35: 50.482 | T35: 44.266 | U35: 50.474 | V35: 57.004 | W35: 49.227 | X35: 56.052 | Y35: 61.309 | Z35: 64.16 | AA35: 68.099 | AB35: 69.16 | AC35: 72.83 | AD35: 71.499 | AE35: 71.148 | AF35: 74.422 | AG35: 76.465 | AH35: 75.663 | AI35: 81.505 | AJ35: 80.402 | AK35: 82.96 | AL35: 84.412 | AM35: 89.484 | AN35: 85.208 | AO35: 88.64 | AP35: 91.13 | AQ35: 94.546 | AR35: 93.417 | AS35: 95.418 | AT35: 95.2 | AU35: 100.772 | AV35: 98.248 | AW35: 102.071 | AX35: 104.461 | AY35: 100.753 | AZ35: 101.39 | BA35: 104.656 | BB35: 105.242 | BC35: 104.578 | BD35: 104.038 | BE35: 106.611 | BF35: 105.855 | BG35: 107.195 | BH35: 106.636 | BI35: 106.787 | BJ35: 106.239 | BK35: 111.605 | BL35: 108.893 | BM35: 108.145 | BN35: 119.853 | BO35: 127.216 | BP35: 123.003 | BQ35: 127.18 | BR35: 130.611 | BS35: 131.873 | BT35: 132.661 | BU35: 130.666 | BV35: 133.748 | BW35: 137.877 | BX35: 138.397 | BY35: 142.977 | BZ35: 146.42 | CA35: 151.067 | CB35: 151.553 | CC35: 154.731 | CD35: 160.882 | CE35: 166.173
A36: France | B36: 902.071 | C36: 931.332 | D36: 932.997 | E36: 949.313 | F36: 987.484 | G36: 1005.157 | H36: 1006.1 | I36: 1010.787 | J36: 1023.91 | K36: 1018.01 | L36: 1025.247 | M36: 1006.569 | N36: 1041.383 | O36: 1069.027 | P36: 1064.558 | Q36: 1049.592 | R36: 1088.261 | S36: 1102.6 | T36: 1117.601 | U36: 1164.697 | V36: 1258.321 | W36: 1342.571 | X36: 1377.485 | Y36: 1385.285 | Z36: 1424.286 | AA36: 1474.527 | AB36: 1463.206 | AC36: 1461.499 | AD36: 1509.921 | AE36: 1569.697 | AF36: 1560.035 | AG36: 1570.402 | AH36: 1625.583 | AI36: 1648.235 | AJ36: 1627.039 | AK36: 1617.438 | AL36: 1659.899 | AM36: 1700.845 | AN36: 1688.997 | AO36: 1692.248 | AP36: 1741.415 | AQ36: 1756.665 | AR36: 1756.683 | AS36: 1747.614 | AT36: 1805.444 | AU36: 1821.783 | AV36: 1819.142 | AW36: 1806.472 | AX36: 1875.163 | AY36: 1902.33 | AZ36: 1890.892 | BA36: 1866.739 | BB36: 1938.639 | BC36: 1960.112 | BD36: 1955.912 | BE36: 1938.073 | BF36: 1966.848 | BG36: 1981.068 | BH36: 2001.268 | BI36: 1991.718 | BJ36: 2035.488 | BK36: 2048.544 | BL36: 2087.216 | BM36: 2052.148 | BN36: 2112.651 | BO36: 2307.454 | BP36: 2343.121 | BQ36: 2321.854 | BR36: 2414.494 | BS36: 2442.79 | BT36: 2509.05 | BU36: 2480.561 | BV36: 2569.371 | BW36: 2570.611 | BX36: 2610.48 | BY36: 2608.925 | BZ36: 2678.795 | CA36: 2713.11 | CB36: 2755.066 | CC36: 2759.667 | CD36: 2819.25 | CE36: 2889.637
A37: Germany | B37: 955.463 | C37: 970.384 | D37: 986.16 | E37: 990.931 | F37: 1008.032 | G37: 1029.287 | H37: 1043.345 | I37: 1060.808 | J37: 1072.692 | K37: 1092.717 | L37: 1103.759 | M37: 1113.99 | N37: 1113.134 | O37: 1131.892 | P37: 1120.219 | Q37: 1144.781 | R37: 1141.395 | S37: 1170.756 | T37: 1180.493 | U37: 1185.837 | V37: 1221.955 | W37: 1288.397 | X37: 1287.132 | Y37: 1303.061 | Z37: 1326.685 | AA37: 1344.112 | AB37: 1365.477 | AC37: 1396.195 | AD37: 1419.061 | AE37: 1451.606 | AF37: 1466.222 | AG37: 1462.256 | AH37: 1496.634 | AI37: 1524.52 | AJ37: 1532.184 | AK37: 1548.351 | AL37: 1555.438 | AM37: 1550.074 | AN37: 1546.947 | AO37: 1556.535 | AP37: 1563.031 | AQ37: 1572.379 | AR37: 1577.612 | AS37: 1574.112 | AT37: 1569.519 | AU37: 1566.634 | AV37: 1568.843 | AW37: 1564.687 | AX37: 1560.438 | AY37: 1561.714 | AZ37: 1569.208 | BA37: 1553.586 | BB37: 1539.561 | BC37: 1540.875 | BD37: 1537.427 | BE37: 1533.252 | BF37: 1527.944 | BG37: 1520.659 | BH37: 1525.842 | BI37: 1508.732 | BJ37: 1524.852 | BK37: 1519.283 | BL37: 1534.73 | BM37: 1514.889 | BN37: 1556.381 | BO37: 1668.127 | BP37: 1773.51 | BQ37: 1769.987 | BR37: 1828.03 | BS37: 1873.071 | BT37: 1904.708 | BU37: 1925.787 | BV37: 1947.782 | BW37: 1972.91 | BX37: 1946.932 | BY37: 1969.045 | BZ37: 2026.741 | CA37: 2044.771 | CB37: 2088.153 | CC37: 2074.599 | CD37: 2093.861 | CE37: 2092.327
A38: Greece | B38: 146.319 | C38: 156.592 | D38: 158.832 | E38: 155.706 | F38: 157.609 | G38: 165.705 | H38: 171.409 | I38: 172.451 | J38: 175.656 | K38: 180.921 | L38: 182.875 | M38: 184.156 | N38: 193.783 | O38: 195.938 | P38: 197.892 | Q38: 201.108 | R38: 208.611 | S38: 213.542 | T38: 220.244 | U38: 225.449 | V38: 244.352 | W38: 255.587 | X38: 260.504 | Y38: 262.773 | Z38: 273.854 | AA38: 260.829 | AB38: 262.153 | AC38: 262.555 | AD38: 257.313 | AE38: 258.14 | AF38: 251.397 | AG38: 251.622 | AH38: 141.692 | AI38: 125.804 | AJ38: 125.79 | AK38: 93.432 | AL38: 89.322 | AM38: 81.965 | AN38: 79.069 | AO38: 79.194 | AP38: 77.36 | AQ38: 72.298 | AR38: 68.997 | AS38: 69.466 | AT38: 68.637 | AU38: 68.208 | AV38: 61.051 | AW38: 61.084 | AX38: 60.968 | AY38: 60.639 | AZ38: 57.864 | BA38: 57.162 | BB38: 56.732 | BC38: 56.193 | BD38: 53.765 | BE38: 54.938 | BF38: 56.529 | BG38: 56.902 | BH38: 54.404 | BI38: 52.882 | BJ38: 61.493 | BK38: 60.86 | BL38: 60.118 | BM38: 57.854 | BN38: 57.792 | BO38: 62.908 | BP38: 66.698 | BQ38: 67.187 | BR38: 74.814 | BS38: 80.252 | BT38: 82.748 | BU38: 80.998 | BV38: 84.043 | BW38: 86.678 | BX38: 85.211 | BY38: 85.246 | BZ38: 85.502 | CA38: 88.941 | CB38: 91.321 | CC38: 92.042 | CD38: 94.931 | CE38: 95.234
A39: Ireland | B39: 35.414 | C39: 37.355 | D39: 36.368 | E39: 34.229 | F39: 35.34 | G39: 36.617 | H39: 36.214 | I39: 34.078 | J39: 36.037 | K39: 36.15 | L39: 34.921 | M39: 33.596 | N39: 34.895 | O39: 35.779 | P39: 43.944 | Q39: 37.386 | R39: 41.676 | S39: 49.93 | T39: 60.561 | U39: 67.983 | V39: 76.996 | W39: 88.254 | X39: 89.87 | Y39: 91.535 | Z39: 99.804 | AA39: 96.055 | AB39: 101.925 | AC39: 96.381 | AD39: 91.503 | AE39: 89.742 | AF39: 96.251 | AG39: 94.031 | AH39: 87.665 | AI39: 84.932 | AJ39: 90.464 | AK39: 87.316 | AL39: 124.592 | AM39: 120.392 | AN39: 118.215 | AO39: 112.545 | AP39: 114.401 | AQ39: 116.034 | AR39: 115.432 | AS39: 119.072 | AT39: 128.53 | AU39: 128.837 | AV39: 128.199 | AW39: 125.761 | AX39: 131.436 | AY39: 124.321 | AZ39: 126.154 | BA39: 123.877 | BB39: 131.665 | BC39: 134.631 | BD39: 134.239 | BE39: 130.108 | BF39: 138.275 | BG39: 142.63 | BH39: 143.81 | BI39: 134.228 | BJ39: 142.565 | BK39: 141.538 | BL39: 141.819 | BM39: 133.025 | BN39: 143.178 | BO39: 155.021 | BP39: 156.769 | BQ39: 147.427 | BR39: 156.964 | BS39: 160.883 | BT39: 162.64 | BU39: 162.012 | BV39: 160.178 | BW39: 161.646 | BX39: 161.043 | BY39: 149.58 | BZ39: 148.271 | CA39: 147.698 | CB39: 147.349 | CC39: 147.315 | CD39: 143.264 | CE39: 144.159
A40: Italy | B40: 1215.161 | C40: 1244.512 | D40: 1250.022 | E40: 1208.994 | F40: 1265.606 | G40: 1295.807 | H40: 1277.814 | I40: 1246.606 | J40: 1278.03 | K40: 1315.096 | L40: 1313.501 | M40: 1286.08 | N40: 1315.518 | O40: 1346.837 | P40: 1346.787 | Q40: 1318.069 | R40: 1367.939 | S40: 1366.486 | T40: 1372.011 | U40: 1383.977 | V40: 1457.44 | W40: 1461.539 | X40: 1502.268 | Y40: 1470.17 | Z40: 1508.744 | AA40: 1531.853 | AB40: 1551.429 | AC40: 1548.479 | AD40: 1573.167 | AE40: 1603.533 | AF40: 1590.812 | AG40: 1604.147 | AH40: 1636.709 | AI40: 1657.755 | AJ40: 1666.559 | AK40: 1654.151 | AL40: 1701.46 | AM40: 1742.818 | AN40: 1737.895 | AO40: 1735.456 | AP40: 1781.728 | AQ40: 1829.308 | AR40: 1801.185 | AS40: 1793.442 | AT40: 1843.039 | AU40: 1857.644 | AV40: 1851.103 | AW40: 1823.508 | AX40: 1881.931 | AY40: 1910.247 | AZ40: 1872.89 | BA40: 1874.334 | BB40: 1912.749 | BC40: 1928.853 | BD40: 1928.304 | BE40: 1913.402 | BF40: 1947.927 | BG40: 1971.077 | BH40: 1981.784 | BI40: 1963.345 | BJ40: 1999.591 | BK40: 2028.639 | BL40: 2020.045 | BM40: 2009.277 | BN40: 2015.892 | BO40: 2120.155 | BP40: 2176.461 | BQ40: 2149.81 | BR40: 2216.149 | BS40: 2252.94 | BT40: 2253.069 | BU40: 2234.078 | BV40: 2291.336 | BW40: 2287.859 | BX40: 2264.474 | BY40: 2280.205 | BZ40: 2322.938 | CA40: 2379.967 | CB40: 2373.816 | CC40: 2378.078 | CD40: 2418.914 | CE40: 2474.267
... A52: United States | B52: 6928.154 | C52: 7038.7 | D52: 7150.902 | E52: 7341.928 | F52: 7527.069 | G52: 7482.177 | H52: 7547.372 | I52: 7709.545 | J52: 7868.964 | K52: 7815.563 | L52: 7878.342 | M52: 7981.395 | N52: 8130.356 | O52: 8049.342 | P52: 8168.711 | Q52: 8348.06 | R52: 8564.356 | S52: 8541.495 | T52: 9104.797 | U52: 9758.877 | V52: 10252.947 | W52: 10604.534 | X52: 11019.045 | Y52: 11397.29 | Z52: 11877.537 | AA52: 12236.053 | AB52: 12639.959 | AC52: 13109.307 | AD52: 13349.314 | AE52: 13450.291 | AF52: 13857.337 | AG52: 14243.031 | AH52: 14626.868 | AI52: 14836.889 | AJ52: 15065.672 | AK52: 15409.728 | AL52: 15746.942 | AM52: 15638.473 | AN52: 15790.321 | AO52: 16205.501 | AP52: 16450.633 | AQ52: 16404.282 | AR52: 16624.752 | AS52: 16902.619 | AT52: 16981.977 | AU52: 16992.342 | AV52: 17103.829 | AW52: 17634.537 | AX52: 17876.495 | AY52: 17883.652 | AZ52: 18111.759 | BA52: 18445.034 | BB52: 18422.417 | BC52: 18392.059 | BD52: 18685.738 | BE52: 19024.482 | BF52: 19489.367 | BG52: 19520.503 | BH52: 19834.344 | BI52: 20264.329 | BJ52: 20487.999 | BK52: 20380.893 | BL52: 20925.094 | BM52: 21357.612 | BN52: 21795.03 | BO52: 24495.401 | BP52: 25035.031 | BQ52: 25710.881 | BR52: 26088.572 | BS52: 26250.635 | BT52: 26314.868 | BU52: 27130.289 | BV52: 27859.012 | BW52: 27761.005 | BX52: 28194.438 | BY52: 28499.037 | BZ52: 28813.732 | CA52: 29348.658 | CB52: 30288.047 | CC52: 31022.747 | CD52: 31622.327 | CE52: 32221.907

Sheet Table 2. Foreign
A1: Billion LC | B1: 2004Q1 | C1: 2004Q2 | D1: 2004Q3 | E1: 2004Q4 | F1: 2005Q1 | G1: 2005Q2 | H1: 2005Q3 | I1: 2005Q4 | J1: 2006Q1 | K1: 2006Q2 | L1: 2006Q3 | M1: 2006Q4 | N1: 2007Q1 | O1: 2007Q2 | P1: 2007Q3 | Q1: 2007Q4 | R1: 2008Q1 | S1: 2008Q2 | T1: 2008Q3 | U1: 2008Q4 | V1: 2009Q1 | W1: 2009Q2 | X1: 2009Q3 | Y1: 2009Q4 | Z1: 2010Q1 | AA1: 2010Q2 | AB1: 2010Q3 | AC1: 2010Q4 | AD1: 2011Q1 | AE1: 2011Q2 | AF1: 2011Q3 | AG1: 2011Q4 | AH1: 2012Q1 | AI1: 2012Q2 | AJ1: 2012Q3 | AK1: 2012Q4 | AL1: 2013Q1 | AM1: 2013Q2 | AN1: 2013Q3 | AO1: 2013Q4 | AP1: 2014Q1 | AQ1: 2014Q2 | AR1: 2014Q3 | AS1: 2014Q4 | AT1: 2015Q1 | AU1: 2015Q2 | AV1: 2015Q3 | AW1: 2015Q4 | AX1: 2016Q1 | AY1: 2016Q2 | AZ1: 2016Q3 | BA1: 2016Q4 | BB1: 2017Q1 | BC1: 2017Q2 | BD1: 2017Q3 | BE1: 2017Q4 | BF1: 2018Q1 | BG1: 2018Q2 | BH1: 2018Q3 | BI1: 2018Q4 | BJ1: 2019Q1 | BK1: 2019Q2 | BL1: 2019Q3 | BM1: 2019Q4 | BN1: 2020Q1 | BO1: 2020Q2 | BP1: 2020Q3 | BQ1: 2020Q4 | BR1: 2021Q1 | BS1: 2021Q2 | BT1: 2021Q3 | BU1: 2021Q4 | BV1: 2022Q1 | BW1: 2022Q2 | BX1: 2022Q3 | BY1: 2022Q4 | BZ1: 2023Q1 | CA1: 2023Q2 | CB1: 2023Q3 | CC1: 2023Q4 | CD1: 2024Q1 | CE1: 2024Q2
A2: Australia | B2: 25.543 | C2: 27.242 | D2: 25.643 | E2: 27.535 | F2: 26.67 | G2: 28.889 | H2: 32.713 | I2: 31.699 | J2: 29.649 | K2: 31.736 | L2: 34.016 | M2: 31.193 | N2: 30.084 | O2: 32.895 | P2: 34.575 | Q2: 39.621 | R2: 37.674 | S2: 36.366 | T2: 36.097 | U2: 38.261 | V2: 35.562 | W2: 51.532 | X2: 63.544 | Y2: 71.158 | Z2: 88.211 | AA2: 100.52 | AB2: 113.555 | AC2: 123.528 | AD2: 129.289 | AE2: 134.285 | AF2: 151.485 | AG2: 167.797 | AH2: 180.576 | AI2: 179.484 | AJ2: 180.107 | AK2: 182.97 | AL2: 182.492 | AM2: 177.267 | AN2: 190.009 | AO2: 205.116 | AP2: 213.702 | AQ2: 221.746 | AR2: 229.392 | AS2: 234.477 | AT2: 243.379 | AU2: 244.454 | AV2: 253.773 | AW2: 255.694 | AX2: 256.837 | AY2: 252.478 | AZ2: 256.393 | BA2: 257.978 | BB2: 271.063 | BC2: 270.925 | BD2: 280.403 | BE2: 290.687 | BF2: 288.881 | BG2: 297.879 | BH2: 297.117 | BI2: 304.959 | BJ2: 302.73 | BK2: 301.788 | BL2: 313.339 | BM2: 321.615 | BN2: 300.739 | BO2: 324.475 | BP2: 389.025 | BQ2: 418.498 | BR2: 413.775 | BS2: 411.916 | BT2: 414.299 | BU2: 401.683 | BV2: 408.014 | BW2: 413.637 | BX2: 419.47 | BY2: 429.769 | BZ2: 436.417 | CA2: 418.367 | CB2: 423.303 | CC2: 440.803 | CD2: 455.269 | CE2: 434.755
A3: Austria | B3: 111.82 | C3: 117.275 | D3: 121.11 | E3: 113.284 | F3: 124.044 | G3: 137.291 | H3: 135.539 | I3: 125.263 | J3: 134.425 | K3: 143.305 | L3: 142.241 | M3: 139.635 | N3: 152.58 | O3: 161.432 | P3: 167.777 | Q3: 145.137 | R3: 151.006 | S3: 146.559 | T3: 149.264 | U3: 159.52 | V3: 163.952 | W3: 169.851 | X3: 170.831 | Y3: 175.875 | Z3: 179.923 | AA3: 190.527 | AB3: 187.509 | AC3: 185.271 | AD3: 182.613 | AE3: 186.163 | AF3: 195.082 | AG3: 192.996 | AH3: 193.426 | AI3: 201.596 | AJ3: 197.107 | AK3: 199.025 | AL3: 196.075 | AM3: 188.781 | AN3: 213.455 | AO3: 200.46 | AP3: 201.265 | AQ3: 208.71 | AR3: 202.236 | AS3: 214.497 | AT3: 222.865 | AU3: 217.498 | AV3: 214.801 | AW3: 216.167 | AX3: 223.892 | AY3: 223.788 | AZ3: 213.652 | BA3: 208.313 | BB3: 198.788 | BC3: 198.193 | BD3: 200.83 | BE3: 194.681 | BF3: 194.985 | BG3: 192.947 | BH3: 190.792 | BI3: 187.715 | BJ3: 191.274 | BK3: 193.85 | BL3: 195.41 | BM3: 187.452 | BN3: 191.904 | BO3: 210.009 | BP3: 195.186 | BQ3: 202.618 | BR3: 192.271 | BS3: 192.647 | BT3: 189.379 | BU3: 186.389 | BV3: 196.083 | BW3: 198.447 | BX3: 199.203 | BY3: 200.901 | BZ3: 211.502 | CA3: 207.428 | CB3: 215.048 | CC3: 222.671 | CD3: 231.801 | CE3: 236.643
A4: Belgium | B4: 153.757 | C4: 155.287 | D4: 156.583 | E4: 144.483 | F4: 155.307 | G4: 163.143 | H4: 160.139 | I4: 150.757 | J4: 160.118 | K4: 154.723 | L4: 158.399 | M4: 154.655 | N4: 170.81 | O4: 174.416 | P4: 180.599 | Q4: 171.689 | R4: 186.494 | S4: 194.434 | T4: 213.397 | U4: 191.069 | V4: 209.572 | W4: 198.927 | X4: 198.933 | Y4: 193.349 | Z4: 215.608 | AA4: 232.629 | AB4: 204.762 | AC4: 196.752 | AD4: 184.967 | AE4: 175.927 | AF4: 188.237 | AG4: 180.429 | AH4: 221.645 | AI4: 208.985 | AJ4: 200.936 | AK4: 187.177 | AL4: 206.76 | AM4: 208.891 | AN4: 213.48 | AO4: 203.771 | AP4: 233.349 | AQ4: 242.202 | AR4: 242.212 | AS4: 234.219 | AT4: 263.983 | AU4: 240.397 | AV4: 246.827 | AW4: 234.354 | AX4: 258.923 | AY4: 262.945 | AZ4: 262.895 | BA4: 242.333 | BB4: 248.503 | BC4: 245.661 | BD4: 250.723 | BE4: 235.301 | BF4: 254.917 | BG4: 253.428 | BH4: 255.235 | BI4: 244.141 | BJ4: 274.468 | BK4: 279.688 | BL4: 288.568 | BM4: 261.031 | BN4: 275.477 | BO4: 295.032 | BP4: 288.549 | BQ4: 283.314 | BR4: 284.024 | BS4: 285.139 | BT4: 291.566 | BU4: 284.152 | BV4: 293.952 | BW4: 298.207 | BX4: 306.799 | BY4: 308.9 | BZ4: 327.187 | CA4: 336.007 | CB4: 333.391 | CC4: 326.362 | CD4: 346.138 | CE4: 356.142
A5: Canada | B5: 176.248 | C5: 176.477 | D5: 169.641 | E5: 167.556 | F5: 168.924 | G5: 166.798 | H5: 159.644 | I5: 160.169 | J5: 163.936 | K5: 161.8 | L5: 158.46 | M5: 167.016 | N5: 167.934 | O5: 155.149 | P5: 147.973 | Q5: 146.306 | R5: 152.622 | S5: 159.432 | T5: 158.611 | U5: 171.943 | V5: 191.59 | W5: 204.155 | X5: 194.915 | Y5: 207.658 | Z5: 214.336 | AA5: 247.535 | AB5: 260.051 | AC5: 262.584 | AD5: 269.037 | AE5: 282.657 | AF5: 310.539 | AG5: 321.157 | AH5: 319.603 | AI5: 347.346 | AJ5: 357.322 | AK5: 370.606 | AL5: 375.511 | AM5: 376.375 | AN5: 374.051 | AO5: 364.288 | AP5: 359.004 | AQ5: 356.309 | AR5: 361.888 | AS5: 364.557 | AT5: 382.199 | AU5: 390.131 | AV5: 388.641 | AW5: 400.65 | AX5: 401.086 | AY5: 407.952 | AZ5: 420.155 | BA5: 422.496 | BB5: 414.98 | BC5: 429.49 | BD5: 444.411 | BE5: 457.383 | BF5: 441.264 | BG5: 435.642 | BH5: 431.116 | BI5: 443.929 | BJ5: 446.203 | BK5: 443.094 | BL5: 431.127 | BM5: 438.321 | BN5: 474.597 | BO5: 513.046 | BP5: 530.306 | BQ5: 550.371 | BR5: 537.961 | BS5: 585.802 | BT5: 600.055 | BU5: 638.793 | BV5: 630.459 | BW5: 608.674 | BX5: 606.3 | BY5: 626.362 | BZ5: 611.83 | CA5: 647.934 | CB5: 639.343 | CC5: 663.178 | CD5: 695.76 | CE5: 758.45
A6: Czech Republic | B6: 79.405 | C6: 133.563 | D6: 156.884 | E6: 178.892 | F6: 210.87 | G6: 227.328 | H6: 241.682 | I6: 244.388 | J6: 250.118 | K6: 252.392 | L6: 254.824 | M6: 264.785 | N6: 275.1 | O6: 290.939 | P6: 280.763 | Q6: 290.494 | R6: 285.185 | S6: 332.002 | T6: 345.038 | U6: 320.045 | V6: 312.041 | W6: 343.247 | X6: 348.232 | Y6: 394.471 | Z6: 395.678 | AA6: 397.533 | AB6: 458.274 | AC6: 454.746 | AD6: 445.904 | AE6: 464.762 | AF6: 475.069 | AG6: 489.918 | AH6: 532.058 | AI6: 532.018 | AJ6: 537.231 | AK6: 536.495 | AL6: 552.285 | AM6: 551.947 | AN6: 541.387 | AO6: 598.357 | AP6: 609.235 | AQ6: 563.932 | AR6: 566.41 | AS6: 539.187 | AT6: 572.701 | AU6: 585.503 | AV6: 654.584 | AW6: 677.453 | AX6: 733.469 | AY6: 765.194 | AZ6: 763.66 | BA6: 785.939 | BB6: 889.696 | BC6: 960.55 | BD6: 812.248 | BE6: 795.192 | BF6: 864.922 | BG6: 767.278 | BH6: 722.361 | BI6: 686.316 | BJ6: 753.978 | BK6: 763.945 | BL6: 737.685 | BM6: 667.951 | BN6: 747.61 | BO6: 849.702 | BP6: 789.318 | BQ6: 691.237 | BR6: 786.161 | BS6: 788.611 | BT6: 749.387 | BU6: 793.376 | BV6: 739.168 | BW6: 758.048 | BX6: 862.392 | BY6: 893.744 | BZ6: 846.343 | CA6: 856.947 | CB6: 869.253 | CC6: 850.046 | CD6: 1080.226 | CE6: 1261.382
